{"schemaVersion":1,"schools":{"12101246077192":[["2021-22",3,"fully_credentialed",58.82,10,17,21,{"reportingYear":"2024-25"}],["2021-22",3,"intern",0,0,17,21,{"reportingYear":"2024-25"}],["2021-22",3,"without_credentials_or_misassigned",0,0,17,21,{"reportingYear":"2024-25"}],["2021-22",3,"out_of_field",0,0,17,21,{"reportingYear":"2024-25"}],["2021-22",3,"unknown",41.18,7,17,21,{"reportingYear":"2024-25"}],["2022-23",3,"fully_credentialed",68.75,11,16,21,{"reportingYear":"2024-25"}],["2022-23",3,"intern",0,0,16,21,{"reportingYear":"2024-25"}],["2022-23",3,"without_credentials_or_misassigned",0,0,16,21,{"reportingYear":"2024-25"}],["2022-23",3,"out_of_field",6.25,1,16,21,{"reportingYear":"2024-25"}],["2022-23",3,"unknown",25,4,16,21,{"reportingYear":"2024-25"}],["2023-24",3,"fully_credentialed",83.33,15,18,21,{"reportingYear":"2024-25"}],["2023-24",3,"intern",0,0,18,21,{"reportingYear":"2024-25"}],["2023-24",3,"without_credentials_or_misassigned",0,0,18,21,{"reportingYear":"2024-25"}],["2023-24",3,"out_of_field",0,0,18,21,{"reportingYear":"2024-25"}],["2023-24",3,"unknown",16.67,3,18,21,{"reportingYear":"2024-25"}],["2022-23",0,"grade_other",6,null,null,22,{"classCounts":{"large":0,"medium":0,"small":11},"classSizeBands":{"large":"33+","medium":"21-32","small":"1-20"}}],["2023-24",0,"grade_k",2,null,null,22,{"classCounts":{"large":0,"medium":0,"small":2},"classSizeBands":{"large":"33+","medium":"21-32","small":"1-20"}}],["2023-24",0,"grade_6",4,null,null,22,{"classCounts":{"large":0,"medium":0,"small":1},"classSizeBands":{"large":"33+","medium":"21-32","small":"1-20"}}],["2023-24",0,"grade_other",5,null,null,22,{"classCounts":{"large":0,"medium":0,"small":10},"classSizeBands":{"large":"33+","medium":"21-32","small":"1-20"}}],["2024-25",0,"grade_2",3,null,null,22,{"classCounts":{"large":null,"medium":null,"small":1},"classSizeBands":{"large":"33+","medium":"21-32","small":"1-20"}}],["2024-25",0,"grade_6",3,null,null,22,{"classCounts":{"large":null,"medium":null,"small":2},"classSizeBands":{"large":"33+","medium":"21-32","small":"1-20"}}],["2024-25",0,"grade_other",6,null,null,22,{"classCounts":{"large":null,"medium":null,"small":9},"classSizeBands":{"large":"33+","medium":"21-32","small":"1-20"}}],["2024-25",2,"speech_language_hearing_specialist",3,null,null,25,{}],["2024-25",2,"other",1,null,null,25,{}],["2025-26",4,"total",9.7,null,18,26,{"charter":"N","dass":"Y","schoolGradeSpan":"GS_K12"}],["2025-26",4,"district",8.5,null,18,26,{"charter":"N","dass":"Y","schoolGradeSpan":"GS_K12"}],["2025-26",5,"total",18,null,18,26,{"charter":"N","dass":"Y","schoolGradeSpan":"GS_K12"}],["2025-26",5,"experienced",16,null,18,26,{"charter":"N","dass":"Y","schoolGradeSpan":"GS_K12"}],["2025-26",5,"inexperienced",2,null,18,26,{"charter":"N","dass":"Y","schoolGradeSpan":"GS_K12"}],["2025-26",5,"first_year",0,null,18,26,{"charter":"N","dass":"Y","schoolGradeSpan":"GS_K12"}],["2025-26",5,"second_year",2,null,18,26,{"charter":"N","dass":"Y","schoolGradeSpan":"GS_K12"}]],"12627376007728":[["2021-22",3,"fully_credentialed",100,8,8,21,{"reportingYear":"2024-25"}],["2021-22",3,"intern",0,0,8,21,{"reportingYear":"2024-25"}],["2021-22",3,"without_credentials_or_misassigned",0,0,8,21,{"reportingYear":"2024-25"}],["2021-22",3,"out_of_field",0,0,8,21,{"reportingYear":"2024-25"}],["2021-22",3,"unknown",0,0,8,21,{"reportingYear":"2024-25"}],["2022-23",3,"fully_credentialed",100,8,8,21,{"reportingYear":"2024-25"}],["2022-23",3,"intern",0,0,8,21,{"reportingYear":"2024-25"}],["2022-23",3,"without_credentials_or_misassigned",0,0,8,21,{"reportingYear":"2024-25"}],["2022-23",3,"out_of_field",0,0,8,21,{"reportingYear":"2024-25"}],["2022-23",3,"unknown",0,0,8,21,{"reportingYear":"2024-25"}],["2023-24",3,"fully_credentialed",80,8,10,21,{"reportingYear":"2024-25"}],["2023-24",3,"intern",0,0,10,21,{"reportingYear":"2024-25"}],["2023-24",3,"without_credentials_or_misassigned",20,2,10,21,{"reportingYear":"2024-25"}],["2023-24",3,"out_of_field",0,0,10,21,{"reportingYear":"2024-25"}],["2023-24",3,"unknown",0,0,10,21,{"reportingYear":"2024-25"}],["2022-23",0,"grade_k",17,null,null,22,{"classCounts":{"large":0,"medium":0,"small":1},"classSizeBands":{"large":"33+","medium":"21-32","small":"1-20"}}],["2022-23",0,"grade_2",20,null,null,22,{"classCounts":{"large":0,"medium":0,"small":1},"classSizeBands":{"large":"33+","medium":"21-32","small":"1-20"}}],["2022-23",0,"grade_4",20,null,null,22,{"classCounts":{"large":0,"medium":0,"small":1},"classSizeBands":{"large":"33+","medium":"21-32","small":"1-20"}}],["2022-23",0,"grade_5",19,null,null,22,{"classCounts":{"large":0,"medium":0,"small":1},"classSizeBands":{"large":"33+","medium":"21-32","small":"1-20"}}],["2022-23",0,"grade_6",8,null,null,22,{"classCounts":{"large":0,"medium":0,"small":2},"classSizeBands":{"large":"33+","medium":"21-32","small":"1-20"}}],["2022-23",0,"grade_other",19,null,null,22,{"classCounts":{"large":0,"medium":0,"small":2},"classSizeBands":{"large":"33+","medium":"21-32","small":"1-20"}}],["2023-24",0,"grade_k",16,null,null,22,{"classCounts":{"large":0,"medium":0,"small":1},"classSizeBands":{"large":"33+","medium":"21-32","small":"1-20"}}],["2023-24",0,"grade_1",17,null,null,22,{"classCounts":{"large":0,"medium":0,"small":1},"classSizeBands":{"large":"33+","medium":"21-32","small":"1-20"}}],["2023-24",0,"grade_2",16,null,null,22,{"classCounts":{"large":0,"medium":0,"small":1},"classSizeBands":{"large":"33+","medium":"21-32","small":"1-20"}}],["2023-24",0,"grade_3",21,null,null,22,{"classCounts":{"large":0,"medium":1,"small":0},"classSizeBands":{"large":"33+","medium":"21-32","small":"1-20"}}],["2023-24",0,"grade_4",16,null,null,22,{"classCounts":{"large":0,"medium":0,"small":1},"classSizeBands":{"large":"33+","medium":"21-32","small":"1-20"}}],["2023-24",0,"grade_5",16,null,null,22,{"classCounts":{"large":0,"medium":0,"small":1},"classSizeBands":{"large":"33+","medium":"21-32","small":"1-20"}}],["2023-24",0,"grade_6",24,null,null,22,{"classCounts":{"large":0,"medium":1,"small":0},"classSizeBands":{"large":"33+","medium":"21-32","small":"1-20"}}],["2024-25",0,"grade_k",16,null,null,22,{"classCounts":{"large":null,"medium":null,"small":1},"classSizeBands":{"large":"33+","medium":"21-32","small":"1-20"}}],["2024-25",0,"grade_1",16,null,null,22,{"classCounts":{"large":null,"medium":null,"small":1},"classSizeBands":{"large":"33+","medium":"21-32","small":"1-20"}}],["2024-25",0,"grade_2",16,null,null,22,{"classCounts":{"large":null,"medium":null,"small":1},"classSizeBands":{"large":"33+","medium":"21-32","small":"1-20"}}],["2024-25",0,"grade_3",15,null,null,22,{"classCounts":{"large":null,"medium":null,"small":1},"classSizeBands":{"large":"33+","medium":"21-32","small":"1-20"}}],["2024-25",0,"grade_4",22,null,null,22,{"classCounts":{"large":null,"medium":1,"small":null},"classSizeBands":{"large":"33+","medium":"21-32","small":"1-20"}}],["2024-25",0,"grade_5",15,null,null,22,{"classCounts":{"large":null,"medium":null,"small":1},"classSizeBands":{"large":"33+","medium":"21-32","small":"1-20"}}],["2024-25",0,"grade_6",17,null,null,22,{"classCounts":{"large":null,"medium":null,"small":1},"classSizeBands":{"large":"33+","medium":"21-32","small":"1-20"}}],["2024-25",1,"all_students",265,null,null,24,{}],["2024-25",2,"counselor",0.6,null,null,25,{}],["2024-25",2,"other",1.6,null,null,25,{}],["2025-26",4,"total",10.7,null,10,26,{"charter":"N","dass":"N","schoolGradeSpan":"GS_K12"}],["2025-26",4,"district",9.6,null,10,26,{"charter":"N","dass":"N","schoolGradeSpan":"GS_K12"}],["2025-26",5,"total",10,null,10,26,{"charter":"N","dass":"N","schoolGradeSpan":"GS_K12"}],["2025-26",5,"experienced",6,null,10,26,{"charter":"N","dass":"N","schoolGradeSpan":"GS_K12"}],["2025-26",5,"inexperienced",4,null,10,26,{"charter":"N","dass":"N","schoolGradeSpan":"GS_K12"}],["2025-26",5,"first_year",2,null,10,26,{"charter":"N","dass":"N","schoolGradeSpan":"GS_K12"}],["2025-26",5,"second_year",2,null,10,26,{"charter":"N","dass":"N","schoolGradeSpan":"GS_K12"}]],"12627456007736":[["2021-22",3,"fully_credentialed",100,16.1,16.1,21,{"reportingYear":"2024-25"}],["2021-22",3,"intern",0,0,16.1,21,{"reportingYear":"2024-25"}],["2021-22",3,"without_credentials_or_misassigned",0,0,16.1,21,{"reportingYear":"2024-25"}],["2021-22",3,"out_of_field",0,0,16.1,21,{"reportingYear":"2024-25"}],["2021-22",3,"unknown",0,0,16.1,21,{"reportingYear":"2024-25"}],["2022-23",3,"fully_credentialed",100,15.6,15.6,21,{"reportingYear":"2024-25"}],["2022-23",3,"intern",0,0,15.6,21,{"reportingYear":"2024-25"}],["2022-23",3,"without_credentials_or_misassigned",0,0,15.6,21,{"reportingYear":"2024-25"}],["2022-23",3,"out_of_field",0,0,15.6,21,{"reportingYear":"2024-25"}],["2022-23",3,"unknown",0,0,15.6,21,{"reportingYear":"2024-25"}],["2023-24",3,"fully_credentialed",98.71,14.5,14.6,21,{"reportingYear":"2024-25"}],["2023-24",3,"intern",0,0,14.6,21,{"reportingYear":"2024-25"}],["2023-24",3,"without_credentials_or_misassigned",0,0,14.6,21,{"reportingYear":"2024-25"}],["2023-24",3,"out_of_field",0,0,14.6,21,{"reportingYear":"2024-25"}],["2023-24",3,"unknown",1.36,0.2,14.6,21,{"reportingYear":"2024-25"}],["2022-23",0,"grade_3",22,null,null,22,{"classCounts":{"large":0,"medium":4,"small":0},"classSizeBands":{"large":"33+","medium":"21-32","small":"1-20"}}],["2022-23",0,"grade_4",22,null,null,22,{"classCounts":{"large":0,"medium":3,"small":0},"classSizeBands":{"large":"33+","medium":"21-32","small":"1-20"}}],["2022-23",0,"grade_5",21,null,null,22,{"classCounts":{"large":0,"medium":3,"small":1},"classSizeBands":{"large":"33+","medium":"21-32","small":"1-20"}}],["2022-23",0,"grade_6",22,null,null,22,{"classCounts":{"large":0,"medium":3,"small":1},"classSizeBands":{"large":"33+","medium":"21-32","small":"1-20"}}],["2022-23",0,"grade_other",160,null,null,22,{"classCounts":{"large":2,"medium":0,"small":0},"classSizeBands":{"large":"33+","medium":"21-32","small":"1-20"}}],["2023-24",0,"grade_3",21,null,null,22,{"classCounts":{"large":0,"medium":2,"small":1},"classSizeBands":{"large":"33+","medium":"21-32","small":"1-20"}}],["2023-24",0,"grade_4",23,null,null,22,{"classCounts":{"large":0,"medium":3,"small":1},"classSizeBands":{"large":"33+","medium":"21-32","small":"1-20"}}],["2023-24",0,"grade_5",21,null,null,22,{"classCounts":{"large":0,"medium":2,"small":1},"classSizeBands":{"large":"33+","medium":"21-32","small":"1-20"}}],["2023-24",0,"grade_6",27,null,null,22,{"classCounts":{"large":0,"medium":3,"small":0},"classSizeBands":{"large":"33+","medium":"21-32","small":"1-20"}}],["2023-24",0,"grade_other",116,null,null,22,{"classCounts":{"large":3,"medium":0,"small":0},"classSizeBands":{"large":"33+","medium":"21-32","small":"1-20"}}],["2024-25",0,"grade_3",14,null,null,22,{"classCounts":{"large":null,"medium":3,"small":2},"classSizeBands":{"large":"33+","medium":"21-32","small":"1-20"}}],["2024-25",0,"grade_4",17,null,null,22,{"classCounts":{"large":null,"medium":1,"small":3},"classSizeBands":{"large":"33+","medium":"21-32","small":"1-20"}}],["2024-25",0,"grade_5",18,null,null,22,{"classCounts":{"large":null,"medium":3,"small":2},"classSizeBands":{"large":"33+","medium":"21-32","small":"1-20"}}],["2024-25",0,"grade_6",15,null,null,22,{"classCounts":{"large":null,"medium":2,"small":2},"classSizeBands":{"large":"33+","medium":"21-32","small":"1-20"}}],["2024-25",0,"grade_other",144,null,null,22,{"classCounts":{"large":2,"medium":null,"small":null},"classSizeBands":{"large":"33+","medium":"21-32","small":"1-20"}}],["2024-25",2,"psychologist",0.5,null,null,25,{}],["2024-25",2,"social_worker",1,null,null,25,{}],["2024-25",2,"speech_language_hearing_specialist",1,null,null,25,{}],["2025-26",4,"total",12.2,null,18,26,{"charter":"N","dass":"N","schoolGradeSpan":"GS_K6"}],["2025-26",4,"district",9.3,null,18,26,{"charter":"N","dass":"N","schoolGradeSpan":"GS_K6"}],["2025-26",5,"total",18,null,18,26,{"charter":"N","dass":"N","schoolGradeSpan":"GS_K6"}],["2025-26",5,"experienced",14,null,18,26,{"charter":"N","dass":"N","schoolGradeSpan":"GS_K6"}],["2025-26",5,"inexperienced",4,null,18,26,{"charter":"N","dass":"N","schoolGradeSpan":"GS_K6"}],["2025-26",5,"first_year",4,null,18,26,{"charter":"N","dass":"N","schoolGradeSpan":"GS_K6"}],["2025-26",5,"second_year",0,null,18,26,{"charter":"N","dass":"N","schoolGradeSpan":"GS_K6"}]],"12627456007744":[["2021-22",3,"fully_credentialed",94.75,15.1,16,21,{"reportingYear":"2024-25"}],["2021-22",3,"intern",0,0,16,21,{"reportingYear":"2024-25"}],["2021-22",3,"without_credentials_or_misassigned",0,0,16,21,{"reportingYear":"2024-25"}],["2021-22",3,"out_of_field",3.13,0.5,16,21,{"reportingYear":"2024-25"}],["2021-22",3,"unknown",2.06,0.3,16,21,{"reportingYear":"2024-25"}],["2022-23",3,"fully_credentialed",92.66,12.5,13.4,21,{"reportingYear":"2024-25"}],["2022-23",3,"intern",0,0,13.4,21,{"reportingYear":"2024-25"}],["2022-23",3,"without_credentials_or_misassigned",0,0,13.4,21,{"reportingYear":"2024-25"}],["2022-23",3,"out_of_field",0,0,13.4,21,{"reportingYear":"2024-25"}],["2022-23",3,"unknown",7.34,0.9,13.4,21,{"reportingYear":"2024-25"}],["2023-24",3,"fully_credentialed",93.55,14.5,15.5,21,{"reportingYear":"2024-25"}],["2023-24",3,"intern",0,0,15.5,21,{"reportingYear":"2024-25"}],["2023-24",3,"without_credentials_or_misassigned",0,0,15.5,21,{"reportingYear":"2024-25"}],["2023-24",3,"out_of_field",0,0,15.5,21,{"reportingYear":"2024-25"}],["2023-24",3,"unknown",6.45,1,15.5,21,{"reportingYear":"2024-25"}],["2022-23",0,"grade_k",15,null,null,22,{"classCounts":{"large":0,"medium":1,"small":6},"classSizeBands":{"large":"33+","medium":"21-32","small":"1-20"}}],["2022-23",0,"grade_1",14,null,null,22,{"classCounts":{"large":0,"medium":0,"small":5},"classSizeBands":{"large":"33+","medium":"21-32","small":"1-20"}}],["2022-23",0,"grade_2",16,null,null,22,{"classCounts":{"large":0,"medium":2,"small":2},"classSizeBands":{"large":"33+","medium":"21-32","small":"1-20"}}],["2022-23",0,"grade_other",231,null,null,22,{"classCounts":{"large":1,"medium":0,"small":0},"classSizeBands":{"large":"33+","medium":"21-32","small":"1-20"}}],["2023-24",0,"grade_k",14,null,null,22,{"classCounts":{"large":0,"medium":1,"small":5},"classSizeBands":{"large":"33+","medium":"21-32","small":"1-20"}}],["2023-24",0,"grade_1",15,null,null,22,{"classCounts":{"large":0,"medium":0,"small":5},"classSizeBands":{"large":"33+","medium":"21-32","small":"1-20"}}],["2023-24",0,"grade_2",17,null,null,22,{"classCounts":{"large":0,"medium":3,"small":1},"classSizeBands":{"large":"33+","medium":"21-32","small":"1-20"}}],["2023-24",0,"grade_other",227,null,null,22,{"classCounts":{"large":1,"medium":0,"small":0},"classSizeBands":{"large":"33+","medium":"21-32","small":"1-20"}}],["2024-25",0,"grade_k",14,null,null,22,{"classCounts":{"large":null,"medium":null,"small":5},"classSizeBands":{"large":"33+","medium":"21-32","small":"1-20"}}],["2024-25",0,"grade_1",15,null,null,22,{"classCounts":{"large":null,"medium":null,"small":5},"classSizeBands":{"large":"33+","medium":"21-32","small":"1-20"}}],["2024-25",0,"grade_2",15,null,null,22,{"classCounts":{"large":null,"medium":null,"small":5},"classSizeBands":{"large":"33+","medium":"21-32","small":"1-20"}}],["2024-25",0,"grade_other",221,null,null,22,{"classCounts":{"large":1,"medium":null,"small":null},"classSizeBands":{"large":"33+","medium":"21-32","small":"1-20"}}],["2024-25",2,"psychologist",0.5,null,null,25,{}],["2024-25",2,"social_worker",1,null,null,25,{}],["2024-25",2,"speech_language_hearing_specialist",1,null,null,25,{}],["2025-26",4,"total",13,null,16,26,{"charter":"N","dass":"N","schoolGradeSpan":"GS_K6"}],["2025-26",4,"district",9.4,null,16,26,{"charter":"N","dass":"N","schoolGradeSpan":"GS_K6"}],["2025-26",5,"total",16,null,16,26,{"charter":"N","dass":"N","schoolGradeSpan":"GS_K6"}],["2025-26",5,"experienced",15,null,16,26,{"charter":"N","dass":"N","schoolGradeSpan":"GS_K6"}],["2025-26",5,"inexperienced",1,null,16,26,{"charter":"N","dass":"N","schoolGradeSpan":"GS_K6"}],["2025-26",5,"first_year",0,null,16,26,{"charter":"N","dass":"N","schoolGradeSpan":"GS_K6"}],["2025-26",5,"second_year",1,null,16,26,{"charter":"N","dass":"N","schoolGradeSpan":"GS_K6"}]],"12628100108688":[["2021-22",3,"fully_credentialed",64.57,5.2,8.1,21,{"reportingYear":"2024-25"}],["2021-22",3,"intern",0,0,8.1,21,{"reportingYear":"2024-25"}],["2021-22",3,"without_credentials_or_misassigned",12.84,1,8.1,21,{"reportingYear":"2024-25"}],["2021-22",3,"out_of_field",10.12,0.8,8.1,21,{"reportingYear":"2024-25"}],["2021-22",3,"unknown",12.22,0.9,8.1,21,{"reportingYear":"2024-25"}],["2022-23",3,"fully_credentialed",85.27,6,7.1,21,{"reportingYear":"2024-25"}],["2022-23",3,"intern",2.81,0.2,7.1,21,{"reportingYear":"2024-25"}],["2022-23",3,"without_credentials_or_misassigned",10.52,0.7,7.1,21,{"reportingYear":"2024-25"}],["2022-23",3,"out_of_field",0,0,7.1,21,{"reportingYear":"2024-25"}],["2022-23",3,"unknown",1.4,0.1,7.1,21,{"reportingYear":"2024-25"}],["2023-24",3,"fully_credentialed",97.36,7.3,7.5,21,{"reportingYear":"2024-25"}],["2023-24",3,"intern",0,0,7.5,21,{"reportingYear":"2024-25"}],["2023-24",3,"without_credentials_or_misassigned",0,0,7.5,21,{"reportingYear":"2024-25"}],["2023-24",3,"out_of_field",1.84,0.1,7.5,21,{"reportingYear":"2024-25"}],["2023-24",3,"unknown",0.66,0,7.5,21,{"reportingYear":"2024-25"}],["2022-23",0,"subject_english",13,null,null,23,{"classCounts":{"large":0,"medium":0,"small":10},"classSizeBands":{"large":"33+","medium":"23-32","small":"1-22"}}],["2022-23",0,"subject_mathematics",14,null,null,23,{"classCounts":{"large":0,"medium":3,"small":7},"classSizeBands":{"large":"33+","medium":"23-32","small":"1-22"}}],["2022-23",0,"subject_science",25,null,null,23,{"classCounts":{"large":0,"medium":4,"small":0},"classSizeBands":{"large":"33+","medium":"23-32","small":"1-22"}}],["2022-23",0,"subject_social_science",25,null,null,23,{"classCounts":{"large":1,"medium":1,"small":3},"classSizeBands":{"large":"33+","medium":"23-32","small":"1-22"}}],["2023-24",0,"subject_english",12,null,null,23,{"classCounts":{"large":null,"medium":1,"small":9},"classSizeBands":{"large":"33+","medium":"23-32","small":"1-22"}}],["2023-24",0,"subject_mathematics",19,null,null,23,{"classCounts":{"large":null,"medium":1,"small":6},"classSizeBands":{"large":"33+","medium":"23-32","small":"1-22"}}],["2023-24",0,"subject_science",23,null,null,23,{"classCounts":{"large":null,"medium":3,"small":1},"classSizeBands":{"large":"33+","medium":"23-32","small":"1-22"}}],["2023-24",0,"subject_social_science",25,null,null,23,{"classCounts":{"large":2,"medium":1,"small":2},"classSizeBands":{"large":"33+","medium":"23-32","small":"1-22"}}],["2024-25",0,"subject_english",13,null,null,23,{"classCounts":{"large":null,"medium":null,"small":8},"classSizeBands":{"large":"33+","medium":"23-32","small":"1-22"}}],["2024-25",0,"subject_mathematics",12,null,null,23,{"classCounts":{"large":null,"medium":null,"small":10},"classSizeBands":{"large":"33+","medium":"23-32","small":"1-22"}}],["2024-25",0,"subject_science",18,null,null,23,{"classCounts":{"large":null,"medium":null,"small":4},"classSizeBands":{"large":"33+","medium":"23-32","small":"1-22"}}],["2024-25",0,"subject_social_science",27,null,null,23,{"classCounts":{"large":1,"medium":2,"small":1},"classSizeBands":{"large":"33+","medium":"23-32","small":"1-22"}}],["2024-25",1,"all_students",165,null,null,24,{}],["2024-25",2,"counselor",1,null,null,25,{}],["2024-25",2,"other",3,null,null,25,{}],["2025-26",4,"total",11.8,null,8,26,{"charter":"N","dass":"N","schoolGradeSpan":"GS_912"}],["2025-26",4,"district",8.5,null,8,26,{"charter":"N","dass":"N","schoolGradeSpan":"GS_912"}],["2025-26",5,"total",8,null,8,26,{"charter":"N","dass":"N","schoolGradeSpan":"GS_912"}],["2025-26",5,"experienced",7,null,8,26,{"charter":"N","dass":"N","schoolGradeSpan":"GS_912"}],["2025-26",5,"inexperienced",1,null,8,26,{"charter":"N","dass":"N","schoolGradeSpan":"GS_912"}],["2025-26",5,"first_year",0,null,8,26,{"charter":"N","dass":"N","schoolGradeSpan":"GS_912"}],["2025-26",5,"second_year",1,null,8,26,{"charter":"N","dass":"N","schoolGradeSpan":"GS_912"}]],"12628101233352":[["2021-22",3,"fully_credentialed",32.58,1.3,3.9,21,{"reportingYear":"2024-25"}],["2021-22",3,"intern",0,0,3.9,21,{"reportingYear":"2024-25"}],["2021-22",3,"without_credentials_or_misassigned",8.52,0.3,3.9,21,{"reportingYear":"2024-25"}],["2021-22",3,"out_of_field",58.65,2.3,3.9,21,{"reportingYear":"2024-25"}],["2021-22",3,"unknown",0,0,3.9,21,{"reportingYear":"2024-25"}],["2022-23",3,"fully_credentialed",38.75,1.5,4,21,{"reportingYear":"2024-25"}],["2022-23",3,"intern",0,0,4,21,{"reportingYear":"2024-25"}],["2022-23",3,"without_credentials_or_misassigned",0,0,4,21,{"reportingYear":"2024-25"}],["2022-23",3,"out_of_field",61.25,2.4,4,21,{"reportingYear":"2024-25"}],["2022-23",3,"unknown",0,0,4,21,{"reportingYear":"2024-25"}],["2023-24",3,"fully_credentialed",30,1.2,4,21,{"reportingYear":"2024-25"}],["2023-24",3,"intern",0,0,4,21,{"reportingYear":"2024-25"}],["2023-24",3,"without_credentials_or_misassigned",0,0,4,21,{"reportingYear":"2024-25"}],["2023-24",3,"out_of_field",69.75,2.7,4,21,{"reportingYear":"2024-25"}],["2023-24",3,"unknown",0,0,4,21,{"reportingYear":"2024-25"}],["2022-23",0,"subject_english",3,null,null,23,{"classCounts":{"large":0,"medium":0,"small":12},"classSizeBands":{"large":"33+","medium":"23-32","small":"1-22"}}],["2022-23",0,"subject_mathematics",4,null,null,23,{"classCounts":{"large":0,"medium":0,"small":14},"classSizeBands":{"large":"33+","medium":"23-32","small":"1-22"}}],["2022-23",0,"subject_science",5,null,null,23,{"classCounts":{"large":0,"medium":0,"small":8},"classSizeBands":{"large":"33+","medium":"23-32","small":"1-22"}}],["2022-23",0,"subject_social_science",3,null,null,23,{"classCounts":{"large":0,"medium":0,"small":28},"classSizeBands":{"large":"33+","medium":"23-32","small":"1-22"}}],["2023-24",0,"subject_english",3,null,null,23,{"classCounts":{"large":null,"medium":null,"small":13},"classSizeBands":{"large":"33+","medium":"23-32","small":"1-22"}}],["2023-24",0,"subject_mathematics",3,null,null,23,{"classCounts":{"large":null,"medium":null,"small":13},"classSizeBands":{"large":"33+","medium":"23-32","small":"1-22"}}],["2023-24",0,"subject_science",2,null,null,23,{"classCounts":{"large":null,"medium":null,"small":10},"classSizeBands":{"large":"33+","medium":"23-32","small":"1-22"}}],["2023-24",0,"subject_social_science",2,null,null,23,{"classCounts":{"large":null,"medium":null,"small":27},"classSizeBands":{"large":"33+","medium":"23-32","small":"1-22"}}],["2024-25",0,"subject_english",11,null,null,23,{"classCounts":{"large":null,"medium":2,"small":4},"classSizeBands":{"large":"33+","medium":"23-32","small":"1-22"}}],["2024-25",0,"subject_mathematics",6,null,null,23,{"classCounts":{"large":null,"medium":1,"small":5},"classSizeBands":{"large":"33+","medium":"23-32","small":"1-22"}}],["2024-25",0,"subject_social_science",7,null,null,23,{"classCounts":{"large":null,"medium":2,"small":8},"classSizeBands":{"large":"33+","medium":"23-32","small":"1-22"}}],["2025-26",4,"total",21.5,null,4,26,{"charter":"N","dass":"Y","schoolGradeSpan":"GS_912"}],["2025-26",4,"district",14.8,null,4,26,{"charter":"N","dass":"Y","schoolGradeSpan":"GS_912"}],["2025-26",5,"total",4,null,4,26,{"charter":"N","dass":"Y","schoolGradeSpan":"GS_912"}],["2025-26",5,"experienced",4,null,4,26,{"charter":"N","dass":"Y","schoolGradeSpan":"GS_912"}],["2025-26",5,"inexperienced",0,null,4,26,{"charter":"N","dass":"Y","schoolGradeSpan":"GS_912"}],["2025-26",5,"first_year",0,null,4,26,{"charter":"N","dass":"Y","schoolGradeSpan":"GS_912"}],["2025-26",5,"second_year",0,null,4,26,{"charter":"N","dass":"Y","schoolGradeSpan":"GS_912"}]],"12629506008056":[["2021-22",3,"fully_credentialed",94.29,16.5,17.5,21,{"reportingYear":"2024-25"}],["2021-22",3,"intern",0,0,17.5,21,{"reportingYear":"2024-25"}],["2021-22",3,"without_credentials_or_misassigned",5.71,1,17.5,21,{"reportingYear":"2024-25"}],["2021-22",3,"out_of_field",0,0,17.5,21,{"reportingYear":"2024-25"}],["2021-22",3,"unknown",0,0,17.5,21,{"reportingYear":"2024-25"}],["2022-23",3,"fully_credentialed",80,12,15,21,{"reportingYear":"2024-25"}],["2022-23",3,"intern",0,0,15,21,{"reportingYear":"2024-25"}],["2022-23",3,"without_credentials_or_misassigned",19.93,2.9,15,21,{"reportingYear":"2024-25"}],["2022-23",3,"out_of_field",0,0,15,21,{"reportingYear":"2024-25"}],["2022-23",3,"unknown",0,0,15,21,{"reportingYear":"2024-25"}],["2023-24",3,"fully_credentialed",100,15,15,21,{"reportingYear":"2024-25"}],["2023-24",3,"intern",0,0,15,21,{"reportingYear":"2024-25"}],["2023-24",3,"without_credentials_or_misassigned",0,0,15,21,{"reportingYear":"2024-25"}],["2023-24",3,"out_of_field",0,0,15,21,{"reportingYear":"2024-25"}],["2023-24",3,"unknown",0,0,15,21,{"reportingYear":"2024-25"}],["2022-23",0,"grade_k",14,null,null,22,{"classCounts":{"large":0,"medium":1,"small":26},"classSizeBands":{"large":"33+","medium":"21-32","small":"1-20"}}],["2022-23",0,"grade_1",17,null,null,22,{"classCounts":{"large":0,"medium":0,"small":20},"classSizeBands":{"large":"33+","medium":"21-32","small":"1-20"}}],["2022-23",0,"grade_2",18,null,null,22,{"classCounts":{"large":0,"medium":0,"small":20},"classSizeBands":{"large":"33+","medium":"21-32","small":"1-20"}}],["2023-24",0,"grade_k",19,null,null,22,{"classCounts":{"large":0,"medium":12,"small":4},"classSizeBands":{"large":"33+","medium":"21-32","small":"1-20"}}],["2023-24",0,"grade_1",16,null,null,22,{"classCounts":{"large":0,"medium":12,"small":8},"classSizeBands":{"large":"33+","medium":"21-32","small":"1-20"}}],["2023-24",0,"grade_2",21,null,null,22,{"classCounts":{"large":0,"medium":12,"small":4},"classSizeBands":{"large":"33+","medium":"21-32","small":"1-20"}}],["2024-25",0,"grade_k",22,null,null,22,{"classCounts":{"large":null,"medium":2,"small":1},"classSizeBands":{"large":"33+","medium":"21-32","small":"1-20"}}],["2024-25",0,"grade_1",19,null,null,22,{"classCounts":{"large":null,"medium":1,"small":3},"classSizeBands":{"large":"33+","medium":"21-32","small":"1-20"}}],["2024-25",0,"grade_2",27,null,null,22,{"classCounts":{"large":null,"medium":1,"small":null},"classSizeBands":{"large":"33+","medium":"21-32","small":"1-20"}}],["2024-25",0,"grade_4",1,null,null,22,{"classCounts":{"large":null,"medium":null,"small":1},"classSizeBands":{"large":"33+","medium":"21-32","small":"1-20"}}],["2024-25",0,"grade_other",24,null,null,22,{"classCounts":{"large":null,"medium":3,"small":null},"classSizeBands":{"large":"33+","medium":"21-32","small":"1-20"}}],["2024-25",2,"speech_language_hearing_specialist",1,null,null,25,{}],["2025-26",4,"total",13.5,null,16,26,{"charter":"N","dass":"N","schoolGradeSpan":"GS_K6"}],["2025-26",4,"district",11.1,null,16,26,{"charter":"N","dass":"N","schoolGradeSpan":"GS_K6"}],["2025-26",5,"total",16,null,16,26,{"charter":"N","dass":"N","schoolGradeSpan":"GS_K6"}],["2025-26",5,"experienced",13,null,16,26,{"charter":"N","dass":"N","schoolGradeSpan":"GS_K6"}],["2025-26",5,"inexperienced",3,null,16,26,{"charter":"N","dass":"N","schoolGradeSpan":"GS_K6"}],["2025-26",5,"first_year",0,null,16,26,{"charter":"N","dass":"N","schoolGradeSpan":"GS_K6"}],["2025-26",5,"second_year",3,null,16,26,{"charter":"N","dass":"N","schoolGradeSpan":"GS_K6"}]],"12629506008064":[["2021-22",3,"fully_credentialed",89.65,10.1,11.3,21,{"reportingYear":"2024-25"}],["2021-22",3,"intern",0,0,11.3,21,{"reportingYear":"2024-25"}],["2021-22",3,"without_credentials_or_misassigned",0,0,11.3,21,{"reportingYear":"2024-25"}],["2021-22",3,"out_of_field",0,0,11.3,21,{"reportingYear":"2024-25"}],["2021-22",3,"unknown",10.27,1.1,11.3,21,{"reportingYear":"2024-25"}],["2022-23",3,"fully_credentialed",66.37,14.2,21.4,21,{"reportingYear":"2024-25"}],["2022-23",3,"intern",0,0,21.4,21,{"reportingYear":"2024-25"}],["2022-23",3,"without_credentials_or_misassigned",3.08,0.6,21.4,21,{"reportingYear":"2024-25"}],["2022-23",3,"out_of_field",0,0,21.4,21,{"reportingYear":"2024-25"}],["2022-23",3,"unknown",30.5,6.5,21.4,21,{"reportingYear":"2024-25"}],["2023-24",3,"fully_credentialed",65.16,10.2,15.7,21,{"reportingYear":"2024-25"}],["2023-24",3,"intern",0,0,15.7,21,{"reportingYear":"2024-25"}],["2023-24",3,"without_credentials_or_misassigned",0,0,15.7,21,{"reportingYear":"2024-25"}],["2023-24",3,"out_of_field",5.29,0.8,15.7,21,{"reportingYear":"2024-25"}],["2023-24",3,"unknown",29.49,4.6,15.7,21,{"reportingYear":"2024-25"}],["2022-23",0,"grade_6",18,null,null,22,{"classCounts":{"large":2,"medium":22,"small":23},"classSizeBands":{"large":"33+","medium":"21-32","small":"1-20"}}],["2023-24",0,"grade_6",14,null,null,22,{"classCounts":{"large":0,"medium":15,"small":27},"classSizeBands":{"large":"33+","medium":"21-32","small":"1-20"}}],["2024-25",0,"grade_6",11,null,null,22,{"classCounts":{"large":1,"medium":15,"small":46},"classSizeBands":{"large":"33+","medium":"21-32","small":"1-20"}}],["2022-23",0,"subject_english",25,null,null,23,{"classCounts":{"large":0,"medium":4,"small":1},"classSizeBands":{"large":"33+","medium":"23-32","small":"1-22"}}],["2022-23",0,"subject_mathematics",24,null,null,23,{"classCounts":{"large":0,"medium":8,"small":1},"classSizeBands":{"large":"33+","medium":"23-32","small":"1-22"}}],["2022-23",0,"subject_science",25,null,null,23,{"classCounts":{"large":0,"medium":8,"small":1},"classSizeBands":{"large":"33+","medium":"23-32","small":"1-22"}}],["2022-23",0,"subject_social_science",25,null,null,23,{"classCounts":{"large":0,"medium":8,"small":1},"classSizeBands":{"large":"33+","medium":"23-32","small":"1-22"}}],["2023-24",0,"subject_english",21,null,null,23,{"classCounts":{"large":null,"medium":4,"small":2},"classSizeBands":{"large":"33+","medium":"23-32","small":"1-22"}}],["2023-24",0,"subject_mathematics",26,null,null,23,{"classCounts":{"large":null,"medium":8,"small":1},"classSizeBands":{"large":"33+","medium":"23-32","small":"1-22"}}],["2023-24",0,"subject_science",24,null,null,23,{"classCounts":{"large":null,"medium":4,"small":1},"classSizeBands":{"large":"33+","medium":"23-32","small":"1-22"}}],["2023-24",0,"subject_social_science",26,null,null,23,{"classCounts":{"large":null,"medium":6,"small":3},"classSizeBands":{"large":"33+","medium":"23-32","small":"1-22"}}],["2024-25",0,"subject_english",22,null,null,23,{"classCounts":{"large":null,"medium":5,"small":4},"classSizeBands":{"large":"33+","medium":"23-32","small":"1-22"}}],["2024-25",0,"subject_mathematics",22,null,null,23,{"classCounts":{"large":null,"medium":6,"small":3},"classSizeBands":{"large":"33+","medium":"23-32","small":"1-22"}}],["2024-25",0,"subject_science",22,null,null,23,{"classCounts":{"large":null,"medium":6,"small":3},"classSizeBands":{"large":"33+","medium":"23-32","small":"1-22"}}],["2024-25",0,"subject_social_science",23,null,null,23,{"classCounts":{"large":null,"medium":6,"small":3},"classSizeBands":{"large":"33+","medium":"23-32","small":"1-22"}}],["2024-25",1,"all_students",338,null,null,24,{}],["2024-25",2,"counselor",1,null,null,25,{}],["2024-25",2,"psychologist",1,null,null,25,{}],["2025-26",4,"total",13.3,null,19,26,{"charter":"N","dass":"N","schoolGradeSpan":"GS_69"}],["2025-26",4,"district",8.7,null,19,26,{"charter":"N","dass":"N","schoolGradeSpan":"GS_69"}],["2025-26",5,"total",19,null,19,26,{"charter":"N","dass":"N","schoolGradeSpan":"GS_69"}],["2025-26",5,"experienced",17,null,19,26,{"charter":"N","dass":"N","schoolGradeSpan":"GS_69"}],["2025-26",5,"inexperienced",2,null,19,26,{"charter":"N","dass":"N","schoolGradeSpan":"GS_69"}],["2025-26",5,"first_year",0,null,19,26,{"charter":"N","dass":"N","schoolGradeSpan":"GS_69"}],["2025-26",5,"second_year",2,null,19,26,{"charter":"N","dass":"N","schoolGradeSpan":"GS_69"}]],"12629506008072":[["2021-22",3,"fully_credentialed",82.73,17,20.5,21,{"reportingYear":"2024-25"}],["2021-22",3,"intern",0,0,20.5,21,{"reportingYear":"2024-25"}],["2021-22",3,"without_credentials_or_misassigned",0,0,20.5,21,{"reportingYear":"2024-25"}],["2021-22",3,"out_of_field",0,0,20.5,21,{"reportingYear":"2024-25"}],["2021-22",3,"unknown",17.23,3.5,20.5,21,{"reportingYear":"2024-25"}],["2022-23",3,"fully_credentialed",90.63,14.5,16,21,{"reportingYear":"2024-25"}],["2022-23",3,"intern",0,0,16,21,{"reportingYear":"2024-25"}],["2022-23",3,"without_credentials_or_misassigned",3.13,0.5,16,21,{"reportingYear":"2024-25"}],["2022-23",3,"out_of_field",0,0,16,21,{"reportingYear":"2024-25"}],["2022-23",3,"unknown",6.25,1,16,21,{"reportingYear":"2024-25"}],["2023-24",3,"fully_credentialed",90.84,11.5,12.6,21,{"reportingYear":"2024-25"}],["2023-24",3,"intern",0,0,12.6,21,{"reportingYear":"2024-25"}],["2023-24",3,"without_credentials_or_misassigned",9.16,1.1,12.6,21,{"reportingYear":"2024-25"}],["2023-24",3,"out_of_field",0,0,12.6,21,{"reportingYear":"2024-25"}],["2023-24",3,"unknown",0,0,12.6,21,{"reportingYear":"2024-25"}],["2022-23",0,"grade_3",21,null,null,22,{"classCounts":{"large":0,"medium":17,"small":16},"classSizeBands":{"large":"33+","medium":"21-32","small":"1-20"}}],["2022-23",0,"grade_4",16,null,null,22,{"classCounts":{"large":0,"medium":0,"small":49},"classSizeBands":{"large":"33+","medium":"21-32","small":"1-20"}}],["2022-23",0,"grade_5",20,null,null,22,{"classCounts":{"large":0,"medium":24,"small":16},"classSizeBands":{"large":"33+","medium":"21-32","small":"1-20"}}],["2022-23",0,"grade_other",14,null,null,22,{"classCounts":{"large":0,"medium":1,"small":2},"classSizeBands":{"large":"33+","medium":"21-32","small":"1-20"}}],["2023-24",0,"grade_3",21,null,null,22,{"classCounts":{"large":0,"medium":24,"small":9},"classSizeBands":{"large":"33+","medium":"21-32","small":"1-20"}}],["2023-24",0,"grade_4",22,null,null,22,{"classCounts":{"large":0,"medium":33,"small":0},"classSizeBands":{"large":"33+","medium":"21-32","small":"1-20"}}],["2023-24",0,"grade_5",24,null,null,22,{"classCounts":{"large":0,"medium":33,"small":1},"classSizeBands":{"large":"33+","medium":"21-32","small":"1-20"}}],["2024-25",0,"grade_3",18,null,null,22,{"classCounts":{"large":null,"medium":null,"small":4},"classSizeBands":{"large":"33+","medium":"21-32","small":"1-20"}}],["2024-25",0,"grade_4",18,null,null,22,{"classCounts":{"large":null,"medium":2,"small":3},"classSizeBands":{"large":"33+","medium":"21-32","small":"1-20"}}],["2024-25",0,"grade_5",23,null,null,22,{"classCounts":{"large":null,"medium":2,"small":2},"classSizeBands":{"large":"33+","medium":"21-32","small":"1-20"}}],["2024-25",2,"psychologist",1,null,null,25,{}],["2025-26",4,"total",11.3,null,6,26,{"charter":"N","dass":"N","schoolGradeSpan":"GS_K6"}],["2025-26",4,"district",10.7,null,6,26,{"charter":"N","dass":"N","schoolGradeSpan":"GS_K6"}],["2025-26",5,"total",6,null,6,26,{"charter":"N","dass":"N","schoolGradeSpan":"GS_K6"}],["2025-26",5,"experienced",5,null,6,26,{"charter":"N","dass":"N","schoolGradeSpan":"GS_K6"}],["2025-26",5,"inexperienced",1,null,6,26,{"charter":"N","dass":"N","schoolGradeSpan":"GS_K6"}],["2025-26",5,"first_year",1,null,6,26,{"charter":"N","dass":"N","schoolGradeSpan":"GS_K6"}],["2025-26",5,"second_year",0,null,6,26,{"charter":"N","dass":"N","schoolGradeSpan":"GS_K6"}]],"12629686008080":[["2021-22",3,"fully_credentialed",100,2,2,21,{"reportingYear":"2024-25"}],["2021-22",3,"intern",0,0,2,21,{"reportingYear":"2024-25"}],["2021-22",3,"without_credentials_or_misassigned",0,0,2,21,{"reportingYear":"2024-25"}],["2021-22",3,"out_of_field",0,0,2,21,{"reportingYear":"2024-25"}],["2021-22",3,"unknown",0,0,2,21,{"reportingYear":"2024-25"}],["2022-23",3,"fully_credentialed",100,1.9,1.9,21,{"reportingYear":"2024-25"}],["2022-23",3,"intern",0,0,1.9,21,{"reportingYear":"2024-25"}],["2022-23",3,"without_credentials_or_misassigned",0,0,1.9,21,{"reportingYear":"2024-25"}],["2022-23",3,"out_of_field",0,0,1.9,21,{"reportingYear":"2024-25"}],["2022-23",3,"unknown",0,0,1.9,21,{"reportingYear":"2024-25"}],["2023-24",3,"fully_credentialed",100,0.9,0.9,21,{"reportingYear":"2024-25"}],["2023-24",3,"intern",0,0,0.9,21,{"reportingYear":"2024-25"}],["2023-24",3,"without_credentials_or_misassigned",0,0,0.9,21,{"reportingYear":"2024-25"}],["2023-24",3,"out_of_field",0,0,0.9,21,{"reportingYear":"2024-25"}],["2023-24",3,"unknown",0,0,0.9,21,{"reportingYear":"2024-25"}],["2022-23",0,"grade_k",3,null,null,22,{"classCounts":{"large":0,"medium":0,"small":1},"classSizeBands":{"large":"33+","medium":"21-32","small":"1-20"}}],["2022-23",0,"grade_1",2,null,null,22,{"classCounts":{"large":0,"medium":0,"small":1},"classSizeBands":{"large":"33+","medium":"21-32","small":"1-20"}}],["2022-23",0,"grade_3",1,null,null,22,{"classCounts":{"large":0,"medium":0,"small":1},"classSizeBands":{"large":"33+","medium":"21-32","small":"1-20"}}],["2022-23",0,"grade_5",1,null,null,22,{"classCounts":{"large":0,"medium":0,"small":1},"classSizeBands":{"large":"33+","medium":"21-32","small":"1-20"}}],["2023-24",0,"grade_k",1,null,null,22,{"classCounts":{"large":null,"medium":null,"small":1},"classSizeBands":{"large":"33+","medium":"21-32","small":"1-20"}}],["2023-24",0,"grade_1",2,null,null,22,{"classCounts":{"large":null,"medium":null,"small":1},"classSizeBands":{"large":"33+","medium":"21-32","small":"1-20"}}],["2023-24",0,"grade_2",2,null,null,22,{"classCounts":{"large":null,"medium":null,"small":1},"classSizeBands":{"large":"33+","medium":"21-32","small":"1-20"}}],["2023-24",0,"grade_4",1,null,null,22,{"classCounts":{"large":null,"medium":null,"small":1},"classSizeBands":{"large":"33+","medium":"21-32","small":"1-20"}}],["2023-24",0,"grade_6",1,null,null,22,{"classCounts":{"large":null,"medium":null,"small":1},"classSizeBands":{"large":"33+","medium":"21-32","small":"1-20"}}],["2024-25",0,"grade_k",1,null,null,22,{"classCounts":{"large":null,"medium":null,"small":1},"classSizeBands":{"large":"33+","medium":"21-32","small":"1-20"}}],["2024-25",0,"grade_1",1,null,null,22,{"classCounts":{"large":null,"medium":null,"small":1},"classSizeBands":{"large":"33+","medium":"21-32","small":"1-20"}}],["2024-25",0,"grade_2",1,null,null,22,{"classCounts":{"large":null,"medium":null,"small":1},"classSizeBands":{"large":"33+","medium":"21-32","small":"1-20"}}],["2024-25",0,"grade_3",1,null,null,22,{"classCounts":{"large":null,"medium":null,"small":1},"classSizeBands":{"large":"33+","medium":"21-32","small":"1-20"}}],["2024-25",1,"all_students",50,null,null,24,{}],["2024-25",2,"counselor",0.2,null,null,25,{}],["2025-26",4,"total",11.5,null,2,26,{"charter":"N","dass":"N","schoolGradeSpan":"GS_K12"}],["2025-26",4,"district",11.5,null,2,26,{"charter":"N","dass":"N","schoolGradeSpan":"GS_K12"}],["2025-26",5,"total",2,null,2,26,{"charter":"N","dass":"N","schoolGradeSpan":"GS_K12"}],["2025-26",5,"experienced",1,null,2,26,{"charter":"N","dass":"N","schoolGradeSpan":"GS_K12"}],["2025-26",5,"inexperienced",1,null,2,26,{"charter":"N","dass":"N","schoolGradeSpan":"GS_K12"}],["2025-26",5,"first_year",0,null,2,26,{"charter":"N","dass":"N","schoolGradeSpan":"GS_K12"}],["2025-26",5,"second_year",1,null,2,26,{"charter":"N","dass":"N","schoolGradeSpan":"GS_K12"}]],"12630400140376":[["2021-22",3,"fully_credentialed",45.5,0.9,2,21,{"reportingYear":"2024-25"}],["2021-22",3,"intern",0,0,2,21,{"reportingYear":"2024-25"}],["2021-22",3,"without_credentials_or_misassigned",54,1,2,21,{"reportingYear":"2024-25"}],["2021-22",3,"out_of_field",0,0,2,21,{"reportingYear":"2024-25"}],["2021-22",3,"unknown",0,0,2,21,{"reportingYear":"2024-25"}],["2022-23",3,"fully_credentialed",68.63,1.4,2,21,{"reportingYear":"2024-25"}],["2022-23",3,"intern",0,0,2,21,{"reportingYear":"2024-25"}],["2022-23",3,"without_credentials_or_misassigned",31.37,0.6,2,21,{"reportingYear":"2024-25"}],["2022-23",3,"out_of_field",0,0,2,21,{"reportingYear":"2024-25"}],["2022-23",3,"unknown",0,0,2,21,{"reportingYear":"2024-25"}],["2023-24",3,"fully_credentialed",50,1.5,3,21,{"reportingYear":"2024-25"}],["2023-24",3,"intern",0,0,3,21,{"reportingYear":"2024-25"}],["2023-24",3,"without_credentials_or_misassigned",50,1.5,3,21,{"reportingYear":"2024-25"}],["2023-24",3,"out_of_field",0,0,3,21,{"reportingYear":"2024-25"}],["2023-24",3,"unknown",0,0,3,21,{"reportingYear":"2024-25"}],["2022-23",0,"subject_english",1,null,null,23,{"classCounts":{"large":0,"medium":0,"small":5},"classSizeBands":{"large":"33+","medium":"23-32","small":"1-22"}}],["2022-23",0,"subject_social_science",2,null,null,23,{"classCounts":{"large":0,"medium":0,"small":1},"classSizeBands":{"large":"33+","medium":"23-32","small":"1-22"}}],["2023-24",0,"subject_english",2,null,null,23,{"classCounts":{"large":null,"medium":null,"small":4},"classSizeBands":{"large":"33+","medium":"23-32","small":"1-22"}}],["2023-24",0,"subject_mathematics",2,null,null,23,{"classCounts":{"large":null,"medium":null,"small":3},"classSizeBands":{"large":"33+","medium":"23-32","small":"1-22"}}],["2023-24",0,"subject_science",3,null,null,23,{"classCounts":{"large":null,"medium":null,"small":2},"classSizeBands":{"large":"33+","medium":"23-32","small":"1-22"}}],["2023-24",0,"subject_social_science",2,null,null,23,{"classCounts":{"large":null,"medium":null,"small":3},"classSizeBands":{"large":"33+","medium":"23-32","small":"1-22"}}],["2024-25",0,"subject_english",1,null,null,23,{"classCounts":{"large":null,"medium":null,"small":3},"classSizeBands":{"large":"33+","medium":"23-32","small":"1-22"}}],["2024-25",0,"subject_mathematics",4,null,null,23,{"classCounts":{"large":null,"medium":null,"small":1},"classSizeBands":{"large":"33+","medium":"23-32","small":"1-22"}}],["2024-25",0,"subject_science",2,null,null,23,{"classCounts":{"large":null,"medium":null,"small":1},"classSizeBands":{"large":"33+","medium":"23-32","small":"1-22"}}],["2024-25",0,"subject_social_science",2,null,null,23,{"classCounts":{"large":null,"medium":null,"small":2},"classSizeBands":{"large":"33+","medium":"23-32","small":"1-22"}}],["2025-26",4,"total",3.7,null,3,26,{"charter":"N","dass":"N","schoolGradeSpan":"GS_912"}],["2025-26",4,"district",3.7,null,3,26,{"charter":"N","dass":"N","schoolGradeSpan":"GS_912"}],["2025-26",5,"total",3,null,3,26,{"charter":"N","dass":"N","schoolGradeSpan":"GS_912"}],["2025-26",5,"experienced",2,null,3,26,{"charter":"N","dass":"N","schoolGradeSpan":"GS_912"}],["2025-26",5,"inexperienced",1,null,3,26,{"charter":"N","dass":"N","schoolGradeSpan":"GS_912"}],["2025-26",5,"first_year",1,null,3,26,{"charter":"N","dass":"N","schoolGradeSpan":"GS_912"}],["2025-26",5,"second_year",0,null,3,26,{"charter":"N","dass":"N","schoolGradeSpan":"GS_912"}]],"12755156057376":[["2021-22",3,"fully_credentialed",91.29,23.3,25.6,21,{"reportingYear":"2024-25"}],["2021-22",3,"intern",0,0,25.6,21,{"reportingYear":"2024-25"}],["2021-22",3,"without_credentials_or_misassigned",1.56,0.4,25.6,21,{"reportingYear":"2024-25"}],["2021-22",3,"out_of_field",1.29,0.3,25.6,21,{"reportingYear":"2024-25"}],["2021-22",3,"unknown",5.86,1.5,25.6,21,{"reportingYear":"2024-25"}],["2022-23",3,"fully_credentialed",89.61,21.8,24.3,21,{"reportingYear":"2024-25"}],["2022-23",3,"intern",0,0,24.3,21,{"reportingYear":"2024-25"}],["2022-23",3,"without_credentials_or_misassigned",5.71,1.3,24.3,21,{"reportingYear":"2024-25"}],["2022-23",3,"out_of_field",1.35,0.3,24.3,21,{"reportingYear":"2024-25"}],["2022-23",3,"unknown",3.28,0.8,24.3,21,{"reportingYear":"2024-25"}],["2023-24",3,"fully_credentialed",83.96,16.7,19.9,21,{"reportingYear":"2024-25"}],["2023-24",3,"intern",0,0,19.9,21,{"reportingYear":"2024-25"}],["2023-24",3,"without_credentials_or_misassigned",7.02,1.4,19.9,21,{"reportingYear":"2024-25"}],["2023-24",3,"out_of_field",5.01,1,19.9,21,{"reportingYear":"2024-25"}],["2023-24",3,"unknown",4.01,0.8,19.9,21,{"reportingYear":"2024-25"}],["2022-23",0,"grade_6",24,null,null,22,{"classCounts":{"large":4,"medium":29,"small":5},"classSizeBands":{"large":"33+","medium":"21-32","small":"1-20"}}],["2023-24",0,"grade_6",24,null,null,22,{"classCounts":{"large":2,"medium":24,"small":8},"classSizeBands":{"large":"33+","medium":"21-32","small":"1-20"}}],["2024-25",0,"grade_6",24,null,null,22,{"classCounts":{"large":5,"medium":26,"small":9},"classSizeBands":{"large":"33+","medium":"21-32","small":"1-20"}}],["2022-23",0,"subject_english",25,null,null,23,{"classCounts":{"large":3,"medium":5,"small":5},"classSizeBands":{"large":"33+","medium":"23-32","small":"1-22"}}],["2022-23",0,"subject_mathematics",25,null,null,23,{"classCounts":{"large":2,"medium":6,"small":4},"classSizeBands":{"large":"33+","medium":"23-32","small":"1-22"}}],["2022-23",0,"subject_science",27,null,null,23,{"classCounts":{"large":1,"medium":8,"small":2},"classSizeBands":{"large":"33+","medium":"23-32","small":"1-22"}}],["2022-23",0,"subject_social_science",27,null,null,23,{"classCounts":{"large":1,"medium":8,"small":2},"classSizeBands":{"large":"33+","medium":"23-32","small":"1-22"}}],["2023-24",0,"subject_english",22,null,null,23,{"classCounts":{"large":2,"medium":6,"small":7},"classSizeBands":{"large":"33+","medium":"23-32","small":"1-22"}}],["2023-24",0,"subject_mathematics",24,null,null,23,{"classCounts":{"large":null,"medium":9,"small":3},"classSizeBands":{"large":"33+","medium":"23-32","small":"1-22"}}],["2023-24",0,"subject_science",24,null,null,23,{"classCounts":{"large":null,"medium":5,"small":1},"classSizeBands":{"large":"33+","medium":"23-32","small":"1-22"}}],["2023-24",0,"subject_social_science",23,null,null,23,{"classCounts":{"large":1,"medium":3,"small":2},"classSizeBands":{"large":"33+","medium":"23-32","small":"1-22"}}],["2024-25",0,"subject_english",22,null,null,23,{"classCounts":{"large":null,"medium":9,"small":6},"classSizeBands":{"large":"33+","medium":"23-32","small":"1-22"}}],["2024-25",0,"subject_mathematics",24,null,null,23,{"classCounts":{"large":null,"medium":9,"small":3},"classSizeBands":{"large":"33+","medium":"23-32","small":"1-22"}}],["2024-25",0,"subject_science",25,null,null,23,{"classCounts":{"large":null,"medium":9,"small":2},"classSizeBands":{"large":"33+","medium":"23-32","small":"1-22"}}],["2024-25",0,"subject_social_science",25,null,null,23,{"classCounts":{"large":null,"medium":9,"small":2},"classSizeBands":{"large":"33+","medium":"23-32","small":"1-22"}}],["2025-26",4,"total",11.1,null,27,26,{"charter":"N","dass":"N","schoolGradeSpan":"GS_69"}],["2025-26",4,"district",8.9,null,27,26,{"charter":"N","dass":"N","schoolGradeSpan":"GS_69"}],["2025-26",5,"total",27,null,27,26,{"charter":"N","dass":"N","schoolGradeSpan":"GS_69"}],["2025-26",5,"experienced",23,null,27,26,{"charter":"N","dass":"N","schoolGradeSpan":"GS_69"}],["2025-26",5,"inexperienced",4,null,27,26,{"charter":"N","dass":"N","schoolGradeSpan":"GS_69"}],["2025-26",5,"first_year",4,null,27,26,{"charter":"N","dass":"N","schoolGradeSpan":"GS_69"}],["2025-26",5,"second_year",0,null,27,26,{"charter":"N","dass":"N","schoolGradeSpan":"GS_69"}]]},"shard":"12-0"}
