{"schemaVersion":1,"schools":{"48705326051049":[["2021-22",3,"fully_credentialed",89.02,24.3,27.3,21,{"reportingYear":"2024-25"}],["2021-22",3,"intern",3.66,1,27.3,21,{"reportingYear":"2024-25"}],["2021-22",3,"without_credentials_or_misassigned",7.32,2,27.3,21,{"reportingYear":"2024-25"}],["2021-22",3,"out_of_field",0,0,27.3,21,{"reportingYear":"2024-25"}],["2021-22",3,"unknown",0,0,27.3,21,{"reportingYear":"2024-25"}],["2022-23",3,"fully_credentialed",89.02,24.3,27.3,21,{"reportingYear":"2024-25"}],["2022-23",3,"intern",3.66,1,27.3,21,{"reportingYear":"2024-25"}],["2022-23",3,"without_credentials_or_misassigned",7.32,2,27.3,21,{"reportingYear":"2024-25"}],["2022-23",3,"out_of_field",0,0,27.3,21,{"reportingYear":"2024-25"}],["2022-23",3,"unknown",0,0,27.3,21,{"reportingYear":"2024-25"}],["2023-24",3,"fully_credentialed",63.83,15,23.5,21,{"reportingYear":"2024-25"}],["2023-24",3,"intern",8.51,2,23.5,21,{"reportingYear":"2024-25"}],["2023-24",3,"without_credentials_or_misassigned",27.66,6.5,23.5,21,{"reportingYear":"2024-25"}],["2023-24",3,"out_of_field",0,0,23.5,21,{"reportingYear":"2024-25"}],["2023-24",3,"unknown",0,0,23.5,21,{"reportingYear":"2024-25"}],["2022-23",0,"grade_k",22,null,null,22,{"classCounts":{"large":0,"medium":4,"small":0},"classSizeBands":{"large":"33+","medium":"21-32","small":"1-20"}}],["2022-23",0,"grade_1",24,null,null,22,{"classCounts":{"large":0,"medium":3,"small":0},"classSizeBands":{"large":"33+","medium":"21-32","small":"1-20"}}],["2022-23",0,"grade_2",25,null,null,22,{"classCounts":{"large":0,"medium":3,"small":0},"classSizeBands":{"large":"33+","medium":"21-32","small":"1-20"}}],["2022-23",0,"grade_3",24,null,null,22,{"classCounts":{"large":0,"medium":2,"small":0},"classSizeBands":{"large":"33+","medium":"21-32","small":"1-20"}}],["2022-23",0,"grade_4",31,null,null,22,{"classCounts":{"large":0,"medium":2,"small":0},"classSizeBands":{"large":"33+","medium":"21-32","small":"1-20"}}],["2022-23",0,"grade_5",23,null,null,22,{"classCounts":{"large":0,"medium":3,"small":1},"classSizeBands":{"large":"33+","medium":"21-32","small":"1-20"}}],["2022-23",0,"grade_other",24,null,null,22,{"classCounts":{"large":0,"medium":1,"small":1},"classSizeBands":{"large":"33+","medium":"21-32","small":"1-20"}}],["2023-24",0,"grade_k",21,null,null,22,{"classCounts":{"large":0,"medium":2,"small":1},"classSizeBands":{"large":"33+","medium":"21-32","small":"1-20"}}],["2023-24",0,"grade_1",25,null,null,22,{"classCounts":{"large":0,"medium":2,"small":0},"classSizeBands":{"large":"33+","medium":"21-32","small":"1-20"}}],["2023-24",0,"grade_2",23,null,null,22,{"classCounts":{"large":0,"medium":3,"small":0},"classSizeBands":{"large":"33+","medium":"21-32","small":"1-20"}}],["2023-24",0,"grade_3",24,null,null,22,{"classCounts":{"large":0,"medium":3,"small":0},"classSizeBands":{"large":"33+","medium":"21-32","small":"1-20"}}],["2023-24",0,"grade_4",32,null,null,22,{"classCounts":{"large":0,"medium":2,"small":0},"classSizeBands":{"large":"33+","medium":"21-32","small":"1-20"}}],["2023-24",0,"grade_5",25,null,null,22,{"classCounts":{"large":0,"medium":3,"small":0},"classSizeBands":{"large":"33+","medium":"21-32","small":"1-20"}}],["2023-24",0,"grade_other",21,null,null,22,{"classCounts":{"large":0,"medium":1,"small":0},"classSizeBands":{"large":"33+","medium":"21-32","small":"1-20"}}],["2024-25",0,"grade_k",17,null,null,22,{"classCounts":{"large":null,"medium":2,"small":1},"classSizeBands":{"large":"33+","medium":"21-32","small":"1-20"}}],["2024-25",0,"grade_1",23,null,null,22,{"classCounts":{"large":null,"medium":3,"small":null},"classSizeBands":{"large":"33+","medium":"21-32","small":"1-20"}}],["2024-25",0,"grade_2",21,null,null,22,{"classCounts":{"large":null,"medium":2,"small":1},"classSizeBands":{"large":"33+","medium":"21-32","small":"1-20"}}],["2024-25",0,"grade_3",24,null,null,22,{"classCounts":{"large":null,"medium":3,"small":null},"classSizeBands":{"large":"33+","medium":"21-32","small":"1-20"}}],["2024-25",0,"grade_4",33,null,null,22,{"classCounts":{"large":null,"medium":1,"small":null},"classSizeBands":{"large":"33+","medium":"21-32","small":"1-20"}}],["2024-25",0,"grade_5",29,null,null,22,{"classCounts":{"large":null,"medium":2,"small":null},"classSizeBands":{"large":"33+","medium":"21-32","small":"1-20"}}],["2024-25",2,"psychologist",1,null,null,25,{}],["2025-26",4,"total",10,null,21,26,{"charter":"N","dass":"N","schoolGradeSpan":"GS_K6"}],["2025-26",4,"district",10,null,21,26,{"charter":"N","dass":"N","schoolGradeSpan":"GS_K6"}],["2025-26",5,"total",21,null,21,26,{"charter":"N","dass":"N","schoolGradeSpan":"GS_K6"}],["2025-26",5,"experienced",14,null,21,26,{"charter":"N","dass":"N","schoolGradeSpan":"GS_K6"}],["2025-26",5,"inexperienced",7,null,21,26,{"charter":"N","dass":"N","schoolGradeSpan":"GS_K6"}],["2025-26",5,"first_year",1,null,21,26,{"charter":"N","dass":"N","schoolGradeSpan":"GS_K6"}],["2025-26",5,"second_year",6,null,21,26,{"charter":"N","dass":"N","schoolGradeSpan":"GS_K6"}]],"48705654838801":[["2021-22",3,"fully_credentialed",86.03,59.2,68.8,21,{"reportingYear":"2024-25"}],["2021-22",3,"intern",1.66,1.1,68.8,21,{"reportingYear":"2024-25"}],["2021-22",3,"without_credentials_or_misassigned",1.55,1,68.8,21,{"reportingYear":"2024-25"}],["2021-22",3,"out_of_field",1.26,0.8,68.8,21,{"reportingYear":"2024-25"}],["2021-22",3,"unknown",9.45,6.5,68.8,21,{"reportingYear":"2024-25"}],["2022-23",3,"fully_credentialed",92.12,67,72.8,21,{"reportingYear":"2024-25"}],["2022-23",3,"intern",0,0,72.8,21,{"reportingYear":"2024-25"}],["2022-23",3,"without_credentials_or_misassigned",0.78,0.5,72.8,21,{"reportingYear":"2024-25"}],["2022-23",3,"out_of_field",1.26,0.9,72.8,21,{"reportingYear":"2024-25"}],["2022-23",3,"unknown",5.81,4.2,72.8,21,{"reportingYear":"2024-25"}],["2023-24",3,"fully_credentialed",86.62,60.4,69.8,21,{"reportingYear":"2024-25"}],["2023-24",3,"intern",0,0,69.8,21,{"reportingYear":"2024-25"}],["2023-24",3,"without_credentials_or_misassigned",4.1,2.8,69.8,21,{"reportingYear":"2024-25"}],["2023-24",3,"out_of_field",4.36,3,69.8,21,{"reportingYear":"2024-25"}],["2023-24",3,"unknown",4.9,3.4,69.8,21,{"reportingYear":"2024-25"}],["2022-23",0,"subject_english",27,null,null,23,{"classCounts":{"large":31,"medium":16,"small":15},"classSizeBands":{"large":"33+","medium":"23-32","small":"1-22"}}],["2022-23",0,"subject_mathematics",30,null,null,23,{"classCounts":{"large":22,"medium":24,"small":3},"classSizeBands":{"large":"33+","medium":"23-32","small":"1-22"}}],["2022-23",0,"subject_science",26,null,null,23,{"classCounts":{"large":0,"medium":42,"small":8},"classSizeBands":{"large":"33+","medium":"23-32","small":"1-22"}}],["2022-23",0,"subject_social_science",31,null,null,23,{"classCounts":{"large":29,"medium":16,"small":7},"classSizeBands":{"large":"33+","medium":"23-32","small":"1-22"}}],["2023-24",0,"subject_english",28,null,null,23,{"classCounts":{"large":39,"medium":8,"small":13},"classSizeBands":{"large":"33+","medium":"23-32","small":"1-22"}}],["2023-24",0,"subject_mathematics",30,null,null,23,{"classCounts":{"large":28,"medium":15,"small":5},"classSizeBands":{"large":"33+","medium":"23-32","small":"1-22"}}],["2023-24",0,"subject_science",26,null,null,23,{"classCounts":{"large":null,"medium":49,"small":3},"classSizeBands":{"large":"33+","medium":"23-32","small":"1-22"}}],["2023-24",0,"subject_social_science",29,null,null,23,{"classCounts":{"large":20,"medium":22,"small":5},"classSizeBands":{"large":"33+","medium":"23-32","small":"1-22"}}],["2024-25",0,"subject_english",29,null,null,23,{"classCounts":{"large":34,"medium":14,"small":11},"classSizeBands":{"large":"33+","medium":"23-32","small":"1-22"}}],["2024-25",0,"subject_mathematics",31,null,null,23,{"classCounts":{"large":28,"medium":13,"small":5},"classSizeBands":{"large":"33+","medium":"23-32","small":"1-22"}}],["2024-25",0,"subject_science",28,null,null,23,{"classCounts":{"large":null,"medium":43,"small":3},"classSizeBands":{"large":"33+","medium":"23-32","small":"1-22"}}],["2024-25",0,"subject_social_science",32,null,null,23,{"classCounts":{"large":35,"medium":9,"small":4},"classSizeBands":{"large":"33+","medium":"23-32","small":"1-22"}}],["2024-25",1,"all_students",404.75,null,null,24,{}],["2024-25",2,"counselor",4,null,null,25,{}],["2024-25",2,"psychologist",1,null,null,25,{}],["2025-26",4,"total",14.3,null,71,26,{"charter":"N","dass":"N","schoolGradeSpan":"GS_912"}],["2025-26",4,"district",10.4,null,71,26,{"charter":"N","dass":"N","schoolGradeSpan":"GS_912"}],["2025-26",5,"total",71,null,71,26,{"charter":"N","dass":"N","schoolGradeSpan":"GS_912"}],["2025-26",5,"experienced",61,null,71,26,{"charter":"N","dass":"N","schoolGradeSpan":"GS_912"}],["2025-26",5,"inexperienced",10,null,71,26,{"charter":"N","dass":"N","schoolGradeSpan":"GS_912"}],["2025-26",5,"first_year",1,null,71,26,{"charter":"N","dass":"N","schoolGradeSpan":"GS_912"}],["2025-26",5,"second_year",9,null,71,26,{"charter":"N","dass":"N","schoolGradeSpan":"GS_912"}]],"48705730133553":[["2021-22",3,"fully_credentialed",89.69,25.6,28.6,21,{"reportingYear":"2024-25"}],["2021-22",3,"intern",0,0,28.6,21,{"reportingYear":"2024-25"}],["2021-22",3,"without_credentials_or_misassigned",3.5,1,28.6,21,{"reportingYear":"2024-25"}],["2021-22",3,"out_of_field",5.66,1.6,28.6,21,{"reportingYear":"2024-25"}],["2021-22",3,"unknown",1.15,0.3,28.6,21,{"reportingYear":"2024-25"}],["2022-23",3,"fully_credentialed",80.59,22.9,28.4,21,{"reportingYear":"2024-25"}],["2022-23",3,"intern",5.83,1.6,28.4,21,{"reportingYear":"2024-25"}],["2022-23",3,"without_credentials_or_misassigned",4.18,1.1,28.4,21,{"reportingYear":"2024-25"}],["2022-23",3,"out_of_field",5.62,1.6,28.4,21,{"reportingYear":"2024-25"}],["2022-23",3,"unknown",3.72,1,28.4,21,{"reportingYear":"2024-25"}],["2023-24",3,"fully_credentialed",88.71,26.4,29.8,21,{"reportingYear":"2024-25"}],["2023-24",3,"intern",0,0,29.8,21,{"reportingYear":"2024-25"}],["2023-24",3,"without_credentials_or_misassigned",1.21,0.3,29.8,21,{"reportingYear":"2024-25"}],["2023-24",3,"out_of_field",6.03,1.8,29.8,21,{"reportingYear":"2024-25"}],["2023-24",3,"unknown",3.99,1.1,29.8,21,{"reportingYear":"2024-25"}],["2022-23",0,"grade_k",23,null,null,22,{"classCounts":{"large":0,"medium":2,"small":0},"classSizeBands":{"large":"33+","medium":"21-32","small":"1-20"}}],["2022-23",0,"grade_1",24,null,null,22,{"classCounts":{"large":0,"medium":2,"small":0},"classSizeBands":{"large":"33+","medium":"21-32","small":"1-20"}}],["2022-23",0,"grade_2",25,null,null,22,{"classCounts":{"large":0,"medium":2,"small":0},"classSizeBands":{"large":"33+","medium":"21-32","small":"1-20"}}],["2022-23",0,"grade_3",24,null,null,22,{"classCounts":{"large":0,"medium":2,"small":0},"classSizeBands":{"large":"33+","medium":"21-32","small":"1-20"}}],["2022-23",0,"grade_4",22,null,null,22,{"classCounts":{"large":0,"medium":2,"small":1},"classSizeBands":{"large":"33+","medium":"21-32","small":"1-20"}}],["2022-23",0,"grade_5",32,null,null,22,{"classCounts":{"large":0,"medium":2,"small":0},"classSizeBands":{"large":"33+","medium":"21-32","small":"1-20"}}],["2022-23",0,"grade_6",23,null,null,22,{"classCounts":{"large":1,"medium":3,"small":6},"classSizeBands":{"large":"33+","medium":"21-32","small":"1-20"}}],["2023-24",0,"grade_k",22,null,null,22,{"classCounts":{"large":null,"medium":2,"small":null},"classSizeBands":{"large":"33+","medium":"21-32","small":"1-20"}}],["2023-24",0,"grade_1",24,null,null,22,{"classCounts":{"large":null,"medium":2,"small":null},"classSizeBands":{"large":"33+","medium":"21-32","small":"1-20"}}],["2023-24",0,"grade_2",25,null,null,22,{"classCounts":{"large":null,"medium":2,"small":null},"classSizeBands":{"large":"33+","medium":"21-32","small":"1-20"}}],["2023-24",0,"grade_3",26,null,null,22,{"classCounts":{"large":null,"medium":2,"small":null},"classSizeBands":{"large":"33+","medium":"21-32","small":"1-20"}}],["2023-24",0,"grade_4",26,null,null,22,{"classCounts":{"large":null,"medium":2,"small":null},"classSizeBands":{"large":"33+","medium":"21-32","small":"1-20"}}],["2023-24",0,"grade_5",32,null,null,22,{"classCounts":{"large":null,"medium":2,"small":null},"classSizeBands":{"large":"33+","medium":"21-32","small":"1-20"}}],["2023-24",0,"grade_6",29,null,null,22,{"classCounts":{"large":5,"medium":2,"small":2},"classSizeBands":{"large":"33+","medium":"21-32","small":"1-20"}}],["2024-25",0,"grade_k",23,null,null,22,{"classCounts":{"large":null,"medium":2,"small":null},"classSizeBands":{"large":"33+","medium":"21-32","small":"1-20"}}],["2024-25",0,"grade_1",24,null,null,22,{"classCounts":{"large":null,"medium":2,"small":null},"classSizeBands":{"large":"33+","medium":"21-32","small":"1-20"}}],["2024-25",0,"grade_2",24,null,null,22,{"classCounts":{"large":null,"medium":2,"small":null},"classSizeBands":{"large":"33+","medium":"21-32","small":"1-20"}}],["2024-25",0,"grade_3",26,null,null,22,{"classCounts":{"large":null,"medium":2,"small":null},"classSizeBands":{"large":"33+","medium":"21-32","small":"1-20"}}],["2024-25",0,"grade_4",31,null,null,22,{"classCounts":{"large":null,"medium":2,"small":null},"classSizeBands":{"large":"33+","medium":"21-32","small":"1-20"}}],["2024-25",0,"grade_5",30,null,null,22,{"classCounts":{"large":null,"medium":2,"small":null},"classSizeBands":{"large":"33+","medium":"21-32","small":"1-20"}}],["2024-25",0,"grade_6",24,null,null,22,{"classCounts":{"large":1,"medium":3,"small":5},"classSizeBands":{"large":"33+","medium":"21-32","small":"1-20"}}],["2022-23",0,"subject_english",23,null,null,23,{"classCounts":{"large":0,"medium":6,"small":4},"classSizeBands":{"large":"33+","medium":"23-32","small":"1-22"}}],["2022-23",0,"subject_mathematics",23,null,null,23,{"classCounts":{"large":0,"medium":7,"small":4},"classSizeBands":{"large":"33+","medium":"23-32","small":"1-22"}}],["2022-23",0,"subject_science",28,null,null,23,{"classCounts":{"large":0,"medium":8,"small":1},"classSizeBands":{"large":"33+","medium":"23-32","small":"1-22"}}],["2022-23",0,"subject_social_science",28,null,null,23,{"classCounts":{"large":0,"medium":8,"small":0},"classSizeBands":{"large":"33+","medium":"23-32","small":"1-22"}}],["2023-24",0,"subject_english",23,null,null,23,{"classCounts":{"large":null,"medium":7,"small":3},"classSizeBands":{"large":"33+","medium":"23-32","small":"1-22"}}],["2023-24",0,"subject_mathematics",21,null,null,23,{"classCounts":{"large":null,"medium":8,"small":4},"classSizeBands":{"large":"33+","medium":"23-32","small":"1-22"}}],["2023-24",0,"subject_science",28,null,null,23,{"classCounts":{"large":null,"medium":8,"small":1},"classSizeBands":{"large":"33+","medium":"23-32","small":"1-22"}}],["2023-24",0,"subject_social_science",29,null,null,23,{"classCounts":{"large":null,"medium":8,"small":null},"classSizeBands":{"large":"33+","medium":"23-32","small":"1-22"}}],["2024-25",0,"subject_english",23,null,null,23,{"classCounts":{"large":null,"medium":7,"small":3},"classSizeBands":{"large":"33+","medium":"23-32","small":"1-22"}}],["2024-25",0,"subject_mathematics",23,null,null,23,{"classCounts":{"large":null,"medium":8,"small":2},"classSizeBands":{"large":"33+","medium":"23-32","small":"1-22"}}],["2024-25",0,"subject_science",28,null,null,23,{"classCounts":{"large":null,"medium":8,"small":1},"classSizeBands":{"large":"33+","medium":"23-32","small":"1-22"}}],["2024-25",0,"subject_social_science",29,null,null,23,{"classCounts":{"large":null,"medium":8,"small":null},"classSizeBands":{"large":"33+","medium":"23-32","small":"1-22"}}],["2024-25",2,"psychologist",0.8,null,null,25,{}],["2024-25",2,"speech_language_hearing_specialist",0.8,null,null,25,{}],["2025-26",4,"total",12.8,null,38,26,{"charter":"N","dass":"N","schoolGradeSpan":"GS_K12"}],["2025-26",4,"district",8.8,null,38,26,{"charter":"N","dass":"N","schoolGradeSpan":"GS_K12"}],["2025-26",5,"total",38,null,38,26,{"charter":"N","dass":"N","schoolGradeSpan":"GS_K12"}],["2025-26",5,"experienced",35,null,38,26,{"charter":"N","dass":"N","schoolGradeSpan":"GS_K12"}],["2025-26",5,"inexperienced",3,null,38,26,{"charter":"N","dass":"N","schoolGradeSpan":"GS_K12"}],["2025-26",5,"first_year",1,null,38,26,{"charter":"N","dass":"N","schoolGradeSpan":"GS_K12"}],["2025-26",5,"second_year",2,null,38,26,{"charter":"N","dass":"N","schoolGradeSpan":"GS_K12"}]],"48705734830089":[["2021-22",3,"fully_credentialed",79.37,61.6,77.7,21,{"reportingYear":"2024-25"}],["2021-22",3,"intern",0,0,77.7,21,{"reportingYear":"2024-25"}],["2021-22",3,"without_credentials_or_misassigned",0.51,0.4,77.7,21,{"reportingYear":"2024-25"}],["2021-22",3,"out_of_field",10.6,8.2,77.7,21,{"reportingYear":"2024-25"}],["2021-22",3,"unknown",9.5,7.3,77.7,21,{"reportingYear":"2024-25"}],["2022-23",3,"fully_credentialed",83.41,66.5,79.8,21,{"reportingYear":"2024-25"}],["2022-23",3,"intern",2.51,2,79.8,21,{"reportingYear":"2024-25"}],["2022-23",3,"without_credentials_or_misassigned",4.89,3.9,79.8,21,{"reportingYear":"2024-25"}],["2022-23",3,"out_of_field",2.31,1.8,79.8,21,{"reportingYear":"2024-25"}],["2022-23",3,"unknown",6.88,5.4,79.8,21,{"reportingYear":"2024-25"}],["2023-24",3,"fully_credentialed",82.31,65.9,80.1,21,{"reportingYear":"2024-25"}],["2023-24",3,"intern",3.43,2.7,80.1,21,{"reportingYear":"2024-25"}],["2023-24",3,"without_credentials_or_misassigned",6.62,5.3,80.1,21,{"reportingYear":"2024-25"}],["2023-24",3,"out_of_field",2,1.6,80.1,21,{"reportingYear":"2024-25"}],["2023-24",3,"unknown",5.63,4.5,80.1,21,{"reportingYear":"2024-25"}],["2022-23",0,"subject_english",23,null,null,23,{"classCounts":{"large":16,"medium":34,"small":28},"classSizeBands":{"large":"33+","medium":"23-32","small":"1-22"}}],["2022-23",0,"subject_mathematics",23,null,null,23,{"classCounts":{"large":16,"medium":24,"small":23},"classSizeBands":{"large":"33+","medium":"23-32","small":"1-22"}}],["2022-23",0,"subject_science",25,null,null,23,{"classCounts":{"large":17,"medium":22,"small":11},"classSizeBands":{"large":"33+","medium":"23-32","small":"1-22"}}],["2022-23",0,"subject_social_science",24,null,null,23,{"classCounts":{"large":16,"medium":25,"small":15},"classSizeBands":{"large":"33+","medium":"23-32","small":"1-22"}}],["2023-24",0,"subject_english",23,null,null,23,{"classCounts":{"large":8,"medium":42,"small":28},"classSizeBands":{"large":"33+","medium":"23-32","small":"1-22"}}],["2023-24",0,"subject_mathematics",23,null,null,23,{"classCounts":{"large":13,"medium":26,"small":24},"classSizeBands":{"large":"33+","medium":"23-32","small":"1-22"}}],["2023-24",0,"subject_science",27,null,null,23,{"classCounts":{"large":22,"medium":13,"small":11},"classSizeBands":{"large":"33+","medium":"23-32","small":"1-22"}}],["2023-24",0,"subject_social_science",24,null,null,23,{"classCounts":{"large":18,"medium":20,"small":18},"classSizeBands":{"large":"33+","medium":"23-32","small":"1-22"}}],["2024-25",0,"subject_english",19,null,null,23,{"classCounts":{"large":8,"medium":42,"small":41},"classSizeBands":{"large":"33+","medium":"23-32","small":"1-22"}}],["2024-25",0,"subject_mathematics",21,null,null,23,{"classCounts":{"large":7,"medium":38,"small":29},"classSizeBands":{"large":"33+","medium":"23-32","small":"1-22"}}],["2024-25",0,"subject_science",22,null,null,23,{"classCounts":{"large":6,"medium":28,"small":18},"classSizeBands":{"large":"33+","medium":"23-32","small":"1-22"}}],["2024-25",0,"subject_social_science",16,null,null,23,{"classCounts":{"large":11,"medium":27,"small":45},"classSizeBands":{"large":"33+","medium":"23-32","small":"1-22"}}],["2024-25",1,"all_students",365.43,null,null,24,{}],["2024-25",2,"counselor",4.6,null,null,25,{}],["2024-25",2,"psychologist",2,null,null,25,{}],["2024-25",2,"nurse",0.3,null,null,25,{}],["2024-25",2,"speech_language_hearing_specialist",1,null,null,25,{}],["2025-26",4,"total",13.5,null,86,26,{"charter":"N","dass":"N","schoolGradeSpan":"GS_912"}],["2025-26",4,"district",10.8,null,86,26,{"charter":"N","dass":"N","schoolGradeSpan":"GS_912"}],["2025-26",5,"total",86,null,86,26,{"charter":"N","dass":"N","schoolGradeSpan":"GS_912"}],["2025-26",5,"experienced",74,null,86,26,{"charter":"N","dass":"N","schoolGradeSpan":"GS_912"}],["2025-26",5,"inexperienced",12,null,86,26,{"charter":"N","dass":"N","schoolGradeSpan":"GS_912"}],["2025-26",5,"first_year",7,null,86,26,{"charter":"N","dass":"N","schoolGradeSpan":"GS_912"}],["2025-26",5,"second_year",5,null,86,26,{"charter":"N","dass":"N","schoolGradeSpan":"GS_912"}]],"48705734830113":[["2021-22",3,"fully_credentialed",84.22,21.3,25.2,21,{"reportingYear":"2024-25"}],["2021-22",3,"intern",0,0,25.2,21,{"reportingYear":"2024-25"}],["2021-22",3,"without_credentials_or_misassigned",3.91,0.9,25.2,21,{"reportingYear":"2024-25"}],["2021-22",3,"out_of_field",0.43,0.1,25.2,21,{"reportingYear":"2024-25"}],["2021-22",3,"unknown",11.39,2.8,25.2,21,{"reportingYear":"2024-25"}],["2022-23",3,"fully_credentialed",87.66,21,23.9,21,{"reportingYear":"2024-25"}],["2022-23",3,"intern",0,0,23.9,21,{"reportingYear":"2024-25"}],["2022-23",3,"without_credentials_or_misassigned",2.46,0.5,23.9,21,{"reportingYear":"2024-25"}],["2022-23",3,"out_of_field",0,0,23.9,21,{"reportingYear":"2024-25"}],["2022-23",3,"unknown",9.84,2.3,23.9,21,{"reportingYear":"2024-25"}],["2023-24",3,"fully_credentialed",92.95,22.6,24.3,21,{"reportingYear":"2024-25"}],["2023-24",3,"intern",2.42,0.5,24.3,21,{"reportingYear":"2024-25"}],["2023-24",3,"without_credentials_or_misassigned",0.66,0.1,24.3,21,{"reportingYear":"2024-25"}],["2023-24",3,"out_of_field",0,0,24.3,21,{"reportingYear":"2024-25"}],["2023-24",3,"unknown",3.9,0.9,24.3,21,{"reportingYear":"2024-25"}],["2022-23",0,"subject_english",18,null,null,23,{"classCounts":{"large":0,"medium":10,"small":15},"classSizeBands":{"large":"33+","medium":"23-32","small":"1-22"}}],["2022-23",0,"subject_mathematics",17,null,null,23,{"classCounts":{"large":0,"medium":10,"small":15},"classSizeBands":{"large":"33+","medium":"23-32","small":"1-22"}}],["2022-23",0,"subject_science",18,null,null,23,{"classCounts":{"large":0,"medium":8,"small":11},"classSizeBands":{"large":"33+","medium":"23-32","small":"1-22"}}],["2022-23",0,"subject_social_science",15,null,null,23,{"classCounts":{"large":0,"medium":6,"small":17},"classSizeBands":{"large":"33+","medium":"23-32","small":"1-22"}}],["2023-24",0,"subject_english",17,null,null,23,{"classCounts":{"large":null,"medium":5,"small":23},"classSizeBands":{"large":"33+","medium":"23-32","small":"1-22"}}],["2023-24",0,"subject_mathematics",17,null,null,23,{"classCounts":{"large":null,"medium":10,"small":17},"classSizeBands":{"large":"33+","medium":"23-32","small":"1-22"}}],["2023-24",0,"subject_science",17,null,null,23,{"classCounts":{"large":null,"medium":8,"small":13},"classSizeBands":{"large":"33+","medium":"23-32","small":"1-22"}}],["2023-24",0,"subject_social_science",18,null,null,23,{"classCounts":{"large":2,"medium":6,"small":13},"classSizeBands":{"large":"33+","medium":"23-32","small":"1-22"}}],["2024-25",0,"subject_english",18,null,null,23,{"classCounts":{"large":null,"medium":12,"small":14},"classSizeBands":{"large":"33+","medium":"23-32","small":"1-22"}}],["2024-25",0,"subject_mathematics",22,null,null,23,{"classCounts":{"large":1,"medium":9,"small":10},"classSizeBands":{"large":"33+","medium":"23-32","small":"1-22"}}],["2024-25",0,"subject_science",17,null,null,23,{"classCounts":{"large":null,"medium":7,"small":12},"classSizeBands":{"large":"33+","medium":"23-32","small":"1-22"}}],["2024-25",0,"subject_social_science",18,null,null,23,{"classCounts":{"large":2,"medium":6,"small":12},"classSizeBands":{"large":"33+","medium":"23-32","small":"1-22"}}],["2024-25",1,"all_students",237,null,null,24,{}],["2024-25",2,"counselor",2,null,null,25,{}],["2024-25",2,"psychologist",0.5,null,null,25,{}],["2024-25",2,"nurse",0.3,null,null,25,{}],["2024-25",2,"speech_language_hearing_specialist",0.2,null,null,25,{}],["2025-26",4,"total",14.1,null,28,26,{"charter":"Y","dass":"N","schoolGradeSpan":"GS_912"}],["2025-26",4,"district",11.9,null,28,26,{"charter":"Y","dass":"N","schoolGradeSpan":"GS_912"}],["2025-26",5,"total",28,null,28,26,{"charter":"Y","dass":"N","schoolGradeSpan":"GS_912"}],["2025-26",5,"experienced",25,null,28,26,{"charter":"Y","dass":"N","schoolGradeSpan":"GS_912"}],["2025-26",5,"inexperienced",3,null,28,26,{"charter":"Y","dass":"N","schoolGradeSpan":"GS_912"}],["2025-26",5,"first_year",3,null,28,26,{"charter":"Y","dass":"N","schoolGradeSpan":"GS_912"}],["2025-26",5,"second_year",0,null,28,26,{"charter":"Y","dass":"N","schoolGradeSpan":"GS_912"}]],"48705736110241":[["2021-22",3,"fully_credentialed",85.2,28.7,33.7,21,{"reportingYear":"2024-25"}],["2021-22",3,"intern",2.96,1,33.7,21,{"reportingYear":"2024-25"}],["2021-22",3,"without_credentials_or_misassigned",8.88,3,33.7,21,{"reportingYear":"2024-25"}],["2021-22",3,"out_of_field",0,0,33.7,21,{"reportingYear":"2024-25"}],["2021-22",3,"unknown",2.96,1,33.7,21,{"reportingYear":"2024-25"}],["2022-23",3,"fully_credentialed",80.28,27.9,34.8,21,{"reportingYear":"2024-25"}],["2022-23",3,"intern",3.07,1,34.8,21,{"reportingYear":"2024-25"}],["2022-23",3,"without_credentials_or_misassigned",13.75,4.7,34.8,21,{"reportingYear":"2024-25"}],["2022-23",3,"out_of_field",0,0,34.8,21,{"reportingYear":"2024-25"}],["2022-23",3,"unknown",2.87,1,34.8,21,{"reportingYear":"2024-25"}],["2023-24",3,"fully_credentialed",85.54,30.5,35.7,21,{"reportingYear":"2024-25"}],["2023-24",3,"intern",2.8,1,35.7,21,{"reportingYear":"2024-25"}],["2023-24",3,"without_credentials_or_misassigned",8.84,3.1,35.7,21,{"reportingYear":"2024-25"}],["2023-24",3,"out_of_field",0,0,35.7,21,{"reportingYear":"2024-25"}],["2023-24",3,"unknown",2.8,1,35.7,21,{"reportingYear":"2024-25"}],["2022-23",0,"grade_k",18,null,null,22,{"classCounts":{"large":0,"medium":2,"small":3},"classSizeBands":{"large":"33+","medium":"21-32","small":"1-20"}}],["2022-23",0,"grade_1",21,null,null,22,{"classCounts":{"large":0,"medium":4,"small":1},"classSizeBands":{"large":"33+","medium":"21-32","small":"1-20"}}],["2022-23",0,"grade_2",25,null,null,22,{"classCounts":{"large":0,"medium":4,"small":0},"classSizeBands":{"large":"33+","medium":"21-32","small":"1-20"}}],["2022-23",0,"grade_3",24,null,null,22,{"classCounts":{"large":0,"medium":4,"small":0},"classSizeBands":{"large":"33+","medium":"21-32","small":"1-20"}}],["2022-23",0,"grade_4",36,null,null,22,{"classCounts":{"large":1,"medium":3,"small":0},"classSizeBands":{"large":"33+","medium":"21-32","small":"1-20"}}],["2022-23",0,"grade_5",30,null,null,22,{"classCounts":{"large":0,"medium":3,"small":0},"classSizeBands":{"large":"33+","medium":"21-32","small":"1-20"}}],["2022-23",0,"grade_6",31,null,null,22,{"classCounts":{"large":0,"medium":3,"small":0},"classSizeBands":{"large":"33+","medium":"21-32","small":"1-20"}}],["2022-23",0,"grade_other",7,null,null,22,{"classCounts":{"large":0,"medium":0,"small":4},"classSizeBands":{"large":"33+","medium":"21-32","small":"1-20"}}],["2023-24",0,"grade_k",20,null,null,22,{"classCounts":{"large":null,"medium":4,"small":1},"classSizeBands":{"large":"33+","medium":"21-32","small":"1-20"}}],["2023-24",0,"grade_1",20,null,null,22,{"classCounts":{"large":null,"medium":4,"small":1},"classSizeBands":{"large":"33+","medium":"21-32","small":"1-20"}}],["2023-24",0,"grade_2",25,null,null,22,{"classCounts":{"large":null,"medium":4,"small":null},"classSizeBands":{"large":"33+","medium":"21-32","small":"1-20"}}],["2023-24",0,"grade_3",23,null,null,22,{"classCounts":{"large":null,"medium":4,"small":null},"classSizeBands":{"large":"33+","medium":"21-32","small":"1-20"}}],["2023-24",0,"grade_4",35,null,null,22,{"classCounts":{"large":1,"medium":2,"small":null},"classSizeBands":{"large":"33+","medium":"21-32","small":"1-20"}}],["2023-24",0,"grade_5",30,null,null,22,{"classCounts":{"large":null,"medium":4,"small":null},"classSizeBands":{"large":"33+","medium":"21-32","small":"1-20"}}],["2023-24",0,"grade_6",30,null,null,22,{"classCounts":{"large":null,"medium":3,"small":null},"classSizeBands":{"large":"33+","medium":"21-32","small":"1-20"}}],["2023-24",0,"grade_other",11,null,null,22,{"classCounts":{"large":null,"medium":1,"small":4},"classSizeBands":{"large":"33+","medium":"21-32","small":"1-20"}}],["2024-25",0,"grade_k",17,null,null,22,{"classCounts":{"large":null,"medium":null,"small":5},"classSizeBands":{"large":"33+","medium":"21-32","small":"1-20"}}],["2024-25",0,"grade_1",19,null,null,22,{"classCounts":{"large":null,"medium":4,"small":1},"classSizeBands":{"large":"33+","medium":"21-32","small":"1-20"}}],["2024-25",0,"grade_2",22,null,null,22,{"classCounts":{"large":null,"medium":4,"small":null},"classSizeBands":{"large":"33+","medium":"21-32","small":"1-20"}}],["2024-25",0,"grade_3",20,null,null,22,{"classCounts":{"large":null,"medium":4,"small":1},"classSizeBands":{"large":"33+","medium":"21-32","small":"1-20"}}],["2024-25",0,"grade_4",25,null,null,22,{"classCounts":{"large":null,"medium":4,"small":null},"classSizeBands":{"large":"33+","medium":"21-32","small":"1-20"}}],["2024-25",0,"grade_5",30,null,null,22,{"classCounts":{"large":null,"medium":3,"small":null},"classSizeBands":{"large":"33+","medium":"21-32","small":"1-20"}}],["2024-25",0,"grade_6",31,null,null,22,{"classCounts":{"large":null,"medium":4,"small":null},"classSizeBands":{"large":"33+","medium":"21-32","small":"1-20"}}],["2024-25",0,"grade_other",8,null,null,22,{"classCounts":{"large":null,"medium":null,"small":3},"classSizeBands":{"large":"33+","medium":"21-32","small":"1-20"}}],["2024-25",2,"nurse",0.3,null,null,25,{}],["2025-26",4,"total",12.5,null,47,26,{"charter":"N","dass":"N","schoolGradeSpan":"GS_K6"}],["2025-26",4,"district",9.4,null,47,26,{"charter":"N","dass":"N","schoolGradeSpan":"GS_K6"}],["2025-26",5,"total",47,null,47,26,{"charter":"N","dass":"N","schoolGradeSpan":"GS_K6"}],["2025-26",5,"experienced",36,null,47,26,{"charter":"N","dass":"N","schoolGradeSpan":"GS_K6"}],["2025-26",5,"inexperienced",11,null,47,26,{"charter":"N","dass":"N","schoolGradeSpan":"GS_K6"}],["2025-26",5,"first_year",5,null,47,26,{"charter":"N","dass":"N","schoolGradeSpan":"GS_K6"}],["2025-26",5,"second_year",6,null,47,26,{"charter":"N","dass":"N","schoolGradeSpan":"GS_K6"}]]},"shard":"48-1"}
