{"schemaVersion":1,"schools":{"23102310110023":{"demographics":{"African American":{"count":1,"percent":5.0},"American Indian":{"count":2,"percent":10.0},"Asian":{"count":1,"percent":5.0},"English Learner":{"count":2,"percent":10.0},"Filipino":{"count":0,"percent":0.0},"Foster":{"count":5,"percent":25.0},"Free/Reduced Meal Eligible":{"count":18,"percent":90.0},"Hispanic":{"count":7,"percent":35.0},"Homeless":{"count":3,"percent":15.0},"Migrant":{"count":0,"percent":0.0},"Not Reported":{"count":0,"percent":0.0},"Pacific Islander":{"count":0,"percent":0.0},"Socioeconomically Disadvantaged":{"count":18,"percent":90.0},"Students with Disabilities":{"count":20,"percent":100.0},"Two or More Races":{"count":2,"percent":10.0},"White":{"count":7,"percent":35.0}},"observations":[[2024,0,13,null,null,null,2,5],[2023,0,13,null,null,null,2,9],[2022,0,13,null,null,null,2,14],[2022,0,0,null,null,null,2,14],[2024,0,0,null,null,null,2,5],[2023,0,0,null,null,null,2,9],[2023,0,14,null,null,null,2,9],[2022,0,14,null,null,null,2,14],[2024,0,14,null,null,null,2,5],[2024,0,15,null,null,null,2,5],[2023,0,15,null,null,null,2,9],[2022,0,15,null,null,null,2,14],[2022,0,2,null,null,null,2,14],[2024,0,2,null,null,null,2,5],[2022,0,22,null,null,null,2,14],[2023,0,22,null,null,null,2,9],[2023,0,16,null,null,null,2,9],[2024,0,16,null,null,null,2,5],[2022,0,16,null,null,null,2,14],[2022,0,5,null,null,null,2,14],[2023,0,5,null,null,null,2,9],[2023,0,17,null,null,null,2,9],[2022,0,17,null,null,null,2,14],[2024,0,17,null,null,null,2,5],[2022,0,6,null,null,null,2,14],[2022,0,23,null,null,null,2,14],[2023,0,23,null,null,null,2,9],[2024,0,23,null,null,null,2,5],[2022,0,25,null,null,null,2,14],[2022,0,18,null,null,null,2,14],[2024,0,18,null,null,null,2,5],[2023,0,18,null,null,null,2,9],[2023,0,19,null,null,null,2,9],[2022,0,19,null,null,null,2,14],[2024,0,19,null,null,null,2,5],[2024,0,11,null,null,null,2,5],[2023,0,11,null,null,null,2,9],[2022,0,11,null,null,null,2,14],[2022,0,12,null,null,null,2,14],[2024,0,12,null,null,null,2,5],[2023,0,12,null,null,null,2,9],[2023,0,20,null,null,null,2,9],[2022,0,20,null,null,null,2,14],[2024,0,20,null,null,null,2,5],[2024,0,21,null,null,null,2,5],[2023,0,21,null,null,null,2,9],[2022,0,21,null,null,null,2,14],[2024,1,13,null,null,null,2,1],[2022,1,13,null,null,null,2,12],[2023,1,13,null,null,null,2,7],[2023,1,0,66.7,14,21,1,7],[2024,1,0,60,15,25,1,1],[2022,1,0,73.4,58,79,0,12],[2022,1,14,null,null,null,2,12],[2023,1,14,null,null,null,2,7],[2024,1,14,null,null,null,2,1],[2024,1,15,null,null,null,2,1],[2022,1,15,null,null,null,2,12],[2023,1,15,null,null,null,2,7],[2023,1,2,null,null,null,2,7],[2024,1,2,null,null,null,2,1],[2022,1,2,66.7,8,12,1,12],[2022,1,22,90.5,19,21,1,12],[2023,1,22,null,null,null,2,7],[2024,1,22,null,null,null,2,1],[2024,1,16,null,null,null,2,1],[2022,1,16,null,null,null,2,12],[2023,1,16,null,null,null,2,7],[2023,1,5,null,null,null,2,7],[2024,1,5,null,null,null,2,1],[2022,1,5,60,9,15,1,12],[2022,1,26,27.3,3,11,1,12],[2023,1,26,null,null,null,2,7],[2024,1,26,null,null,null,2,1],[2024,1,27,null,null,null,2,1],[2022,1,27,63.6,7,11,1,12],[2023,1,27,null,null,null,2,7],[2023,1,28,null,null,null,2,7],[2024,1,28,null,null,null,2,1],[2022,1,28,80,20,25,1,12],[2022,1,29,90.3,28,31,0,12],[2023,1,29,null,null,null,2,7],[2024,1,29,null,null,null,2,1],[2024,1,30,43.8,7,16,1,1],[2022,1,30,62.5,30,48,0,12],[2023,1,30,70,14,20,1,7],[2022,1,31,null,null,null,2,12],[2022,1,17,68,17,25,1,12],[2024,1,17,null,null,null,2,1],[2023,1,17,null,null,null,2,7],[2023,1,6,null,null,null,2,7],[2022,1,6,94.1,16,17,1,12],[2024,1,6,null,null,null,2,1],[2024,1,23,57.9,11,19,1,1],[2023,1,23,71.4,10,14,1,7],[2022,1,23,67.2,39,58,0,12],[2022,1,18,null,null,null,2,12],[2024,1,18,null,null,null,2,1],[2023,1,18,null,null,null,2,7],[2023,1,19,null,null,null,2,7],[2022,1,19,null,null,null,2,12],[2024,1,19,null,null,null,2,1],[2024,1,11,61.9,13,21,1,1],[2023,1,11,66.7,14,21,1,7],[2022,1,11,76.2,48,63,0,12],[2022,1,12,73.4,58,79,0,12],[2024,1,12,60,15,25,1,1],[2023,1,12,66.7,14,21,1,7],[2023,1,20,null,null,null,2,7],[2022,1,20,null,null,null,2,12],[2024,1,20,null,null,null,2,1],[2024,1,21,54.5,6,11,1,1],[2023,1,21,54.5,6,11,1,7],[2022,1,21,75,30,40,0,12],[2024,2,0,null,null,6,2,2],[2022,2,0,-239.6,null,32,0,15],[2023,2,0,null,null,7,2,10],[2023,2,1,null,null,1,2,10],[2023,2,14,null,null,0,3,10],[2024,2,14,null,null,0,3,2],[2022,2,14,null,null,3,2,15],[2022,2,2,null,null,3,2,15],[2023,2,2,null,null,2,2,10],[2024,2,2,null,null,1,2,2],[2022,2,3,null,null,2,2,15],[2023,2,3,null,null,2,2,10],[2023,2,4,null,null,5,2,10],[2024,2,4,null,null,5,2,2],[2022,2,4,-246.7,null,30,0,15],[2022,2,5,null,null,4,2,15],[2023,2,5,null,null,2,2,10],[2024,2,5,null,null,0,3,2],[2024,2,17,null,null,2,2,2],[2022,2,17,null,null,10,2,15],[2023,2,17,null,null,3,2,10],[2023,2,6,null,null,1,2,10],[2024,2,6,null,null,1,2,2],[2022,2,6,null,null,7,2,15],[2023,2,7,null,null,2,2,10],[2022,2,9,null,null,1,2,15],[2024,2,9,null,null,1,2,2],[2024,2,10,null,null,6,2,2],[2023,2,10,null,null,5,2,10],[2022,2,10,-175.7,null,19,1,15],[2022,2,11,-258.3,null,27,1,15],[2024,2,11,null,null,4,2,2],[2023,2,11,null,null,6,2,10],[2023,2,12,null,null,7,2,10],[2022,2,12,-239.6,null,32,0,15],[2024,2,12,null,null,6,2,2],[2024,2,20,null,null,1,2,2],[2023,2,20,null,null,0,3,10],[2022,2,20,null,null,2,2,15],[2022,2,21,-268.1,null,18,1,15],[2024,2,21,null,null,3,2,2],[2023,2,21,null,null,4,2,10],[2023,3,13,null,null,null,2,9],[2022,3,13,null,null,null,2,14],[2024,3,13,null,null,null,2,5],[2024,3,0,null,null,null,2,5],[2022,3,0,null,null,null,2,14],[2023,3,0,null,null,null,2,9],[2023,3,14,null,null,null,2,9],[2022,3,14,null,null,null,2,14],[2024,3,14,null,null,null,2,5],[2022,3,15,null,null,null,2,14],[2023,3,15,null,null,null,2,9],[2024,3,15,null,null,null,2,5],[2022,3,2,null,null,null,2,14],[2024,3,2,null,null,null,2,5],[2022,3,22,null,null,null,2,14],[2023,3,22,null,null,null,2,9],[2023,3,16,null,null,null,2,9],[2024,3,16,null,null,null,2,5],[2022,3,16,null,null,null,2,14],[2022,3,5,null,null,null,2,14],[2023,3,5,null,null,null,2,9],[2023,3,17,null,null,null,2,9],[2022,3,17,null,null,null,2,14],[2024,3,17,null,null,null,2,5],[2022,3,6,null,null,null,2,14],[2022,3,23,null,null,null,2,14],[2023,3,23,null,null,null,2,9],[2024,3,23,null,null,null,2,5],[2022,3,25,null,null,null,2,14],[2022,3,18,null,null,null,2,14],[2024,3,18,null,null,null,2,5],[2023,3,18,null,null,null,2,9],[2023,3,19,null,null,null,2,9],[2022,3,19,null,null,null,2,14],[2024,3,19,null,null,null,2,5],[2024,3,11,null,null,null,2,5],[2023,3,11,null,null,null,2,9],[2022,3,11,null,null,null,2,14],[2022,3,12,null,null,null,2,14],[2024,3,12,null,null,null,2,5],[2023,3,12,null,null,null,2,9],[2023,3,20,null,null,null,2,9],[2022,3,20,null,null,null,2,14],[2024,3,20,null,null,null,2,5],[2024,3,21,null,null,null,2,5],[2023,3,21,null,null,null,2,9],[2022,3,21,null,null,null,2,14],[2022,4,13,null,null,null,2,14],[2024,4,13,null,null,null,2,5],[2023,4,13,null,null,null,2,9],[2023,4,0,null,null,null,2,9],[2022,4,0,null,null,null,2,14],[2024,4,0,null,null,null,2,5],[2024,4,14,null,null,null,2,5],[2023,4,14,null,null,null,2,9],[2022,4,14,null,null,null,2,14],[2022,4,15,null,null,null,2,14],[2024,4,15,null,null,null,2,5],[2023,4,15,null,null,null,2,9],[2022,4,2,null,null,null,2,14],[2024,4,2,null,null,null,2,5],[2023,4,22,null,null,null,2,9],[2022,4,22,null,null,null,2,14],[2022,4,16,null,null,null,2,14],[2024,4,16,null,null,null,2,5],[2023,4,16,null,null,null,2,9],[2023,4,5,null,null,null,2,9],[2022,4,5,null,null,null,2,14],[2022,4,17,null,null,null,2,14],[2023,4,17,null,null,null,2,9],[2024,4,17,null,null,null,2,5],[2022,4,6,null,null,null,2,14],[2022,4,23,null,null,null,2,14],[2024,4,23,null,null,null,2,5],[2023,4,23,null,null,null,2,9],[2022,4,25,null,null,null,2,14],[2022,4,18,null,null,null,2,14],[2023,4,18,null,null,null,2,9],[2024,4,18,null,null,null,2,5],[2024,4,19,null,null,null,2,5],[2022,4,19,null,null,null,2,14],[2023,4,19,null,null,null,2,9],[2023,4,11,null,null,null,2,9],[2024,4,11,null,null,null,2,5],[2022,4,11,null,null,null,2,14],[2022,4,12,null,null,null,2,14],[2023,4,12,null,null,null,2,9],[2024,4,12,null,null,null,2,5],[2024,4,20,null,null,null,2,5],[2022,4,20,null,null,null,2,14],[2023,4,20,null,null,null,2,9],[2023,4,21,null,null,null,2,9],[2024,4,21,null,null,null,2,5],[2022,4,21,null,null,null,2,14],[2022,5,0,-290.6,null,32,0,16],[2023,5,0,null,null,6,2,11],[2024,5,0,null,null,6,2,3],[2023,5,1,null,null,1,2,11],[2023,5,14,null,null,0,3,11],[2022,5,14,null,null,2,2,16],[2024,5,14,null,null,0,3,3],[2024,5,2,null,null,1,2,3],[2023,5,2,null,null,2,2,11],[2022,5,2,null,null,4,2,16],[2022,5,3,null,null,3,2,16],[2023,5,3,null,null,2,2,11],[2023,5,4,null,null,4,2,11],[2024,5,4,null,null,5,2,3],[2022,5,4,-297.3,null,29,1,16],[2022,5,5,null,null,5,2,16],[2023,5,5,null,null,1,2,11],[2024,5,5,null,null,0,3,3],[2024,5,17,null,null,2,2,3],[2022,5,17,-249.5,null,11,1,16],[2023,5,17,null,null,3,2,11],[2023,5,6,null,null,1,2,11],[2024,5,6,null,null,1,2,3],[2022,5,6,null,null,7,2,16],[2023,5,7,null,null,2,2,11],[2022,5,9,null,null,1,2,16],[2024,5,9,null,null,1,2,3],[2024,5,10,null,null,6,2,3],[2023,5,10,null,null,5,2,11],[2022,5,10,-216.8,null,14,1,16],[2022,5,11,-306.6,null,27,1,16],[2024,5,11,null,null,4,2,3],[2023,5,11,null,null,5,2,11],[2023,5,12,null,null,6,2,11],[2022,5,12,-290.6,null,32,0,16],[2024,5,12,null,null,6,2,3],[2024,5,20,null,null,1,2,3],[2023,5,20,null,null,0,3,11],[2022,5,20,null,null,2,2,16],[2022,5,21,-316.6,null,18,1,16],[2024,5,21,null,null,3,2,3],[2023,5,21,null,null,3,2,11],[2022,6,13,null,null,null,2,13],[2024,6,13,null,null,null,2,4],[2023,6,13,null,null,null,2,8],[2023,6,0,19.2,5,26,1,8],[2024,6,0,25,7,28,1,4],[2022,6,0,25.9,21,81,0,13],[2022,6,14,null,null,null,2,13],[2024,6,14,null,null,null,2,4],[2023,6,14,null,null,null,2,8],[2023,6,15,null,null,null,2,8],[2024,6,15,null,null,null,2,4],[2022,6,15,null,null,null,2,13],[2022,6,2,16.7,2,12,1,13],[2024,6,2,null,null,null,2,4],[2023,6,2,null,null,null,2,8],[2023,6,22,null,null,null,2,8],[2024,6,22,null,null,null,2,4],[2022,6,22,31.8,7,22,1,13],[2022,6,16,null,null,null,2,13],[2024,6,16,null,null,null,2,4],[2023,6,16,null,null,null,2,8],[2023,6,5,null,null,null,2,8],[2024,6,5,null,null,null,2,4],[2022,6,5,12.5,2,16,1,13],[2022,6,17,20,5,25,1,13],[2024,6,17,null,null,null,2,4],[2023,6,17,null,null,null,2,8],[2023,6,6,null,null,null,2,8],[2024,6,6,null,null,null,2,4],[2022,6,6,23.5,4,17,1,13],[2022,6,23,23.7,14,59,0,13],[2024,6,23,28.6,6,21,1,4],[2023,6,23,23.5,4,17,1,8],[2023,6,18,null,null,null,2,8],[2024,6,18,null,null,null,2,4],[2022,6,18,null,null,null,2,13],[2022,6,19,null,null,null,2,13],[2024,6,19,null,null,null,2,4],[2023,6,19,null,null,null,2,8],[2023,6,11,20,5,25,1,8],[2024,6,11,20.8,5,24,1,4],[2022,6,11,25,16,64,0,13],[2022,6,12,25.9,21,81,0,13],[2024,6,12,25,7,28,1,4],[2023,6,12,19.2,5,26,1,8],[2023,6,20,null,null,null,2,8],[2024,6,20,null,null,null,2,4],[2022,6,20,null,null,null,2,13],[2022,6,21,28.6,12,42,0,13],[2024,6,21,16.7,2,12,1,4],[2023,6,21,14.3,2,14,1,8]]},"23102312330447":{"demographics":{"African American":{"count":0,"percent":0.0},"American Indian":{"count":3,"percent":15.8},"Asian":{"count":0,"percent":0.0},"English Learner":{"count":4,"percent":21.1},"Filipino":{"count":0,"percent":0.0},"Foster":{"count":1,"percent":5.3},"Free/Reduced Meal Eligible":{"count":15,"percent":78.9},"Hispanic":{"count":13,"percent":68.4},"Homeless":{"count":1,"percent":5.3},"Migrant":{"count":0,"percent":0.0},"Not Reported":{"count":0,"percent":0.0},"Pacific Islander":{"count":0,"percent":0.0},"Socioeconomically Disadvantaged":{"count":15,"percent":78.9},"Students with Disabilities":{"count":5,"percent":26.3},"Two or More Races":{"count":1,"percent":5.3},"White":{"count":2,"percent":10.5}},"observations":[[2024,0,13,null,null,null,2,5],[2022,0,13,null,null,null,2,14],[2023,0,13,null,null,null,2,9],[2024,0,0,null,null,null,2,5],[2022,0,0,null,null,null,2,14],[2022,0,14,null,null,null,2,14],[2023,0,14,null,null,null,2,9],[2024,0,14,null,null,null,2,5],[2024,0,15,null,null,null,2,5],[2022,0,15,null,null,null,2,14],[2023,0,15,null,null,null,2,9],[2024,0,2,null,null,null,2,5],[2024,0,16,null,null,null,2,5],[2023,0,16,null,null,null,2,9],[2022,0,16,null,null,null,2,14],[2022,0,17,null,null,null,2,14],[2024,0,17,null,null,null,2,5],[2023,0,17,null,null,null,2,9],[2022,0,6,null,null,null,2,14],[2024,0,6,null,null,null,2,5],[2024,0,23,null,null,null,2,5],[2022,0,23,null,null,null,2,14],[2024,0,8,null,null,null,2,5],[2024,0,18,null,null,null,2,5],[2023,0,18,null,null,null,2,9],[2022,0,18,null,null,null,2,14],[2022,0,19,null,null,null,2,14],[2024,0,19,null,null,null,2,5],[2023,0,19,null,null,null,2,9],[2022,0,11,null,null,null,2,14],[2024,0,11,null,null,null,2,5],[2024,0,12,null,null,null,2,5],[2022,0,12,null,null,null,2,14],[2022,0,20,null,null,null,2,14],[2023,0,20,null,null,null,2,9],[2024,0,20,null,null,null,2,5],[2024,0,21,null,null,null,2,5],[2022,0,21,null,null,null,2,14],[2023,0,21,null,null,null,2,9],[2024,1,13,null,null,null,2,1],[2023,1,13,null,null,null,2,7],[2022,1,13,null,null,null,2,12],[2022,1,0,68.8,22,32,0,12],[2024,1,0,77.8,28,36,0,1],[2023,1,0,75,21,28,1,7],[2023,1,14,null,null,null,2,7],[2022,1,14,null,null,null,2,12],[2024,1,14,null,null,null,2,1],[2024,1,15,null,null,null,2,1],[2023,1,15,null,null,null,2,7],[2022,1,15,null,null,null,2,12],[2022,1,2,null,null,null,2,12],[2024,1,2,null,null,null,2,1],[2023,1,2,null,null,null,2,7],[2023,1,22,null,null,null,2,7],[2022,1,22,null,null,null,2,12],[2024,1,22,null,null,null,2,1],[2024,1,16,null,null,null,2,1],[2023,1,16,null,null,null,2,7],[2022,1,16,null,null,null,2,12],[2022,1,5,null,null,null,2,12],[2024,1,5,null,null,null,2,1],[2023,1,5,null,null,null,2,7],[2024,1,27,null,null,null,2,1],[2024,1,28,null,null,null,2,1],[2022,1,28,78.6,11,14,1,12],[2023,1,28,null,null,null,2,7],[2023,1,29,73.7,14,19,1,7],[2024,1,29,75,21,28,1,1],[2022,1,29,61.1,11,18,1,12],[2022,1,30,78.6,11,14,1,12],[2023,1,30,null,null,null,2,7],[2024,1,30,null,null,null,2,1],[2024,1,17,77.8,14,18,1,1],[2022,1,17,63.6,14,22,1,12],[2023,1,17,72.2,13,18,1,7],[2023,1,6,null,null,null,2,7],[2024,1,6,null,null,null,2,1],[2022,1,6,null,null,null,2,12],[2022,1,23,60.9,14,23,1,12],[2023,1,23,73.7,14,19,1,7],[2024,1,23,84.6,22,26,1,1],[2023,1,8,null,null,null,2,7],[2023,1,18,null,null,null,2,7],[2022,1,18,null,null,null,2,12],[2024,1,18,null,null,null,2,1],[2024,1,19,null,null,null,2,1],[2023,1,19,null,null,null,2,7],[2022,1,19,null,null,null,2,12],[2022,1,11,68.8,22,32,0,12],[2024,1,11,81.3,26,32,0,1],[2023,1,11,77.8,21,27,1,7],[2023,1,12,null,null,null,2,7],[2022,1,12,84.6,11,13,1,12],[2024,1,12,null,null,null,2,1],[2024,1,20,null,null,null,2,1],[2023,1,20,null,null,null,2,7],[2022,1,20,null,null,null,2,12],[2022,1,21,null,null,null,2,12],[2024,1,21,null,null,null,2,1],[2023,1,21,null,null,null,2,7],[2024,2,13,null,null,0,3,2],[2024,2,0,null,null,4,2,2],[2023,2,0,null,null,6,2,10],[2022,2,0,null,null,3,2,15],[2024,2,14,null,null,1,2,2],[2024,2,2,null,null,0,3,2],[2022,2,2,null,null,2,2,15],[2023,2,2,null,null,2,2,10],[2023,2,3,null,null,1,2,10],[2024,2,3,null,null,0,3,2],[2022,2,3,null,null,2,2,15],[2022,2,4,null,null,1,2,15],[2023,2,4,null,null,4,2,10],[2024,2,4,null,null,4,2,2],[2024,2,5,null,null,1,2,2],[2024,2,17,null,null,0,3,2],[2022,2,17,null,null,2,2,15],[2023,2,17,null,null,4,2,10],[2023,2,6,null,null,0,3,10],[2024,2,6,null,null,3,2,2],[2022,2,6,null,null,1,2,15],[2023,2,7,null,null,1,2,10],[2024,2,7,null,null,0,3,2],[2022,2,9,null,null,0,3,15],[2023,2,9,null,null,1,2,10],[2023,2,10,null,null,2,2,10],[2024,2,10,null,null,2,2,2],[2022,2,10,null,null,1,2,15],[2022,2,11,null,null,3,2,15],[2023,2,11,null,null,5,2,10],[2024,2,11,null,null,4,2,2],[2024,2,12,null,null,1,2,2],[2022,2,12,null,null,0,3,15],[2023,2,12,null,null,2,2,10],[2022,2,20,null,null,0,3,15],[2022,2,21,null,null,1,2,15],[2024,2,21,null,null,3,2,2],[2023,2,21,null,null,2,2,10],[2023,3,13,null,null,null,2,9],[2022,3,13,null,null,null,2,14],[2024,3,13,null,null,null,2,5],[2024,3,0,null,null,null,2,5],[2022,3,0,null,null,null,2,14],[2022,3,14,null,null,null,2,14],[2024,3,14,null,null,null,2,5],[2023,3,14,null,null,null,2,9],[2023,3,15,null,null,null,2,9],[2024,3,15,null,null,null,2,5],[2022,3,15,null,null,null,2,14],[2024,3,2,null,null,null,2,5],[2024,3,16,null,null,null,2,5],[2022,3,16,null,null,null,2,14],[2023,3,16,null,null,null,2,9],[2023,3,17,null,null,null,2,9],[2022,3,17,null,null,null,2,14],[2024,3,17,null,null,null,2,5],[2024,3,6,null,null,null,2,5],[2022,3,6,null,null,null,2,14],[2022,3,23,null,null,null,2,14],[2024,3,23,null,null,null,2,5],[2024,3,8,null,null,null,2,5],[2024,3,18,null,null,null,2,5],[2022,3,18,null,null,null,2,14],[2023,3,18,null,null,null,2,9],[2023,3,19,null,null,null,2,9],[2022,3,19,null,null,null,2,14],[2024,3,19,null,null,null,2,5],[2024,3,11,null,null,null,2,5],[2022,3,11,null,null,null,2,14],[2022,3,12,null,null,null,2,14],[2024,3,12,null,null,null,2,5],[2024,3,20,null,null,null,2,5],[2022,3,20,null,null,null,2,14],[2023,3,20,null,null,null,2,9],[2023,3,21,null,null,null,2,9],[2022,3,21,null,null,null,2,14],[2024,3,21,null,null,null,2,5],[2024,4,13,null,null,null,2,5],[2022,4,13,null,null,null,2,14],[2023,4,13,null,null,null,2,9],[2022,4,0,null,null,null,2,14],[2024,4,0,null,null,null,2,5],[2024,4,14,null,null,null,2,5],[2022,4,14,null,null,null,2,14],[2023,4,14,null,null,null,2,9],[2023,4,15,null,null,null,2,9],[2022,4,15,null,null,null,2,14],[2024,4,15,null,null,null,2,5],[2024,4,2,null,null,null,2,5],[2024,4,16,null,null,null,2,5],[2022,4,16,null,null,null,2,14],[2023,4,16,null,null,null,2,9],[2023,4,17,null,null,null,2,9],[2022,4,17,null,null,null,2,14],[2024,4,17,null,null,null,2,5],[2024,4,6,null,null,null,2,5],[2022,4,6,null,null,null,2,14],[2022,4,23,null,null,null,2,14],[2024,4,23,null,null,null,2,5],[2024,4,8,null,null,null,2,5],[2024,4,18,null,null,null,2,5],[2022,4,18,null,null,null,2,14],[2023,4,18,null,null,null,2,9],[2023,4,19,null,null,null,2,9],[2022,4,19,null,null,null,2,14],[2024,4,19,null,null,null,2,5],[2024,4,11,null,null,null,2,5],[2022,4,11,null,null,null,2,14],[2022,4,12,null,null,null,2,14],[2024,4,12,null,null,null,2,5],[2024,4,20,null,null,null,2,5],[2022,4,20,null,null,null,2,14],[2023,4,20,null,null,null,2,9],[2023,4,21,null,null,null,2,9],[2022,4,21,null,null,null,2,14],[2024,4,21,null,null,null,2,5],[2024,5,13,null,null,0,3,3],[2024,5,0,null,null,4,2,3],[2022,5,0,null,null,4,2,16],[2023,5,0,null,null,4,2,11],[2024,5,14,null,null,1,2,3],[2024,5,2,null,null,0,3,3],[2023,5,2,null,null,2,2,11],[2022,5,2,null,null,3,2,16],[2022,5,3,null,null,3,2,16],[2023,5,3,null,null,1,2,11],[2024,5,3,null,null,0,3,3],[2024,5,4,null,null,4,2,3],[2023,5,4,null,null,2,2,11],[2022,5,4,null,null,1,2,16],[2024,5,5,null,null,1,2,3],[2024,5,17,null,null,0,3,3],[2022,5,17,null,null,3,2,16],[2023,5,17,null,null,2,2,11],[2023,5,6,null,null,0,3,11],[2022,5,6,null,null,1,2,16],[2024,5,6,null,null,3,2,3],[2024,5,7,null,null,0,3,3],[2023,5,7,null,null,1,2,11],[2023,5,9,null,null,1,2,11],[2022,5,9,null,null,0,3,16],[2022,5,10,null,null,1,2,16],[2023,5,10,null,null,2,2,11],[2024,5,10,null,null,2,2,3],[2024,5,11,null,null,4,2,3],[2023,5,11,null,null,4,2,11],[2022,5,11,null,null,4,2,16],[2022,5,12,null,null,1,2,16],[2023,5,12,null,null,2,2,11],[2024,5,12,null,null,1,2,3],[2022,5,20,null,null,0,3,16],[2022,5,21,null,null,1,2,16],[2024,5,21,null,null,3,2,3],[2023,5,21,null,null,2,2,11],[2024,6,13,null,null,null,2,4],[2022,6,13,null,null,null,2,13],[2023,6,13,null,null,null,2,8],[2023,6,0,38.7,12,31,0,8],[2024,6,0,37.8,14,37,0,4],[2022,6,0,40.5,15,37,0,13],[2022,6,14,null,null,null,2,13],[2023,6,14,null,null,null,2,8],[2024,6,14,null,null,null,2,4],[2024,6,15,null,null,null,2,4],[2022,6,15,null,null,null,2,13],[2023,6,15,null,null,null,2,8],[2023,6,2,null,null,null,2,8],[2024,6,2,null,null,null,2,4],[2022,6,2,25,3,12,1,13],[2022,6,22,45.5,5,11,1,13],[2023,6,22,null,null,null,2,8],[2024,6,22,54.5,6,11,1,4],[2024,6,16,null,null,null,2,4],[2022,6,16,null,null,null,2,13],[2023,6,16,null,null,null,2,8],[2023,6,5,null,null,null,2,8],[2024,6,5,null,null,null,2,4],[2022,6,5,null,null,null,2,13],[2022,6,17,37.5,9,24,1,13],[2023,6,17,33.3,7,21,1,8],[2024,6,17,31.6,6,19,1,4],[2024,6,6,null,null,null,2,4],[2022,6,6,null,null,null,2,13],[2023,6,6,null,null,null,2,8],[2023,6,23,42.9,9,21,1,8],[2024,6,23,30.8,8,26,1,4],[2022,6,23,38.5,10,26,1,13],[2023,6,8,null,null,null,2,8],[2023,6,18,null,null,null,2,8],[2022,6,18,null,null,null,2,13],[2024,6,18,null,null,null,2,4],[2024,6,19,null,null,null,2,4],[2023,6,19,null,null,null,2,8],[2022,6,19,null,null,null,2,13],[2022,6,11,40.5,15,37,0,13],[2024,6,11,33.3,11,33,0,4],[2023,6,11,36.7,11,30,0,8],[2023,6,12,null,null,null,2,8],[2022,6,12,40,6,15,1,13],[2024,6,12,null,null,null,2,4],[2024,6,20,null,null,null,2,4],[2023,6,20,null,null,null,2,8],[2022,6,20,null,null,null,2,13],[2022,6,21,null,null,null,2,13],[2024,6,21,null,null,null,2,4],[2023,6,21,null,null,null,2,8]]},"23655652330215":{"demographics":{"African American":{"count":0,"percent":0.0},"American Indian":{"count":1,"percent":4.3},"Asian":{"count":0,"percent":0.0},"English Learner":{"count":7,"percent":30.4},"Filipino":{"count":0,"percent":0.0},"Foster":{"count":1,"percent":4.3},"Free/Reduced Meal Eligible":{"count":19,"percent":82.6},"Hispanic":{"count":14,"percent":60.9},"Homeless":{"count":1,"percent":4.3},"Migrant":{"count":2,"percent":8.7},"Not Reported":{"count":0,"percent":0.0},"Pacific Islander":{"count":0,"percent":0.0},"Socioeconomically Disadvantaged":{"count":19,"percent":82.6},"Students with Disabilities":{"count":3,"percent":13.0},"Two or More Races":{"count":2,"percent":8.7},"White":{"count":6,"percent":26.1}},"observations":[[2024,0,13,null,null,null,2,5],[2023,0,13,null,null,null,2,9],[2022,0,13,null,null,null,2,14],[2022,0,0,0,0,10,1,14],[2023,0,0,0,0,8,1,9],[2024,0,0,0,0,10,1,5],[2024,0,14,null,null,null,2,5],[2023,0,14,null,null,null,2,9],[2022,0,14,null,null,null,2,14],[2022,0,15,null,null,null,2,14],[2023,0,15,null,null,null,2,9],[2024,0,15,null,null,null,2,5],[2024,0,2,null,null,null,2,5],[2023,0,2,null,null,null,2,9],[2022,0,2,null,null,null,2,14],[2022,0,22,null,null,null,2,14],[2023,0,22,null,null,null,2,9],[2024,0,22,0,0,7,1,5],[2024,0,16,null,null,null,2,5],[2023,0,16,null,null,null,2,9],[2022,0,16,null,null,null,2,14],[2022,0,5,null,null,null,2,14],[2023,0,5,null,null,null,2,9],[2024,0,5,null,null,null,2,5],[2024,0,17,null,null,null,2,5],[2023,0,17,null,null,null,2,9],[2022,0,17,null,null,null,2,14],[2022,0,6,null,null,null,2,14],[2023,0,6,null,null,null,2,9],[2024,0,6,null,null,null,2,5],[2024,0,23,null,null,null,2,5],[2023,0,23,0,0,5,1,9],[2022,0,23,0,0,8,1,14],[2022,0,8,null,null,null,2,14],[2024,0,8,null,null,null,2,5],[2024,0,18,null,null,null,2,5],[2022,0,18,null,null,null,2,14],[2023,0,18,null,null,null,2,9],[2023,0,19,null,null,null,2,9],[2022,0,19,null,null,null,2,14],[2024,0,19,null,null,null,2,5],[2024,0,11,0,0,10,1,5],[2022,0,11,0,0,10,1,14],[2023,0,11,0,0,8,1,9],[2023,0,12,null,null,null,2,9],[2022,0,12,null,null,null,2,14],[2024,0,12,null,null,null,2,5],[2024,0,20,null,null,null,2,5],[2022,0,20,null,null,null,2,14],[2023,0,20,null,null,null,2,9],[2023,0,21,null,null,null,2,9],[2022,0,21,null,null,null,2,14],[2024,0,21,0,0,6,1,5],[2024,1,13,null,null,null,2,1],[2022,1,13,null,null,null,2,12],[2023,1,13,null,null,null,2,7],[2023,1,0,91.7,33,36,0,7],[2022,1,0,90,36,40,0,12],[2024,1,0,97,32,33,0,1],[2024,1,14,null,null,null,2,1],[2022,1,14,null,null,null,2,12],[2023,1,14,null,null,null,2,7],[2023,1,15,null,null,null,2,7],[2022,1,15,null,null,null,2,12],[2024,1,15,null,null,null,2,1],[2024,1,2,null,null,null,2,1],[2022,1,2,null,null,null,2,12],[2023,1,2,null,null,null,2,7],[2023,1,22,100,16,16,1,7],[2022,1,22,100,16,16,1,12],[2024,1,22,100,17,17,1,1],[2024,1,16,null,null,null,2,1],[2022,1,16,null,null,null,2,12],[2023,1,16,null,null,null,2,7],[2023,1,5,null,null,null,2,7],[2022,1,5,null,null,null,2,12],[2024,1,5,null,null,null,2,1],[2024,1,29,97,32,33,0,1],[2022,1,29,90,36,40,0,12],[2023,1,29,91.7,33,36,0,7],[2023,1,17,null,null,null,2,7],[2022,1,17,null,null,null,2,12],[2024,1,17,null,null,null,2,1],[2024,1,6,null,null,null,2,1],[2023,1,6,null,null,null,2,7],[2023,1,23,85,17,20,1,7],[2024,1,23,93.3,14,15,1,1],[2022,1,23,83.3,20,24,1,12],[2024,1,8,null,null,null,2,1],[2024,1,25,null,null,null,2,1],[2024,1,18,null,null,null,2,1],[2022,1,18,null,null,null,2,12],[2023,1,18,null,null,null,2,7],[2023,1,19,null,null,null,2,7],[2022,1,19,null,null,null,2,12],[2024,1,19,null,null,null,2,1],[2024,1,11,96.8,30,31,0,1],[2022,1,11,88.2,30,34,0,12],[2023,1,11,89.3,25,28,1,7],[2023,1,12,null,null,null,2,7],[2022,1,12,null,null,null,2,12],[2024,1,12,null,null,null,2,1],[2024,1,20,null,null,null,2,1],[2022,1,20,null,null,null,2,12],[2023,1,20,null,null,null,2,7],[2023,1,21,93.3,14,15,1,7],[2022,1,21,94.4,17,18,1,12],[2024,1,21,94.1,16,17,1,1],[2024,2,0,null,null,10,2,2],[2023,2,0,-157,null,12,1,10],[2022,2,0,null,null,6,2,15],[2024,2,14,null,null,2,2,2],[2024,2,4,null,null,9,2,2],[2022,2,4,null,null,5,2,15],[2023,2,4,null,null,10,2,10],[2023,2,5,null,null,0,3,10],[2024,2,5,null,null,1,2,2],[2024,2,17,null,null,3,2,2],[2023,2,17,null,null,4,2,10],[2022,2,17,null,null,2,2,15],[2023,2,6,null,null,1,2,10],[2023,2,10,null,null,10,2,10],[2022,2,10,null,null,4,2,15],[2024,2,10,null,null,7,2,2],[2024,2,11,null,null,10,2,2],[2022,2,11,null,null,4,2,15],[2023,2,11,null,null,7,2,10],[2023,2,12,null,null,4,2,10],[2024,2,12,null,null,2,2,2],[2024,2,20,null,null,1,2,2],[2023,2,20,null,null,0,3,10],[2022,2,20,null,null,0,3,15],[2022,2,21,null,null,3,2,15],[2023,2,21,null,null,7,2,10],[2024,2,21,null,null,4,2,2],[2023,3,13,null,null,null,2,9],[2024,3,13,null,null,null,2,5],[2022,3,13,null,null,null,2,14],[2022,3,0,9.5,2,21,1,14],[2024,3,0,47.4,9,19,1,5],[2023,3,0,30,6,20,1,9],[2023,3,14,null,null,null,2,9],[2024,3,14,null,null,null,2,5],[2022,3,14,null,null,null,2,14],[2022,3,15,null,null,null,2,14],[2024,3,15,null,null,null,2,5],[2023,3,15,null,null,null,2,9],[2023,3,2,null,null,null,2,9],[2024,3,2,null,null,null,2,5],[2022,3,2,null,null,null,2,14],[2022,3,22,null,null,null,2,14],[2024,3,22,41.7,5,12,1,5],[2023,3,22,null,null,null,2,9],[2023,3,16,null,null,null,2,9],[2024,3,16,null,null,null,2,5],[2022,3,16,null,null,null,2,14],[2022,3,5,null,null,null,2,14],[2024,3,5,null,null,null,2,5],[2023,3,5,null,null,null,2,9],[2023,3,17,null,null,null,2,9],[2024,3,17,null,null,null,2,5],[2022,3,17,null,null,null,2,14],[2022,3,6,null,null,null,2,14],[2024,3,6,null,null,null,2,5],[2023,3,6,null,null,null,2,9],[2023,3,23,35.7,5,14,1,9],[2024,3,23,null,null,null,2,5],[2022,3,23,14.3,2,14,1,14],[2022,3,8,null,null,null,2,14],[2024,3,8,null,null,null,2,5],[2024,3,18,null,null,null,2,5],[2022,3,18,null,null,null,2,14],[2023,3,18,null,null,null,2,9],[2023,3,19,null,null,null,2,9],[2022,3,19,null,null,null,2,14],[2024,3,19,null,null,null,2,5],[2024,3,11,47.4,9,19,1,5],[2022,3,11,5.3,1,19,1,14],[2023,3,11,30,6,20,1,9],[2023,3,12,null,null,null,2,9],[2022,3,12,null,null,null,2,14],[2024,3,12,null,null,null,2,5],[2024,3,20,null,null,null,2,5],[2022,3,20,null,null,null,2,14],[2023,3,20,null,null,null,2,9],[2023,3,21,null,null,null,2,9],[2022,3,21,null,null,null,2,14],[2024,3,21,45.5,5,11,1,5],[2024,4,13,null,null,null,2,5],[2022,4,13,null,null,null,2,14],[2023,4,13,null,null,null,2,9],[2023,4,0,40,8,20,1,9],[2022,4,0,47.6,10,21,1,14],[2024,4,0,52.6,10,19,1,5],[2024,4,14,null,null,null,2,5],[2022,4,14,null,null,null,2,14],[2023,4,14,null,null,null,2,9],[2023,4,15,null,null,null,2,9],[2022,4,15,null,null,null,2,14],[2024,4,15,null,null,null,2,5],[2024,4,2,null,null,null,2,5],[2022,4,2,null,null,null,2,14],[2023,4,2,null,null,null,2,9],[2023,4,22,null,null,null,2,9],[2022,4,22,null,null,null,2,14],[2024,4,22,58.3,7,12,1,5],[2024,4,16,null,null,null,2,5],[2022,4,16,null,null,null,2,14],[2023,4,16,null,null,null,2,9],[2023,4,5,null,null,null,2,9],[2022,4,5,null,null,null,2,14],[2024,4,5,null,null,null,2,5],[2024,4,17,null,null,null,2,5],[2022,4,17,null,null,null,2,14],[2023,4,17,null,null,null,2,9],[2023,4,6,null,null,null,2,9],[2022,4,6,null,null,null,2,14],[2024,4,6,null,null,null,2,5],[2024,4,23,null,null,null,2,5],[2022,4,23,57.1,8,14,1,14],[2023,4,23,35.7,5,14,1,9],[2022,4,8,null,null,null,2,14],[2024,4,8,null,null,null,2,5],[2024,4,18,null,null,null,2,5],[2022,4,18,null,null,null,2,14],[2023,4,18,null,null,null,2,9],[2023,4,19,null,null,null,2,9],[2022,4,19,null,null,null,2,14],[2024,4,19,null,null,null,2,5],[2024,4,11,52.6,10,19,1,5],[2022,4,11,52.6,10,19,1,14],[2023,4,11,40,8,20,1,9],[2023,4,12,null,null,null,2,9],[2022,4,12,null,null,null,2,14],[2024,4,12,null,null,null,2,5],[2024,4,20,null,null,null,2,5],[2022,4,20,null,null,null,2,14],[2023,4,20,null,null,null,2,9],[2023,4,21,null,null,null,2,9],[2022,4,21,null,null,null,2,14],[2024,4,21,54.5,6,11,1,5],[2024,5,0,null,null,10,2,3],[2022,5,0,null,null,6,2,16],[2023,5,0,-256.5,null,13,1,11],[2024,5,14,null,null,2,2,3],[2023,5,2,null,null,1,2,11],[2023,5,3,null,null,1,2,11],[2023,5,4,null,null,10,2,11],[2024,5,4,null,null,9,2,3],[2022,5,4,null,null,5,2,16],[2024,5,5,null,null,1,2,3],[2023,5,5,null,null,0,3,11],[2023,5,17,null,null,5,2,11],[2024,5,17,null,null,3,2,3],[2022,5,17,null,null,2,2,16],[2023,5,6,null,null,1,2,11],[2023,5,10,null,null,10,2,11],[2022,5,10,null,null,3,2,16],[2024,5,10,null,null,6,2,3],[2024,5,11,null,null,10,2,3],[2022,5,11,null,null,4,2,16],[2023,5,11,null,null,8,2,11],[2023,5,12,null,null,4,2,11],[2024,5,12,null,null,2,2,3],[2024,5,20,null,null,1,2,3],[2023,5,20,null,null,0,3,11],[2022,5,20,null,null,0,3,16],[2022,5,21,null,null,3,2,16],[2023,5,21,null,null,7,2,11],[2024,5,21,null,null,4,2,3],[2024,6,13,null,null,null,2,4],[2022,6,13,null,null,null,2,13],[2023,6,13,null,null,null,2,8],[2023,6,0,8.1,3,37,0,8],[2022,6,0,10.6,5,47,0,13],[2024,6,0,0,0,37,0,4],[2024,6,14,null,null,null,2,4],[2022,6,14,null,null,null,2,13],[2023,6,14,null,null,null,2,8],[2023,6,15,null,null,null,2,8],[2022,6,15,null,null,null,2,13],[2024,6,15,null,null,null,2,4],[2024,6,2,null,null,null,2,4],[2022,6,2,null,null,null,2,13],[2023,6,2,null,null,null,2,8],[2023,6,22,6.3,1,16,1,8],[2022,6,22,5.6,1,18,1,13],[2024,6,22,0,0,19,1,4],[2024,6,16,null,null,null,2,4],[2022,6,16,null,null,null,2,13],[2023,6,16,null,null,null,2,8],[2023,6,5,null,null,null,2,8],[2022,6,5,null,null,null,2,13],[2024,6,5,null,null,null,2,4],[2024,6,17,0,0,11,1,4],[2022,6,17,25,3,12,1,13],[2023,6,17,null,null,null,2,8],[2023,6,6,null,null,null,2,8],[2024,6,6,null,null,null,2,4],[2024,6,23,0,0,17,1,4],[2023,6,23,9.5,2,21,1,8],[2022,6,23,13.8,4,29,1,13],[2024,6,8,null,null,null,2,4],[2024,6,25,null,null,null,2,4],[2024,6,18,null,null,null,2,4],[2022,6,18,null,null,null,2,13],[2023,6,18,null,null,null,2,8],[2023,6,19,null,null,null,2,8],[2022,6,19,null,null,null,2,13],[2024,6,19,null,null,null,2,4],[2024,6,11,0,0,34,0,4],[2022,6,11,13.2,5,38,0,13],[2023,6,11,10.3,3,29,1,8],[2023,6,12,null,null,null,2,8],[2022,6,12,null,null,null,2,13],[2024,6,12,null,null,null,2,4],[2024,6,20,null,null,null,2,4],[2022,6,20,null,null,null,2,13],[2023,6,20,null,null,null,2,8],[2023,6,21,0,0,15,1,8],[2022,6,21,9.5,2,21,1,13],[2024,6,21,0,0,19,1,4]]},"23655816025167":{"demographics":{"African American":{"count":0,"percent":0.0},"American Indian":{"count":1,"percent":0.5},"Asian":{"count":0,"percent":0.0},"English Learner":{"count":11,"percent":5.0},"Filipino":{"count":1,"percent":0.5},"Foster":{"count":0,"percent":0.0},"Free/Reduced Meal Eligible":{"count":150,"percent":67.6},"Hispanic":{"count":44,"percent":19.8},"Homeless":{"count":10,"percent":4.5},"Migrant":{"count":0,"percent":0.0},"Not Reported":{"count":4,"percent":1.8},"Pacific Islander":{"count":0,"percent":0.0},"Socioeconomically Disadvantaged":{"count":150,"percent":67.6},"Students with Disabilities":{"count":43,"percent":19.4},"Two or More Races":{"count":15,"percent":6.8},"White":{"count":157,"percent":70.7}},"observations":[[2024,1,13,null,null,null,2,1],[2023,1,13,null,null,null,2,7],[2022,1,13,null,null,null,2,12],[2022,1,0,53.1,137,258,0,12],[2023,1,0,32.7,83,254,0,7],[2024,1,0,27.2,66,243,0,1],[2024,1,14,null,null,null,2,1],[2023,1,14,null,null,null,2,7],[2022,1,14,null,null,null,2,12],[2022,1,15,null,null,null,2,12],[2023,1,15,null,null,null,2,7],[2024,1,15,null,null,null,2,1],[2024,1,2,15.4,2,13,1,1],[2023,1,2,20,3,15,1,7],[2022,1,2,41.2,7,17,1,12],[2022,1,22,54.2,64,118,0,12],[2023,1,22,31.2,34,109,0,7],[2024,1,22,23.1,25,108,0,1],[2024,1,16,null,null,null,2,1],[2023,1,16,null,null,null,2,7],[2022,1,16,null,null,null,2,12],[2024,1,5,null,null,null,2,1],[2024,1,26,26.3,15,57,0,1],[2022,1,26,47.2,25,53,0,12],[2023,1,26,30.2,19,63,0,7],[2023,1,27,25.8,24,93,0,7],[2022,1,27,47.4,46,97,0,12],[2024,1,27,20.7,18,87,0,1],[2024,1,28,32.9,24,73,0,1],[2022,1,28,56.3,45,80,0,12],[2023,1,28,44.7,34,76,0,7],[2023,1,30,32.7,83,254,0,7],[2022,1,30,53.1,137,258,0,12],[2024,1,30,27.2,66,243,0,1],[2024,1,31,34.6,9,26,1,1],[2022,1,31,75,21,28,1,12],[2023,1,31,27.3,6,22,1,7],[2023,1,17,18.2,8,44,0,7],[2022,1,17,50,24,48,0,12],[2024,1,17,11.6,5,43,0,1],[2024,1,6,22.2,4,18,1,1],[2022,1,6,85.7,12,14,1,12],[2023,1,6,36.4,8,22,1,7],[2023,1,23,34,49,144,0,7],[2022,1,23,51.8,72,139,0,12],[2024,1,23,30.6,41,134,0,1],[2024,1,8,null,null,null,2,1],[2024,1,25,null,null,null,2,1],[2022,1,25,null,null,null,2,12],[2023,1,25,null,null,null,2,7],[2023,1,18,null,null,null,2,7],[2022,1,18,null,null,null,2,12],[2024,1,18,null,null,null,2,1],[2024,1,19,null,null,null,2,1],[2022,1,19,null,null,null,2,12],[2023,1,19,null,null,null,2,7],[2023,1,11,36.1,75,208,0,7],[2022,1,11,56.2,95,169,0,12],[2024,1,11,32,56,175,0,1],[2024,1,12,28.3,13,46,0,1],[2022,1,12,57.8,26,45,0,12],[2023,1,12,44.9,22,49,0,7],[2023,1,20,25,3,12,1,7],[2022,1,20,null,null,null,2,12],[2024,1,20,21.4,3,14,1,1],[2024,1,21,30.9,56,181,0,1],[2022,1,21,52.9,101,191,0,12],[2023,1,21,36.8,71,193,0,7],[2022,2,13,null,null,1,2,15],[2022,2,0,-7.3,null,170,0,15],[2023,2,0,0.9,null,168,0,10],[2024,2,0,-0.2,null,168,0,2],[2024,2,1,null,null,2,2,2],[2022,2,1,null,null,5,2,15],[2023,2,1,null,null,2,2,10],[2022,2,15,null,null,1,2,15],[2022,2,2,-46.8,null,12,1,15],[2024,2,2,-73.8,null,12,1,2],[2023,2,2,-64.7,null,12,1,10],[2023,2,3,null,null,8,2,10],[2022,2,3,null,null,6,2,15],[2024,2,3,null,null,7,2,2],[2024,2,4,4.9,null,152,0,2],[2023,2,4,4.8,null,147,0,10],[2022,2,4,-9.8,null,151,0,15],[2022,2,16,null,null,1,2,15],[2023,2,16,null,null,1,2,10],[2023,2,17,-40,null,33,0,10],[2024,2,17,-61.9,null,31,0,2],[2022,2,17,-20.2,null,31,0,15],[2022,2,6,null,null,8,2,15],[2023,2,6,-59.6,null,16,1,10],[2024,2,6,-79,null,14,1,2],[2024,2,7,null,null,3,2,2],[2023,2,7,null,null,2,2,10],[2023,2,9,null,null,4,2,10],[2022,2,9,null,null,6,2,15],[2024,2,9,null,null,5,2,2],[2024,2,10,-0.7,null,166,0,2],[2023,2,10,-0.1,null,166,0,10],[2022,2,10,-6.2,null,164,0,15],[2022,2,11,-23.7,null,112,0,15],[2024,2,11,-5,null,118,0,2],[2023,2,11,-4.6,null,142,0,10],[2023,2,12,-114.5,null,29,1,10],[2022,2,12,-88.8,null,31,0,15],[2024,2,12,-86.7,null,33,0,2],[2024,2,20,null,null,9,2,2],[2023,2,20,null,null,6,2,10],[2022,2,20,null,null,6,2,15],[2022,2,21,-5,null,128,0,15],[2024,2,21,12.5,null,126,0,2],[2023,2,21,10.4,null,127,0,10],[2022,5,13,null,null,1,2,16],[2022,5,0,-36.8,null,170,0,16],[2023,5,0,-20.3,null,168,0,11],[2024,5,0,-21.5,null,168,0,3],[2024,5,1,null,null,2,2,3],[2023,5,1,null,null,2,2,11],[2022,5,1,null,null,5,2,16],[2022,5,15,null,null,1,2,16],[2022,5,2,-50.3,null,12,1,16],[2023,5,2,-116.3,null,12,1,11],[2024,5,2,-113.4,null,12,1,3],[2024,5,3,null,null,7,2,3],[2023,5,3,null,null,8,2,11],[2022,5,3,null,null,6,2,16],[2022,5,4,-42.4,null,151,0,16],[2023,5,4,-13.1,null,147,0,11],[2024,5,4,-12.3,null,152,0,3],[2023,5,16,null,null,1,2,11],[2022,5,16,null,null,1,2,16],[2022,5,17,-41.6,null,31,0,16],[2023,5,17,-54.4,null,33,0,11],[2024,5,17,-93.9,null,31,0,3],[2024,5,6,-103.9,null,14,1,3],[2023,5,6,-95.1,null,16,1,11],[2022,5,6,null,null,8,2,16],[2023,5,7,null,null,2,2,11],[2024,5,7,null,null,3,2,3],[2024,5,9,null,null,5,2,3],[2023,5,9,null,null,4,2,11],[2022,5,9,null,null,6,2,16],[2022,5,10,-34.5,null,163,0,16],[2023,5,10,-20.8,null,166,0,11],[2024,5,10,-20.7,null,166,0,3],[2024,5,11,-30.4,null,118,0,3],[2023,5,11,-25.5,null,142,0,11],[2022,5,11,-51.8,null,112,0,16],[2022,5,12,-123.5,null,31,0,16],[2023,5,12,-127.4,null,29,1,11],[2024,5,12,-116.6,null,33,0,3],[2024,5,20,null,null,9,2,3],[2023,5,20,null,null,6,2,11],[2022,5,20,null,null,6,2,16],[2022,5,21,-38.9,null,128,0,16],[2023,5,21,-11.7,null,127,0,11],[2024,5,21,-5.3,null,126,0,3],[2024,6,13,null,null,null,2,4],[2023,6,13,null,null,null,2,8],[2022,6,13,null,null,null,2,13],[2022,6,0,4.2,11,262,0,13],[2024,6,0,2.8,7,246,0,4],[2023,6,0,1.2,3,258,0,8],[2023,6,14,null,null,null,2,8],[2022,6,14,null,null,null,2,13],[2024,6,14,null,null,null,2,4],[2024,6,15,null,null,null,2,4],[2023,6,15,null,null,null,2,8],[2022,6,15,null,null,null,2,13],[2022,6,2,5.9,1,17,1,13],[2024,6,2,15.4,2,13,1,4],[2023,6,2,6.3,1,16,1,8],[2023,6,22,0.9,1,111,0,8],[2022,6,22,0.8,1,119,0,13],[2024,6,22,3.7,4,109,0,4],[2024,6,16,null,null,null,2,4],[2023,6,16,null,null,null,2,8],[2022,6,16,null,null,null,2,13],[2024,6,5,null,null,null,2,4],[2024,6,17,7,3,43,0,4],[2022,6,17,2,1,50,0,13],[2023,6,17,0,0,46,0,8],[2023,6,6,0,0,23,1,8],[2024,6,6,5.6,1,18,1,4],[2022,6,6,7.1,1,14,1,13],[2022,6,23,7,10,142,0,13],[2023,6,23,1.4,2,146,0,8],[2024,6,23,2.2,3,136,0,4],[2024,6,8,null,null,null,2,4],[2024,6,25,null,null,null,2,4],[2022,6,25,null,null,null,2,13],[2023,6,25,null,null,null,2,8],[2023,6,18,null,null,null,2,8],[2024,6,18,null,null,null,2,4],[2022,6,18,null,null,null,2,13],[2022,6,19,null,null,null,2,13],[2023,6,19,null,null,null,2,8],[2024,6,19,null,null,null,2,4],[2024,6,11,3.4,6,178,0,4],[2022,6,11,5.3,9,171,0,13],[2023,6,11,1.4,3,212,0,8],[2023,6,12,4,2,50,0,8],[2024,6,12,4.1,2,49,0,4],[2022,6,12,6.7,3,45,0,13],[2022,6,20,null,null,null,2,13],[2023,6,20,0,0,12,1,8],[2024,6,20,0,0,14,1,4],[2024,6,21,2.2,4,184,0,4],[2022,6,21,4.1,8,193,0,13],[2023,6,21,1.5,3,195,0,8]]},"23656076025175":{"demographics":{"African American":{"count":0,"percent":0.0},"American Indian":{"count":161,"percent":57.1},"Asian":{"count":0,"percent":0.0},"English Learner":{"count":57,"percent":20.2},"Filipino":{"count":0,"percent":0.0},"Foster":{"count":38,"percent":13.5},"Free/Reduced Meal Eligible":{"count":246,"percent":87.2},"Hispanic":{"count":86,"percent":30.5},"Homeless":{"count":106,"percent":37.6},"Migrant":{"count":2,"percent":0.7},"Not Reported":{"count":1,"percent":0.4},"Pacific Islander":{"count":0,"percent":0.0},"Socioeconomically Disadvantaged":{"count":246,"percent":87.2},"Students with Disabilities":{"count":56,"percent":19.9},"Two or More Races":{"count":10,"percent":3.5},"White":{"count":24,"percent":8.5}},"observations":[[2022,1,13,null,null,null,2,12],[2023,1,13,null,null,null,2,7],[2024,1,13,null,null,null,2,1],[2024,1,0,37,120,324,0,1],[2023,1,0,37.1,129,348,0,7],[2022,1,0,48.9,162,331,0,12],[2022,1,14,52.6,90,171,0,12],[2023,1,14,40.9,76,186,0,7],[2024,1,14,39.1,68,174,0,1],[2024,1,15,null,null,null,2,1],[2023,1,15,null,null,null,2,7],[2022,1,15,null,null,null,2,12],[2022,1,2,32.9,24,73,0,12],[2023,1,2,20.9,19,91,0,7],[2024,1,2,25,22,88,0,1],[2024,1,22,32.9,49,149,0,1],[2023,1,22,40,62,155,0,7],[2022,1,22,47.6,70,147,0,12],[2022,1,16,null,null,null,2,12],[2023,1,16,null,null,null,2,7],[2024,1,16,null,null,null,2,1],[2024,1,5,null,null,null,2,1],[2023,1,5,36.4,4,11,1,7],[2022,1,5,30.8,4,13,1,12],[2022,1,26,45.4,49,108,0,12],[2023,1,26,34.5,41,119,0,7],[2024,1,26,27,30,111,0,1],[2024,1,27,31.4,27,86,0,1],[2023,1,27,29.9,26,87,0,7],[2022,1,27,38.3,36,94,0,12],[2022,1,28,47.2,34,72,0,12],[2023,1,28,31.6,25,79,0,7],[2024,1,28,41.5,34,82,0,1],[2024,1,30,37,120,324,0,1],[2023,1,30,37.1,129,348,0,7],[2022,1,30,48.9,162,331,0,12],[2022,1,31,75.4,43,57,0,12],[2023,1,31,58.7,37,63,0,7],[2024,1,31,64.4,29,45,0,1],[2024,1,17,29.8,34,114,0,1],[2023,1,17,25,29,116,0,7],[2022,1,17,36.4,32,88,0,12],[2022,1,6,44.1,30,68,0,12],[2023,1,6,25.5,13,51,0,7],[2024,1,6,36,50,139,0,1],[2024,1,23,40.6,71,175,0,1],[2023,1,23,34.7,67,193,0,7],[2022,1,23,50,92,184,0,12],[2022,1,18,null,null,null,2,12],[2023,1,18,null,null,null,2,7],[2024,1,18,null,null,null,2,1],[2024,1,19,null,null,null,2,1],[2023,1,19,null,null,null,2,7],[2022,1,19,55.3,21,38,0,12],[2022,1,11,48.5,144,297,0,12],[2023,1,11,38.6,120,311,0,7],[2024,1,11,35.4,104,294,0,1],[2024,1,12,43.1,25,58,0,1],[2023,1,12,35.7,20,56,0,7],[2022,1,12,44.8,26,58,0,12],[2022,1,20,null,null,null,2,12],[2023,1,20,63.6,7,11,1,7],[2024,1,20,null,null,null,2,1],[2024,1,21,56,14,25,1,1],[2023,1,21,48.5,16,33,0,7],[2022,1,21,59.3,16,27,1,12],[2024,2,0,-107.7,null,171,0,2],[2023,2,0,-84.2,null,170,0,10],[2022,2,0,-113.6,null,156,0,15],[2022,2,1,null,null,2,2,15],[2024,2,1,null,null,1,2,2],[2023,2,1,null,null,1,2,10],[2023,2,14,-78.4,null,102,0,10],[2022,2,14,-104.3,null,91,0,15],[2024,2,14,-105.4,null,90,0,2],[2024,2,2,-131.4,null,56,0,2],[2023,2,2,-105,null,41,0,10],[2022,2,2,-129.3,null,36,0,15],[2022,2,3,-134.7,null,34,0,15],[2024,2,3,-140.5,null,49,0,2],[2023,2,3,-107.8,null,39,0,10],[2023,2,4,-77.6,null,129,0,10],[2022,2,4,-112.5,null,122,0,15],[2024,2,4,-96.1,null,115,0,2],[2024,2,5,null,null,4,2,2],[2023,2,5,null,null,4,2,10],[2022,2,5,null,null,5,2,15],[2022,2,17,-126.6,null,40,0,15],[2024,2,17,-131.1,null,60,0,2],[2023,2,17,-102.6,null,48,0,10],[2023,2,6,-85.3,null,49,0,10],[2022,2,6,-113.1,null,54,0,15],[2024,2,6,-125.8,null,75,0,2],[2024,2,7,-139.9,null,20,1,2],[2023,2,7,-111.4,null,12,1,10],[2023,2,9,null,null,2,2,10],[2024,2,9,null,null,7,2,2],[2022,2,9,null,null,2,2,15],[2022,2,10,-107.7,null,149,0,15],[2023,2,10,-84.3,null,169,0,10],[2024,2,10,-108.3,null,170,0,2],[2024,2,11,-110.5,null,159,0,2],[2022,2,11,-114.5,null,148,0,15],[2023,2,11,-84.6,null,159,0,10],[2023,2,12,-134,null,33,0,10],[2024,2,12,-100.4,null,29,1,2],[2022,2,12,-152.5,null,26,1,15],[2022,2,20,null,null,4,2,15],[2023,2,20,null,null,4,2,10],[2024,2,20,null,null,4,2,2],[2024,2,21,-52.6,null,18,1,2],[2022,2,21,-145.6,null,16,1,15],[2023,2,21,-71.9,null,17,1,10],[2023,5,0,-134.3,null,173,0,11],[2022,5,0,-150.4,null,156,0,16],[2024,5,0,-148.4,null,169,0,3],[2022,5,1,null,null,2,2,16],[2023,5,1,null,null,1,2,11],[2023,5,14,-134.8,null,101,0,11],[2022,5,14,-147.4,null,91,0,16],[2024,5,14,-152.8,null,89,0,3],[2024,5,2,-163.9,null,56,0,3],[2022,5,2,-150.1,null,36,0,16],[2023,5,2,-143.9,null,45,0,11],[2023,5,3,-145.6,null,43,0,11],[2022,5,3,-152.5,null,34,0,16],[2024,5,3,-168.3,null,49,0,3],[2024,5,4,-140.7,null,113,0,3],[2022,5,4,-153.7,null,122,0,16],[2023,5,4,-130.9,null,128,0,11],[2023,5,5,null,null,4,2,11],[2022,5,5,null,null,5,2,16],[2024,5,5,null,null,4,2,3],[2024,5,17,-166.8,null,59,0,3],[2022,5,17,-155.6,null,40,0,16],[2023,5,17,-135.6,null,51,0,11],[2023,5,6,-143.3,null,48,0,11],[2022,5,6,-155.2,null,53,0,16],[2024,5,6,-168.9,null,75,0,3],[2024,5,7,-192.5,null,20,1,3],[2023,5,7,-163.3,null,12,1,11],[2023,5,9,null,null,2,2,11],[2024,5,9,null,null,7,2,3],[2022,5,9,null,null,2,2,16],[2022,5,10,-142.4,null,147,0,16],[2024,5,10,-148.4,null,169,0,3],[2023,5,10,-134.7,null,172,0,11],[2023,5,11,-133.9,null,162,0,11],[2024,5,11,-150.5,null,157,0,3],[2022,5,11,-151.7,null,148,0,16],[2022,5,12,-169.2,null,26,1,16],[2024,5,12,-148.6,null,29,1,3],[2023,5,12,-147.4,null,33,0,11],[2023,5,20,null,null,4,2,11],[2024,5,20,null,null,4,2,3],[2022,5,20,null,null,4,2,16],[2022,5,21,-169.9,null,16,1,16],[2024,5,21,-91.1,null,18,1,3],[2023,5,21,-126,null,17,1,11],[2023,6,13,null,null,null,2,8],[2022,6,13,null,null,null,2,13],[2024,6,13,null,null,null,2,4],[2024,6,0,10.5,36,344,0,4],[2023,6,0,8.4,31,371,0,8],[2022,6,0,19.3,65,336,0,13],[2022,6,14,21.6,37,171,0,13],[2024,6,14,11.8,22,187,0,4],[2023,6,14,6.3,12,192,0,8],[2023,6,15,null,null,null,2,8],[2022,6,15,null,null,null,2,13],[2024,6,15,null,null,null,2,4],[2024,6,2,12.1,11,91,0,4],[2023,6,2,13.5,13,96,0,8],[2022,6,2,21.3,16,75,0,13],[2022,6,22,12.5,19,152,0,13],[2024,6,22,6.3,10,160,0,4],[2023,6,22,8.8,15,170,0,8],[2023,6,16,null,null,null,2,8],[2022,6,16,null,null,null,2,13],[2024,6,16,null,null,null,2,4],[2024,6,5,null,null,null,2,4],[2023,6,5,7.7,1,13,1,8],[2022,6,5,38.5,5,13,1,13],[2022,6,17,18.5,17,92,0,13],[2024,6,17,9.3,11,118,0,4],[2023,6,17,10.7,13,121,0,8],[2023,6,6,23.5,12,51,0,8],[2022,6,6,32.4,22,68,0,13],[2024,6,6,13.7,19,139,0,4],[2024,6,23,14.1,26,184,0,4],[2023,6,23,8,16,201,0,8],[2022,6,23,25,46,184,0,13],[2022,6,18,null,null,null,2,13],[2024,6,18,null,null,null,2,4],[2023,6,18,null,null,null,2,8],[2023,6,19,null,null,null,2,8],[2022,6,19,13.2,5,38,0,13],[2024,6,19,null,null,null,2,4],[2024,6,11,11.4,35,308,0,4],[2023,6,11,9.5,31,327,0,8],[2022,6,11,20.3,61,301,0,13],[2022,6,12,12.1,7,58,0,13],[2024,6,12,11.3,7,62,0,4],[2023,6,12,10.3,6,58,0,8],[2023,6,20,14.3,2,14,1,8],[2022,6,20,null,null,null,2,13],[2024,6,20,null,null,null,2,4],[2024,6,21,10.7,3,28,1,4],[2023,6,21,11.4,4,35,0,8],[2022,6,21,14.8,4,27,1,13]]},"23656150115055":{"demographics":{"African American":{"count":5,"percent":2.0},"American Indian":{"count":7,"percent":2.8},"Asian":{"count":8,"percent":3.2},"English Learner":{"count":13,"percent":5.2},"Filipino":{"count":0,"percent":0.0},"Foster":{"count":0,"percent":0.0},"Free/Reduced Meal Eligible":{"count":113,"percent":44.8},"Hispanic":{"count":52,"percent":20.6},"Homeless":{"count":0,"percent":0.0},"Migrant":{"count":0,"percent":0.0},"Not Reported":{"count":6,"percent":2.4},"Pacific Islander":{"count":0,"percent":0.0},"Socioeconomically Disadvantaged":{"count":113,"percent":44.8},"Students with Disabilities":{"count":32,"percent":12.7},"Two or More Races":{"count":23,"percent":9.1},"White":{"count":151,"percent":59.9}},"observations":[[2023,1,13,null,null,null,2,7],[2024,1,13,null,null,null,2,1],[2022,1,13,null,null,null,2,12],[2022,1,0,31,74,239,0,12],[2023,1,0,17.5,43,246,0,7],[2024,1,0,21.1,54,256,0,1],[2024,1,14,null,null,null,2,1],[2022,1,14,null,null,null,2,12],[2023,1,14,null,null,null,2,7],[2023,1,15,null,null,null,2,7],[2024,1,15,null,null,null,2,1],[2022,1,15,null,null,null,2,12],[2022,1,2,45.8,11,24,1,12],[2023,1,2,33.3,7,21,1,7],[2024,1,2,31.6,6,19,1,1],[2024,1,22,18,22,122,0,1],[2022,1,22,26.8,34,127,0,12],[2023,1,22,14.8,18,122,0,7],[2023,1,16,null,null,null,2,7],[2024,1,16,null,null,null,2,1],[2022,1,16,null,null,null,2,12],[2022,1,5,null,null,null,2,12],[2023,1,5,null,null,null,2,7],[2024,1,5,null,null,null,2,1],[2024,1,26,17.3,13,75,0,1],[2022,1,26,31.2,24,77,0,12],[2023,1,26,18.4,14,76,0,7],[2023,1,27,11,9,82,0,7],[2024,1,27,17.9,14,78,0,1],[2022,1,27,17.8,13,73,0,12],[2022,1,28,28.6,14,49,0,12],[2023,1,28,21.3,10,47,0,7],[2024,1,28,27.5,14,51,0,1],[2024,1,30,21.1,54,256,0,1],[2022,1,30,31,74,239,0,12],[2023,1,30,17.5,43,246,0,7],[2023,1,31,24.4,10,41,0,7],[2024,1,31,25,13,52,0,1],[2022,1,31,57.5,23,40,0,12],[2022,1,17,31.6,18,57,0,12],[2023,1,17,22.6,14,62,0,7],[2024,1,17,27.4,17,62,0,1],[2022,1,6,null,null,null,2,12],[2023,1,6,null,null,null,2,7],[2023,1,23,20.2,25,124,0,7],[2024,1,23,23.3,31,133,0,1],[2022,1,23,36,40,111,0,12],[2022,1,25,null,null,null,2,12],[2024,1,25,null,null,null,2,1],[2024,1,18,null,null,null,2,1],[2023,1,18,null,null,null,2,7],[2022,1,18,null,null,null,2,12],[2022,1,19,null,null,null,2,12],[2024,1,19,null,null,null,2,1],[2023,1,19,null,null,null,2,7],[2023,1,11,24.2,29,120,0,7],[2022,1,11,38.7,46,119,0,12],[2024,1,11,29.2,35,120,0,1],[2024,1,12,26.2,11,42,0,1],[2023,1,12,3.1,1,32,0,7],[2022,1,12,28.6,6,21,1,12],[2022,1,20,46.7,7,15,1,12],[2024,1,20,11.1,2,18,1,1],[2023,1,20,28.6,4,14,1,7],[2023,1,21,13.5,20,148,0,7],[2022,1,21,26.9,39,145,0,12],[2024,1,21,18.7,28,150,0,1],[2024,2,13,null,null,2,2,2],[2022,2,13,null,null,2,2,15],[2023,2,13,null,null,2,2,10],[2023,2,0,-21.4,null,143,0,10],[2024,2,0,-6.2,null,139,0,2],[2022,2,0,-14.2,null,140,0,15],[2023,2,1,null,null,1,2,10],[2023,2,14,null,null,4,2,10],[2022,2,14,null,null,2,2,15],[2024,2,14,null,null,5,2,2],[2024,2,15,null,null,5,2,2],[2023,2,15,null,null,4,2,10],[2022,2,15,null,null,4,2,15],[2022,2,2,-47.6,null,14,1,15],[2024,2,2,-77,null,13,1,2],[2023,2,2,-66.1,null,15,1,10],[2023,2,3,-90.8,null,11,1,10],[2022,2,3,-54.8,null,12,1,15],[2024,2,3,null,null,10,2,2],[2024,2,4,-1.1,null,116,0,2],[2023,2,4,-24.4,null,120,0,10],[2022,2,4,-12.1,null,115,0,15],[2022,2,16,null,null,1,2,15],[2022,2,5,null,null,1,2,15],[2022,2,17,-20.8,null,36,0,15],[2024,2,17,-40.7,null,36,0,2],[2023,2,17,-40,null,40,0,10],[2023,2,6,null,null,1,2,10],[2022,2,6,null,null,1,2,15],[2023,2,7,null,null,5,2,10],[2024,2,7,null,null,5,2,2],[2024,2,9,null,null,3,2,2],[2022,2,9,null,null,2,2,15],[2023,2,9,null,null,4,2,10],[2023,2,10,-22,null,142,0,10],[2024,2,10,-6.2,null,139,0,2],[2022,2,10,-14.2,null,140,0,15],[2022,2,11,-27.3,null,67,0,15],[2023,2,11,-47.1,null,70,0,10],[2024,2,11,-28.2,null,64,0,2],[2024,2,12,-80.1,null,29,1,2],[2022,2,12,-129.4,null,13,1,15],[2023,2,12,-100.7,null,23,1,10],[2023,2,20,null,null,8,2,10],[2024,2,20,null,null,8,2,2],[2022,2,20,null,null,4,2,15],[2022,2,21,-12.5,null,88,0,15],[2023,2,21,-18.8,null,86,0,10],[2024,2,21,8.8,null,80,0,2],[2022,5,13,null,null,2,2,16],[2024,5,13,null,null,2,2,3],[2023,5,13,null,null,2,2,11],[2023,5,0,-27.7,null,144,0,11],[2022,5,0,-32.9,null,141,0,16],[2024,5,0,-26.4,null,139,0,3],[2023,5,1,null,null,1,2,11],[2023,5,14,null,null,4,2,11],[2024,5,14,null,null,5,2,3],[2022,5,14,null,null,2,2,16],[2022,5,15,null,null,4,2,16],[2023,5,15,null,null,4,2,11],[2024,5,15,null,null,5,2,3],[2024,5,2,-46.5,null,13,1,3],[2022,5,2,-100.1,null,14,1,16],[2023,5,2,-61.5,null,15,1,11],[2023,5,3,-82.8,null,11,1,11],[2024,5,3,null,null,10,2,3],[2022,5,3,-102.8,null,12,1,16],[2022,5,4,-24.9,null,116,0,16],[2023,5,4,-30,null,121,0,11],[2024,5,4,-21.8,null,116,0,3],[2022,5,16,null,null,1,2,16],[2022,5,5,null,null,1,2,16],[2022,5,17,-47.7,null,36,0,16],[2024,5,17,-46.2,null,36,0,3],[2023,5,17,-46.7,null,40,0,11],[2023,5,6,null,null,1,2,11],[2022,5,6,null,null,1,2,16],[2023,5,7,null,null,5,2,11],[2024,5,7,null,null,5,2,3],[2024,5,9,null,null,3,2,3],[2022,5,9,null,null,2,2,16],[2023,5,9,null,null,4,2,11],[2023,5,10,-27.9,null,143,0,11],[2024,5,10,-26.4,null,139,0,3],[2022,5,10,-32.9,null,141,0,16],[2022,5,11,-55.3,null,67,0,16],[2023,5,11,-64.7,null,70,0,11],[2024,5,11,-45.2,null,64,0,3],[2024,5,12,-104.6,null,29,1,3],[2022,5,12,-127.1,null,13,1,16],[2023,5,12,-122.3,null,23,1,11],[2023,5,20,null,null,8,2,11],[2024,5,20,null,null,8,2,3],[2022,5,20,null,null,4,2,16],[2022,5,21,-27.7,null,89,0,16],[2023,5,21,-18.9,null,86,0,11],[2024,5,21,-12.1,null,80,0,3],[2024,6,13,null,null,null,2,4],[2023,6,13,null,null,null,2,8],[2022,6,13,null,null,null,2,13],[2022,6,0,1.7,4,240,0,13],[2024,6,0,1.2,3,258,0,4],[2023,6,0,1.2,3,253,0,8],[2023,6,14,null,null,null,2,8],[2022,6,14,null,null,null,2,13],[2024,6,14,null,null,null,2,4],[2024,6,15,null,null,null,2,4],[2023,6,15,null,null,null,2,8],[2022,6,15,null,null,null,2,13],[2022,6,2,0,0,24,1,13],[2024,6,2,0,0,20,1,4],[2023,6,2,0,0,22,1,8],[2023,6,22,0.8,1,123,0,8],[2022,6,22,0.8,1,127,0,13],[2024,6,22,0.8,1,122,0,4],[2024,6,16,null,null,null,2,4],[2023,6,16,null,null,null,2,8],[2022,6,16,null,null,null,2,13],[2022,6,5,null,null,null,2,13],[2024,6,5,null,null,null,2,4],[2023,6,5,null,null,null,2,8],[2023,6,17,1.6,1,64,0,8],[2022,6,17,1.7,1,58,0,13],[2024,6,17,1.6,1,63,0,4],[2023,6,6,null,null,null,2,8],[2022,6,6,null,null,null,2,13],[2022,6,23,2.7,3,112,0,13],[2024,6,23,1.5,2,135,0,4],[2023,6,23,1.5,2,130,0,8],[2022,6,25,null,null,null,2,13],[2024,6,25,null,null,null,2,4],[2024,6,18,null,null,null,2,4],[2023,6,18,null,null,null,2,8],[2022,6,18,null,null,null,2,13],[2022,6,19,null,null,null,2,13],[2024,6,19,null,null,null,2,4],[2023,6,19,null,null,null,2,8],[2023,6,11,2.5,3,122,0,8],[2022,6,11,0.8,1,119,0,13],[2024,6,11,2.5,3,121,0,4],[2024,6,12,4.8,2,42,0,4],[2023,6,12,3,1,33,0,8],[2022,6,12,0,0,21,1,13],[2022,6,20,0,0,15,1,13],[2024,6,20,0,0,18,1,4],[2023,6,20,0,0,16,1,8],[2023,6,21,1.3,2,149,0,8],[2022,6,21,1.4,2,145,0,13],[2024,6,21,1.3,2,150,0,4]]},"23656156025183":{"demographics":{"African American":{"count":0,"percent":0.0},"American Indian":{"count":30,"percent":6.8},"Asian":{"count":2,"percent":0.5},"English Learner":{"count":130,"percent":29.7},"Filipino":{"count":0,"percent":0.0},"Foster":{"count":3,"percent":0.7},"Free/Reduced Meal Eligible":{"count":358,"percent":81.7},"Hispanic":{"count":226,"percent":51.6},"Homeless":{"count":7,"percent":1.6},"Migrant":{"count":14,"percent":3.2},"Not Reported":{"count":0,"percent":0.0},"Pacific Islander":{"count":0,"percent":0.0},"Socioeconomically Disadvantaged":{"count":360,"percent":82.2},"Students with Disabilities":{"count":67,"percent":15.3},"Two or More Races":{"count":32,"percent":7.3},"White":{"count":148,"percent":33.8}},"observations":[[2022,1,13,null,null,null,2,12],[2023,1,13,null,null,null,2,7],[2024,1,13,null,null,null,2,1],[2024,1,0,23.3,114,490,0,1],[2023,1,0,23,114,496,0,7],[2022,1,0,38.2,193,505,0,12],[2022,1,14,51.5,17,33,0,12],[2023,1,14,29.6,8,27,1,7],[2024,1,14,40.7,11,27,1,1],[2024,1,15,null,null,null,2,1],[2023,1,15,null,null,null,2,7],[2022,1,15,null,null,null,2,12],[2022,1,2,35.5,49,138,0,12],[2023,1,2,19.6,30,153,0,7],[2024,1,2,17.8,26,146,0,1],[2024,1,22,24.3,52,214,0,1],[2023,1,22,21,45,214,0,7],[2022,1,22,36.5,88,241,0,12],[2022,1,16,null,null,null,2,12],[2023,1,16,null,null,null,2,7],[2024,1,16,null,null,null,2,1],[2024,1,5,null,null,null,2,1],[2023,1,5,null,null,null,2,7],[2022,1,5,null,null,null,2,12],[2022,1,26,33.4,99,296,0,12],[2023,1,26,23.4,65,278,0,7],[2024,1,26,19,54,284,0,1],[2024,1,27,14,13,93,0,1],[2023,1,27,14.4,13,90,0,7],[2022,1,27,33.7,31,92,0,12],[2022,1,30,38.2,193,505,0,12],[2023,1,30,23,114,496,0,7],[2024,1,30,23.3,114,490,0,1],[2024,1,31,41.6,47,113,0,1],[2023,1,31,28.1,36,128,0,7],[2022,1,31,53.8,63,117,0,12],[2022,1,17,36.4,90,247,0,12],[2023,1,17,23.2,59,254,0,7],[2024,1,17,23.4,61,261,0,1],[2024,1,6,41.7,5,12,1,1],[2023,1,6,50,7,14,1,7],[2022,1,6,58.3,7,12,1,12],[2022,1,23,39.8,105,264,0,12],[2023,1,23,24.5,69,282,0,7],[2024,1,23,22.5,62,276,0,1],[2024,1,8,13,3,23,1,1],[2023,1,8,12.5,3,24,1,7],[2022,1,8,33.3,7,21,1,12],[2022,1,18,null,null,null,2,12],[2023,1,18,null,null,null,2,7],[2024,1,18,null,null,null,2,1],[2024,1,19,null,null,null,2,1],[2023,1,19,null,null,null,2,7],[2022,1,19,null,null,null,2,12],[2022,1,11,43.4,175,403,0,12],[2023,1,11,25.4,103,405,0,7],[2024,1,11,25.9,106,410,0,1],[2024,1,12,25.3,25,99,0,1],[2023,1,12,26.7,24,90,0,7],[2022,1,12,44.9,35,78,0,12],[2022,1,20,41.2,14,34,0,12],[2023,1,20,25.8,8,31,0,7],[2024,1,20,15.2,5,33,0,1],[2024,1,21,22.6,37,164,0,1],[2023,1,21,20.1,36,179,0,7],[2022,1,21,37,70,189,0,12],[2024,2,0,-67.9,null,180,0,2],[2023,2,0,-63.6,null,178,0,10],[2022,2,0,-59.9,null,175,0,15],[2022,2,1,null,null,2,2,15],[2023,2,1,null,null,3,2,10],[2024,2,1,null,null,7,2,2],[2024,2,14,null,null,7,2,2],[2023,2,14,null,null,8,2,10],[2022,2,14,-124.3,null,16,1,15],[2022,2,2,-98.1,null,43,0,15],[2023,2,2,-92.7,null,50,0,10],[2024,2,2,-94.5,null,61,0,2],[2024,2,3,-110.2,null,47,0,2],[2023,2,3,-105.7,null,42,0,10],[2022,2,3,-107,null,38,0,15],[2022,2,4,-46.3,null,124,0,15],[2023,2,4,-53.4,null,123,0,10],[2024,2,4,-54.2,null,117,0,2],[2024,2,5,null,null,3,2,2],[2023,2,5,null,null,2,2,10],[2022,2,5,null,null,2,2,15],[2022,2,17,-77.2,null,80,0,15],[2023,2,17,-67.6,null,89,0,10],[2024,2,17,-76.4,null,95,0,2],[2024,2,6,null,null,2,2,2],[2023,2,6,null,null,3,2,10],[2022,2,6,null,null,1,2,15],[2022,2,9,null,null,5,2,15],[2023,2,9,null,null,8,2,10],[2024,2,9,-41.9,null,14,1,2],[2024,2,10,-70.5,null,173,0,2],[2023,2,10,-65,null,175,0,10],[2022,2,10,-61.3,null,173,0,15],[2022,2,11,-74.5,null,137,0,15],[2023,2,11,-79.5,null,144,0,10],[2024,2,11,-74.7,null,154,0,2],[2024,2,12,-100,null,47,0,2],[2023,2,12,-101.7,null,40,0,10],[2022,2,12,-115,null,27,1,15],[2022,2,20,null,null,10,2,15],[2023,2,20,-61.6,null,11,1,10],[2024,2,20,-61.8,null,16,1,2],[2024,2,21,-49.7,null,62,0,2],[2023,2,21,-48.7,null,70,0,10],[2022,2,21,-29.8,null,70,0,15],[2022,5,0,-46.7,null,175,0,16],[2024,5,0,-62.9,null,179,0,3],[2023,5,0,-52.4,null,180,0,11],[2023,5,1,null,null,3,2,11],[2022,5,1,null,null,2,2,16],[2024,5,1,null,null,6,2,3],[2024,5,14,null,null,7,2,3],[2023,5,14,null,null,8,2,11],[2022,5,14,-116.1,null,16,1,16],[2022,5,2,-64.5,null,43,0,16],[2024,5,2,-78.4,null,60,0,3],[2023,5,2,-77.8,null,52,0,11],[2023,5,3,-86.1,null,44,0,11],[2022,5,3,-70.1,null,38,0,16],[2024,5,3,-92,null,47,0,3],[2024,5,4,-55.1,null,117,0,3],[2023,5,4,-41.7,null,123,0,11],[2022,5,4,-41.1,null,124,0,16],[2022,5,5,null,null,2,2,16],[2024,5,5,null,null,3,2,3],[2023,5,5,null,null,2,2,11],[2023,5,17,-64.6,null,91,0,11],[2022,5,17,-56.4,null,80,0,16],[2024,5,17,-67.8,null,94,0,3],[2024,5,6,null,null,2,2,3],[2023,5,6,null,null,3,2,11],[2022,5,6,null,null,1,2,16],[2022,5,9,null,null,5,2,16],[2024,5,9,-29,null,13,1,3],[2023,5,9,null,null,8,2,11],[2023,5,10,-53,null,177,0,11],[2022,5,10,-47.5,null,173,0,16],[2024,5,10,-63.4,null,173,0,3],[2024,5,11,-70,null,153,0,3],[2023,5,11,-64.2,null,146,0,11],[2022,5,11,-60.4,null,137,0,16],[2022,5,12,-86.2,null,27,1,16],[2024,5,12,-81.3,null,46,0,3],[2023,5,12,-77.1,null,40,0,11],[2023,5,20,-36,null,11,1,11],[2022,5,20,null,null,10,2,16],[2024,5,20,-61.4,null,16,1,3],[2024,5,21,-52.4,null,62,0,3],[2023,5,21,-32.6,null,70,0,11],[2022,5,21,-23.3,null,70,0,16],[2024,6,13,null,null,null,2,4],[2023,6,13,null,null,null,2,8],[2022,6,13,null,null,null,2,13],[2022,6,0,1,5,510,0,13],[2023,6,0,1.8,9,505,0,8],[2024,6,0,1.2,6,493,0,4],[2024,6,14,7.4,2,27,1,4],[2023,6,14,11.1,3,27,1,8],[2022,6,14,5.9,2,34,0,13],[2022,6,15,null,null,null,2,13],[2023,6,15,null,null,null,2,8],[2024,6,15,null,null,null,2,4],[2024,6,2,0,0,146,0,4],[2023,6,2,0,0,158,0,8],[2022,6,2,0,0,141,0,13],[2022,6,22,0,0,242,0,13],[2023,6,22,0.5,1,220,0,8],[2024,6,22,0.5,1,215,0,4],[2024,6,16,null,null,null,2,4],[2023,6,16,null,null,null,2,8],[2022,6,16,null,null,null,2,13],[2022,6,5,null,null,null,2,13],[2023,6,5,null,null,null,2,8],[2024,6,5,null,null,null,2,4],[2024,6,17,0,0,262,0,4],[2023,6,17,0.8,2,260,0,8],[2022,6,17,0,0,250,0,13],[2022,6,6,0,0,13,1,13],[2023,6,6,0,0,17,1,8],[2024,6,6,0,0,12,1,4],[2024,6,23,1.8,5,278,0,4],[2023,6,23,2.8,8,285,0,8],[2022,6,23,1.9,5,268,0,13],[2022,6,8,0,0,23,1,13],[2023,6,8,0,0,24,1,8],[2024,6,8,0,0,23,1,4],[2024,6,18,null,null,null,2,4],[2023,6,18,null,null,null,2,8],[2022,6,18,null,null,null,2,13],[2022,6,19,null,null,null,2,13],[2023,6,19,null,null,null,2,8],[2024,6,19,null,null,null,2,4],[2024,6,11,1.2,5,411,0,4],[2023,6,11,2,8,410,0,8],[2022,6,11,1.2,5,407,0,13],[2022,6,12,2.6,2,78,0,13],[2023,6,12,4.4,4,90,0,8],[2024,6,12,2,2,99,0,4],[2024,6,20,0,0,33,0,4],[2023,6,20,0,0,31,0,8],[2022,6,20,0,0,34,0,13],[2022,6,21,1.6,3,190,0,13],[2023,6,21,2.2,4,182,0,8],[2024,6,21,2.4,4,166,0,4]]},"23656156025191":{"demographics":{"African American":{"count":1,"percent":0.3},"American Indian":{"count":11,"percent":2.8},"Asian":{"count":6,"percent":1.5},"English Learner":{"count":108,"percent":27.3},"Filipino":{"count":2,"percent":0.5},"Foster":{"count":2,"percent":0.5},"Free/Reduced Meal Eligible":{"count":296,"percent":74.7},"Hispanic":{"count":231,"percent":58.3},"Homeless":{"count":11,"percent":2.8},"Migrant":{"count":21,"percent":5.3},"Not Reported":{"count":13,"percent":3.3},"Pacific Islander":{"count":4,"percent":1.0},"Socioeconomically Disadvantaged":{"count":296,"percent":74.7},"Students with Disabilities":{"count":65,"percent":16.4},"Two or More Races":{"count":15,"percent":3.8},"White":{"count":113,"percent":28.5}},"observations":[[2023,1,13,null,null,null,2,7],[2022,1,13,null,null,null,2,12],[2024,1,13,null,null,null,2,1],[2024,1,0,16.5,67,405,0,1],[2023,1,0,17.9,81,453,0,7],[2022,1,0,29.2,135,462,0,12],[2022,1,14,null,null,null,2,12],[2024,1,14,18.2,2,11,1,1],[2023,1,14,null,null,null,2,7],[2023,1,15,null,null,null,2,7],[2022,1,15,null,null,null,2,12],[2024,1,15,null,null,null,2,1],[2024,1,2,18.3,23,126,0,1],[2023,1,2,17.1,26,152,0,7],[2022,1,2,32.2,48,149,0,12],[2022,1,22,29.1,65,223,0,12],[2024,1,22,17.2,35,203,0,1],[2023,1,22,16.5,36,218,0,7],[2023,1,16,null,null,null,2,7],[2022,1,16,null,null,null,2,12],[2024,1,16,null,null,null,2,1],[2024,1,5,null,null,null,2,1],[2023,1,5,null,null,null,2,7],[2022,1,5,null,null,null,2,12],[2022,1,26,28.4,61,215,0,12],[2024,1,26,17.1,36,211,0,1],[2023,1,26,12,25,208,0,7],[2023,1,27,23.4,36,154,0,7],[2022,1,27,24.8,38,153,0,12],[2024,1,27,15.6,19,122,0,1],[2024,1,30,16.5,67,405,0,1],[2023,1,30,17.9,81,453,0,7],[2022,1,30,29.2,135,462,0,12],[2022,1,31,38.3,36,94,0,12],[2024,1,31,16.7,12,72,0,1],[2023,1,31,22,20,91,0,7],[2023,1,17,20.2,55,272,0,7],[2022,1,17,30.5,84,275,0,12],[2024,1,17,14.9,36,242,0,1],[2024,1,6,40,10,25,1,1],[2023,1,6,28.6,10,35,0,7],[2022,1,6,68.8,11,16,1,12],[2022,1,23,29.3,70,239,0,12],[2024,1,23,15.8,32,202,0,1],[2023,1,23,19.1,45,235,0,7],[2023,1,8,16.7,6,36,0,7],[2022,1,8,18.2,8,44,0,12],[2024,1,8,22.2,6,27,1,1],[2024,1,18,null,null,null,2,1],[2023,1,18,null,null,null,2,7],[2022,1,18,null,null,null,2,12],[2022,1,19,null,null,null,2,12],[2024,1,19,20,3,15,1,1],[2023,1,19,14.3,2,14,1,7],[2023,1,11,21.4,75,351,0,7],[2022,1,11,33.6,118,351,0,12],[2024,1,11,18,55,306,0,1],[2024,1,12,25.8,17,66,0,1],[2023,1,12,27.9,17,61,0,7],[2022,1,12,49.2,29,59,0,12],[2022,1,20,38.1,8,21,1,12],[2024,1,20,38.5,5,13,1,1],[2023,1,20,23.8,5,21,1,7],[2023,1,21,12.5,16,128,0,7],[2022,1,21,25.7,36,140,0,12],[2024,1,21,17,19,112,0,1],[2022,2,13,null,null,1,2,15],[2023,2,13,null,null,1,2,10],[2023,2,0,7.6,null,198,0,10],[2024,2,0,21.8,null,176,0,2],[2022,2,0,4.4,null,209,0,15],[2022,2,1,null,null,7,2,15],[2023,2,1,null,null,3,2,10],[2024,2,1,null,null,2,2,2],[2024,2,14,null,null,4,2,2],[2022,2,14,null,null,2,2,15],[2023,2,14,null,null,1,2,10],[2023,2,15,null,null,1,2,10],[2022,2,15,null,null,1,2,15],[2022,2,2,-32,null,75,0,15],[2024,2,2,-24,null,61,0,2],[2023,2,2,-32.4,null,71,0,10],[2023,2,3,-56.1,null,54,0,10],[2022,2,3,-53.3,null,55,0,15],[2024,2,3,-49.8,null,45,0,2],[2024,2,4,42.3,null,108,0,2],[2023,2,4,27.2,null,119,0,10],[2022,2,4,26.1,null,123,0,15],[2022,2,16,null,null,3,2,15],[2024,2,16,null,null,2,2,2],[2023,2,16,null,null,2,2,10],[2023,2,5,null,null,4,2,10],[2022,2,5,null,null,4,2,15],[2024,2,5,null,null,1,2,2],[2024,2,17,5.7,null,109,0,2],[2023,2,17,0.6,null,121,0,10],[2022,2,17,-9.7,null,130,0,15],[2022,2,6,null,null,6,2,15],[2024,2,6,null,null,9,2,2],[2023,2,6,null,null,10,2,10],[2023,2,7,null,null,4,2,10],[2024,2,18,null,null,2,2,2],[2024,2,9,48.6,null,16,1,2],[2022,2,9,26.5,null,20,1,15],[2023,2,9,43.1,null,17,1,10],[2023,2,10,8.7,null,195,0,10],[2024,2,10,22.4,null,174,0,2],[2022,2,10,6.4,null,202,0,15],[2022,2,11,-6.3,null,158,0,15],[2023,2,11,-3.5,null,146,0,10],[2024,2,11,10.9,null,136,0,2],[2024,2,12,-75.9,null,28,1,2],[2022,2,12,-95.8,null,31,0,15],[2023,2,12,-82.7,null,25,1,10],[2023,2,20,28,null,12,1,10],[2024,2,20,null,null,5,2,2],[2022,2,20,null,null,7,2,15],[2022,2,21,28.2,null,61,0,15],[2023,2,21,23.5,null,53,0,10],[2024,2,21,59.6,null,48,0,2],[2022,5,13,null,null,1,2,16],[2023,5,13,null,null,1,2,11],[2023,5,0,-11.1,null,200,0,11],[2024,5,0,-2.3,null,175,0,3],[2022,5,0,-15.8,null,209,0,16],[2022,5,1,null,null,6,2,16],[2023,5,1,null,null,3,2,11],[2024,5,1,null,null,1,2,3],[2024,5,14,null,null,4,2,3],[2022,5,14,null,null,2,2,16],[2023,5,14,null,null,1,2,11],[2023,5,15,null,null,1,2,11],[2022,5,15,null,null,1,2,16],[2022,5,2,-46,null,74,0,16],[2024,5,2,-40.2,null,61,0,3],[2023,5,2,-38.8,null,73,0,11],[2023,5,3,-52.7,null,56,0,11],[2022,5,3,-63.6,null,55,0,16],[2024,5,3,-63.7,null,45,0,3],[2024,5,4,16.5,null,107,0,3],[2023,5,4,2.5,null,119,0,11],[2022,5,4,1.5,null,124,0,16],[2022,5,16,null,null,3,2,16],[2024,5,16,null,null,2,2,3],[2023,5,16,null,null,2,2,11],[2023,5,5,null,null,4,2,11],[2022,5,5,null,null,4,2,16],[2024,5,5,null,null,1,2,3],[2024,5,17,-22.1,null,109,0,3],[2023,5,17,-20.1,null,123,0,11],[2022,5,17,-27.9,null,129,0,16],[2022,5,6,null,null,6,2,16],[2024,5,6,null,null,9,2,3],[2023,5,6,-89.1,null,12,1,11],[2023,5,7,null,null,4,2,11],[2024,5,18,null,null,2,2,3],[2024,5,9,25.8,null,16,1,3],[2022,5,9,4.9,null,19,1,16],[2023,5,9,6.9,null,17,1,11],[2023,5,10,-10.1,null,197,0,11],[2024,5,10,-1.9,null,174,0,3],[2022,5,10,-14.4,null,203,0,16],[2022,5,11,-26,null,157,0,16],[2023,5,11,-25.1,null,148,0,11],[2024,5,11,-9.3,null,135,0,3],[2024,5,12,-108.1,null,27,1,3],[2022,5,12,-104.6,null,30,0,16],[2023,5,12,-105.4,null,25,1,11],[2023,5,20,-19.3,null,12,1,11],[2024,5,20,null,null,5,2,3],[2022,5,20,null,null,7,2,16],[2022,5,21,8.2,null,62,0,16],[2023,5,21,10.8,null,53,0,11],[2024,5,21,44,null,47,0,3],[2024,6,13,null,null,null,2,4],[2023,6,13,null,null,null,2,8],[2022,6,13,null,null,null,2,13],[2022,6,0,1.3,6,465,0,13],[2024,6,0,1.2,5,414,0,4],[2023,6,0,1.5,7,461,0,8],[2023,6,14,null,null,null,2,8],[2022,6,14,null,null,null,2,13],[2024,6,14,0,0,11,1,4],[2024,6,15,null,null,null,2,4],[2023,6,15,null,null,null,2,8],[2022,6,15,null,null,null,2,13],[2022,6,2,2,3,149,0,13],[2024,6,2,0.8,1,130,0,4],[2023,6,2,2,3,152,0,8],[2023,6,22,1.4,3,222,0,8],[2022,6,22,0.9,2,224,0,13],[2024,6,22,1,2,209,0,4],[2024,6,16,null,null,null,2,4],[2023,6,16,null,null,null,2,8],[2022,6,16,null,null,null,2,13],[2022,6,5,null,null,null,2,13],[2024,6,5,null,null,null,2,4],[2023,6,5,null,null,null,2,8],[2023,6,17,1.5,4,274,0,8],[2022,6,17,1.5,4,275,0,13],[2024,6,17,0.4,1,247,0,4],[2024,6,6,3.8,1,26,1,4],[2023,6,6,5.7,2,35,0,8],[2022,6,6,6.3,1,16,1,13],[2022,6,23,1.7,4,241,0,13],[2024,6,23,1.5,3,205,0,4],[2023,6,23,1.7,4,239,0,8],[2023,6,8,0,0,36,0,8],[2022,6,8,0,0,44,0,13],[2024,6,8,3.6,1,28,1,4],[2024,6,18,null,null,null,2,4],[2023,6,18,null,null,null,2,8],[2022,6,18,null,null,null,2,13],[2022,6,19,null,null,null,2,13],[2024,6,19,0,0,15,1,4],[2023,6,19,0,0,14,1,8],[2023,6,11,2,7,354,0,8],[2022,6,11,1.7,6,353,0,13],[2024,6,11,1.3,4,312,0,4],[2024,6,12,4.5,3,66,0,4],[2023,6,12,3.2,2,63,0,8],[2022,6,12,0,0,59,0,13],[2022,6,20,0,0,21,1,13],[2024,6,20,0,0,14,1,4],[2023,6,20,0,0,21,1,8],[2023,6,21,2.3,3,132,0,8],[2022,6,21,1.4,2,143,0,13],[2024,6,21,3.5,4,115,0,4]]},"23656230136887":{"demographics":{"African American":{"count":0,"percent":0.0},"American Indian":{"count":1,"percent":5.6},"Asian":{"count":0,"percent":0.0},"English Learner":{"count":4,"percent":22.2},"Filipino":{"count":0,"percent":0.0},"Foster":{"count":0,"percent":0.0},"Free/Reduced Meal Eligible":{"count":11,"percent":61.1},"Hispanic":{"count":8,"percent":44.4},"Homeless":{"count":0,"percent":0.0},"Migrant":{"count":0,"percent":0.0},"Not Reported":{"count":4,"percent":22.2},"Pacific Islander":{"count":0,"percent":0.0},"Socioeconomically Disadvantaged":{"count":12,"percent":66.7},"Students with Disabilities":{"count":0,"percent":0.0},"Two or More Races":{"count":0,"percent":0.0},"White":{"count":5,"percent":27.8}},"observations":[[2022,0,13,null,null,null,2,14],[2023,0,13,null,null,null,2,9],[2024,0,13,null,null,null,2,5],[2024,0,0,23.1,9,39,0,5],[2022,0,0,0,0,53,0,14],[2023,0,0,0,0,25,0,9],[2023,0,14,null,null,null,2,9],[2024,0,14,null,null,null,2,5],[2022,0,14,null,null,null,2,14],[2022,0,15,null,null,null,2,14],[2023,0,15,null,null,null,2,9],[2024,0,15,null,null,null,2,5],[2024,0,2,null,null,null,2,5],[2022,0,2,null,null,null,2,14],[2023,0,2,null,null,null,2,9],[2023,0,22,0,0,11,1,9],[2024,0,22,11.8,2,17,1,5],[2022,0,22,0,0,28,0,14],[2022,0,16,null,null,null,2,14],[2023,0,16,null,null,null,2,9],[2024,0,16,null,null,null,2,5],[2024,0,5,null,null,null,2,5],[2022,0,5,null,null,null,2,14],[2023,0,5,null,null,null,2,9],[2023,0,17,null,null,null,2,9],[2024,0,17,20,2,10,1,5],[2022,0,17,0,0,17,1,14],[2022,0,6,null,null,null,2,14],[2023,0,6,null,null,null,2,9],[2024,0,6,null,null,null,2,5],[2024,0,23,31.8,7,22,1,5],[2022,0,23,0,0,25,0,14],[2023,0,23,0,0,14,1,9],[2023,0,8,null,null,null,2,9],[2024,0,8,null,null,null,2,5],[2022,0,8,null,null,null,2,14],[2024,0,25,null,null,null,2,5],[2024,0,18,null,null,null,2,5],[2023,0,18,null,null,null,2,9],[2022,0,18,null,null,null,2,14],[2022,0,19,null,null,null,2,14],[2024,0,19,null,null,null,2,5],[2023,0,19,0,0,6,1,9],[2023,0,11,0,0,20,0,9],[2022,0,11,0,0,41,0,14],[2024,0,11,25.7,9,35,0,5],[2024,0,12,null,null,null,2,5],[2023,0,12,null,null,null,2,9],[2022,0,12,null,null,null,2,14],[2022,0,20,null,null,null,2,14],[2024,0,20,null,null,null,2,5],[2023,0,20,null,null,null,2,9],[2023,0,21,0,0,12,1,9],[2022,0,21,0,0,25,1,14],[2024,0,21,20,4,20,1,5],[2024,1,13,null,null,null,2,1],[2022,1,13,null,null,null,2,12],[2023,1,13,null,null,null,2,7],[2023,1,0,2.4,2,85,0,7],[2024,1,0,46.5,40,86,0,1],[2022,1,0,16.7,17,102,0,12],[2022,1,14,null,null,null,2,12],[2023,1,14,null,null,null,2,7],[2024,1,14,null,null,null,2,1],[2024,1,15,null,null,null,2,1],[2022,1,15,null,null,null,2,12],[2023,1,15,null,null,null,2,7],[2023,1,2,null,null,null,2,7],[2024,1,2,null,null,null,2,1],[2022,1,2,null,null,null,2,12],[2022,1,22,10.6,5,47,0,12],[2023,1,22,2.9,1,34,0,7],[2024,1,22,46.2,18,39,0,1],[2024,1,16,null,null,null,2,1],[2022,1,16,null,null,null,2,12],[2023,1,16,null,null,null,2,7],[2023,1,5,null,null,null,2,7],[2024,1,5,null,null,null,2,1],[2022,1,5,null,null,null,2,12],[2022,1,29,16.7,17,102,0,12],[2023,1,29,2.4,2,85,0,7],[2024,1,29,46.5,40,86,0,1],[2024,1,17,69.2,18,26,1,1],[2022,1,17,6.5,2,31,0,12],[2023,1,17,4.3,1,23,1,7],[2023,1,6,null,null,null,2,7],[2024,1,6,null,null,null,2,1],[2022,1,6,null,null,null,2,12],[2022,1,23,22.6,12,53,0,12],[2023,1,23,2,1,49,0,7],[2024,1,23,47.8,22,46,0,1],[2024,1,8,null,null,null,2,1],[2022,1,8,null,null,null,2,12],[2023,1,8,null,null,null,2,7],[2023,1,25,null,null,null,2,7],[2024,1,25,null,null,null,2,1],[2022,1,25,null,null,null,2,12],[2022,1,18,null,null,null,2,12],[2023,1,18,null,null,null,2,7],[2024,1,18,null,null,null,2,1],[2024,1,19,null,null,null,2,1],[2022,1,19,7.7,1,13,1,12],[2023,1,19,0,0,12,1,7],[2023,1,11,0,0,60,0,7],[2024,1,11,45.6,31,68,0,1],[2022,1,11,14.5,10,69,0,12],[2022,1,12,18.8,3,16,1,12],[2023,1,12,0,0,18,1,7],[2024,1,12,83.3,10,12,1,1],[2024,1,20,null,null,null,2,1],[2022,1,20,null,null,null,2,12],[2023,1,20,null,null,null,2,7],[2023,1,21,0,0,40,0,7],[2024,1,21,27,10,37,0,1],[2022,1,21,25,12,48,0,12],[2023,2,0,-270.1,null,16,1,10],[2024,2,0,-198.6,null,21,1,2],[2022,2,0,null,null,8,2,15],[2024,2,14,null,null,1,2,2],[2023,2,14,null,null,1,2,10],[2022,2,15,null,null,1,2,15],[2022,2,2,null,null,1,2,15],[2023,2,2,null,null,2,2,10],[2024,2,2,null,null,5,2,2],[2024,2,3,null,null,2,2,2],[2023,2,3,null,null,2,2,10],[2022,2,3,null,null,1,2,15],[2022,2,4,null,null,7,2,15],[2023,2,4,-280.7,null,15,1,10],[2024,2,4,-190.5,null,14,1,2],[2024,2,5,null,null,1,2,2],[2023,2,5,null,null,0,3,10],[2023,2,17,null,null,5,2,10],[2024,2,17,-225.5,null,11,1,2],[2022,2,17,null,null,1,2,15],[2024,2,6,null,null,1,2,2],[2024,2,7,null,null,1,2,2],[2023,2,7,null,null,2,2,10],[2024,2,9,null,null,3,2,2],[2024,2,10,-115.9,null,13,1,2],[2023,2,10,null,null,4,2,10],[2022,2,10,null,null,5,2,15],[2022,2,11,null,null,4,2,15],[2023,2,11,-261.1,null,14,1,10],[2024,2,11,-198.6,null,19,1,2],[2024,2,12,null,null,3,2,2],[2023,2,12,null,null,4,2,10],[2022,2,12,null,null,1,2,15],[2023,2,20,null,null,1,2,10],[2024,2,20,null,null,1,2,2],[2024,2,21,null,null,9,2,2],[2023,2,21,null,null,10,2,10],[2022,2,21,null,null,4,2,15],[2022,3,13,null,null,null,2,14],[2024,3,13,null,null,null,2,5],[2023,3,13,null,null,null,2,9],[2023,3,0,32.4,12,37,0,9],[2022,3,0,23.2,16,69,0,14],[2024,3,0,20.4,10,49,0,5],[2024,3,14,null,null,null,2,5],[2023,3,14,null,null,null,2,9],[2022,3,14,null,null,null,2,14],[2022,3,15,null,null,null,2,14],[2024,3,15,null,null,null,2,5],[2023,3,15,null,null,null,2,9],[2023,3,2,null,null,null,2,9],[2022,3,2,null,null,null,2,14],[2024,3,2,null,null,null,2,5],[2024,3,22,10.5,2,19,1,5],[2023,3,22,26.7,4,15,1,9],[2022,3,22,9.7,3,31,0,14],[2022,3,16,null,null,null,2,14],[2024,3,16,null,null,null,2,5],[2023,3,16,null,null,null,2,9],[2023,3,5,null,null,null,2,9],[2022,3,5,null,null,null,2,14],[2024,3,5,null,null,null,2,5],[2024,3,17,9.1,1,11,1,5],[2023,3,17,null,null,null,2,9],[2022,3,17,34.6,9,26,1,14],[2022,3,6,null,null,null,2,14],[2024,3,6,null,null,null,2,5],[2023,3,6,null,null,null,2,9],[2023,3,23,36.4,8,22,1,9],[2022,3,23,34.2,13,38,0,14],[2024,3,23,24.1,7,29,1,5],[2024,3,8,null,null,null,2,5],[2023,3,8,null,null,null,2,9],[2022,3,8,null,null,null,2,14],[2024,3,25,null,null,null,2,5],[2024,3,18,null,null,null,2,5],[2022,3,18,null,null,null,2,14],[2023,3,18,null,null,null,2,9],[2023,3,19,45.5,5,11,1,9],[2024,3,19,null,null,null,2,5],[2022,3,19,null,null,null,2,14],[2022,3,11,24.1,13,54,0,14],[2023,3,11,33.3,10,30,0,9],[2024,3,11,22.2,10,45,0,5],[2024,3,12,null,null,null,2,5],[2022,3,12,null,null,null,2,14],[2023,3,12,null,null,null,2,9],[2023,3,20,null,null,null,2,9],[2024,3,20,null,null,null,2,5],[2022,3,20,null,null,null,2,14],[2022,3,21,13.8,4,29,1,14],[2023,3,21,25,4,16,1,9],[2024,3,21,25.9,7,27,1,5],[2024,4,13,null,null,null,2,5],[2022,4,13,null,null,null,2,14],[2023,4,13,null,null,null,2,9],[2023,4,0,67.6,25,37,0,9],[2024,4,0,79.6,39,49,0,5],[2022,4,0,76.8,53,69,0,14],[2022,4,14,null,null,null,2,14],[2023,4,14,null,null,null,2,9],[2024,4,14,null,null,null,2,5],[2024,4,15,null,null,null,2,5],[2022,4,15,null,null,null,2,14],[2023,4,15,null,null,null,2,9],[2023,4,2,null,null,null,2,9],[2024,4,2,null,null,null,2,5],[2022,4,2,null,null,null,2,14],[2022,4,22,90.3,28,31,0,14],[2023,4,22,73.3,11,15,1,9],[2024,4,22,89.5,17,19,1,5],[2024,4,16,null,null,null,2,5],[2022,4,16,null,null,null,2,14],[2023,4,16,null,null,null,2,9],[2023,4,5,null,null,null,2,9],[2024,4,5,null,null,null,2,5],[2022,4,5,null,null,null,2,14],[2022,4,17,65.4,17,26,1,14],[2023,4,17,null,null,null,2,9],[2024,4,17,90.9,10,11,1,5],[2024,4,6,null,null,null,2,5],[2022,4,6,null,null,null,2,14],[2023,4,6,null,null,null,2,9],[2023,4,23,63.6,14,22,1,9],[2024,4,23,75.9,22,29,1,5],[2022,4,23,65.8,25,38,0,14],[2022,4,8,null,null,null,2,14],[2023,4,8,null,null,null,2,9],[2024,4,8,null,null,null,2,5],[2024,4,25,null,null,null,2,5],[2024,4,18,null,null,null,2,5],[2022,4,18,null,null,null,2,14],[2023,4,18,null,null,null,2,9],[2023,4,19,54.5,6,11,1,9],[2024,4,19,null,null,null,2,5],[2022,4,19,null,null,null,2,14],[2022,4,11,75.9,41,54,0,14],[2023,4,11,66.7,20,30,0,9],[2024,4,11,77.8,35,45,0,5],[2024,4,12,null,null,null,2,5],[2022,4,12,null,null,null,2,14],[2023,4,12,null,null,null,2,9],[2023,4,20,null,null,null,2,9],[2024,4,20,null,null,null,2,5],[2022,4,20,null,null,null,2,14],[2022,4,21,86.2,25,29,1,14],[2023,4,21,75,12,16,1,9],[2024,4,21,74.1,20,27,1,5],[2024,5,0,-247.5,null,19,1,3],[2022,5,0,null,null,8,2,16],[2023,5,0,-313.8,null,16,1,11],[2023,5,14,null,null,1,2,11],[2024,5,14,null,null,1,2,3],[2022,5,15,null,null,1,2,16],[2022,5,2,null,null,1,2,16],[2023,5,2,null,null,2,2,11],[2024,5,2,null,null,5,2,3],[2024,5,3,null,null,2,2,3],[2022,5,3,null,null,1,2,16],[2023,5,3,null,null,2,2,11],[2023,5,4,-311.5,null,15,1,11],[2024,5,4,-252.5,null,12,1,3],[2022,5,4,null,null,7,2,16],[2023,5,5,null,null,0,3,11],[2024,5,5,null,null,1,2,3],[2024,5,17,-278.5,null,11,1,3],[2022,5,17,null,null,1,2,16],[2023,5,17,null,null,5,2,11],[2024,5,6,null,null,1,2,3],[2024,5,7,null,null,1,2,3],[2023,5,7,null,null,2,2,11],[2024,5,9,null,null,3,2,3],[2024,5,10,-201.1,null,13,1,3],[2023,5,10,null,null,3,2,11],[2022,5,10,null,null,5,2,16],[2022,5,11,null,null,4,2,16],[2024,5,11,-247.6,null,17,1,3],[2023,5,11,-308.9,null,14,1,11],[2023,5,12,null,null,4,2,11],[2022,5,12,null,null,1,2,16],[2024,5,12,null,null,3,2,3],[2024,5,20,null,null,1,2,3],[2023,5,20,null,null,1,2,11],[2023,5,21,null,null,10,2,11],[2024,5,21,null,null,7,2,3],[2022,5,21,null,null,4,2,16],[2023,6,13,null,null,null,2,8],[2022,6,13,null,null,null,2,13],[2024,6,13,null,null,null,2,4],[2024,6,0,1,1,97,0,4],[2023,6,0,4.4,4,91,0,8],[2022,6,0,9.4,10,106,0,13],[2022,6,14,null,null,null,2,13],[2024,6,14,null,null,null,2,4],[2023,6,14,null,null,null,2,8],[2023,6,15,null,null,null,2,8],[2022,6,15,null,null,null,2,13],[2024,6,15,null,null,null,2,4],[2024,6,2,null,null,null,2,4],[2023,6,2,null,null,null,2,8],[2022,6,2,null,null,null,2,13],[2022,6,22,14.3,7,49,0,13],[2024,6,22,2.3,1,44,0,4],[2023,6,22,5.6,2,36,0,8],[2023,6,16,null,null,null,2,8],[2022,6,16,null,null,null,2,13],[2024,6,16,null,null,null,2,4],[2024,6,5,null,null,null,2,4],[2023,6,5,null,null,null,2,8],[2022,6,5,null,null,null,2,13],[2022,6,17,12.5,4,32,0,13],[2024,6,17,0,0,30,0,4],[2023,6,17,4,1,25,1,8],[2023,6,6,null,null,null,2,8],[2022,6,6,null,null,null,2,13],[2024,6,6,null,null,null,2,4],[2024,6,23,0,0,52,0,4],[2023,6,23,3.8,2,53,0,8],[2022,6,23,5.5,3,55,0,13],[2022,6,8,null,null,null,2,13],[2024,6,8,null,null,null,2,4],[2023,6,8,null,null,null,2,8],[2023,6,25,null,null,null,2,8],[2022,6,25,null,null,null,2,13],[2024,6,25,null,null,null,2,4],[2024,6,18,null,null,null,2,4],[2023,6,18,null,null,null,2,8],[2022,6,18,null,null,null,2,13],[2022,6,19,7.1,1,14,1,13],[2024,6,19,null,null,null,2,4],[2023,6,19,7.1,1,14,1,8],[2023,6,11,3.1,2,65,0,8],[2022,6,11,11,8,73,0,13],[2024,6,11,1.3,1,78,0,4],[2024,6,12,0,0,15,1,4],[2023,6,12,10.5,2,19,1,8],[2022,6,12,12.5,2,16,1,13],[2022,6,20,null,null,null,2,13],[2024,6,20,null,null,null,2,4],[2023,6,20,null,null,null,2,8],[2023,6,21,2.4,1,42,0,8],[2022,6,21,4,2,50,0,13],[2024,6,21,2.4,1,42,0,4]]},"23656232335487":{"demographics":{"African American":{"count":5,"percent":1.2},"American Indian":{"count":34,"percent":8.3},"Asian":{"count":3,"percent":0.7},"English Learner":{"count":26,"percent":6.4},"Filipino":{"count":1,"percent":0.2},"Foster":{"count":4,"percent":1.0},"Free/Reduced Meal Eligible":{"count":198,"percent":48.4},"Hispanic":{"count":141,"percent":34.5},"Homeless":{"count":4,"percent":1.0},"Migrant":{"count":12,"percent":2.9},"Not Reported":{"count":56,"percent":13.7},"Pacific Islander":{"count":1,"percent":0.2},"Socioeconomically Disadvantaged":{"count":211,"percent":51.6},"Students with Disabilities":{"count":81,"percent":19.8},"Two or More Races":{"count":21,"percent":5.1},"White":{"count":147,"percent":35.9}},"observations":[[2024,0,13,null,null,null,2,5],[2023,0,13,null,null,null,2,9],[2022,0,13,null,null,null,2,14],[2022,0,0,31.3,25,80,0,14],[2023,0,0,46.1,35,76,0,9],[2024,0,0,45.1,32,71,0,5],[2024,0,14,null,null,null,2,5],[2023,0,14,null,null,null,2,9],[2022,0,14,null,null,null,2,14],[2022,0,15,null,null,null,2,14],[2023,0,15,null,null,null,2,9],[2024,0,15,null,null,null,2,5],[2024,0,2,null,null,null,2,5],[2023,0,2,null,null,null,2,9],[2022,0,2,10,1,10,1,14],[2022,0,22,39,16,41,0,14],[2023,0,22,65.7,23,35,0,9],[2024,0,22,54.5,18,33,0,5],[2024,0,16,null,null,null,2,5],[2023,0,16,null,null,null,2,9],[2022,0,16,null,null,null,2,14],[2022,0,5,null,null,null,2,14],[2023,0,5,null,null,null,2,9],[2023,0,17,50,12,24,1,9],[2022,0,17,32.3,10,31,0,14],[2024,0,17,45.2,14,31,0,5],[2024,0,6,null,null,null,2,5],[2022,0,6,null,null,null,2,14],[2023,0,6,null,null,null,2,9],[2023,0,23,29.3,12,41,0,9],[2022,0,23,23.1,9,39,0,14],[2024,0,23,34.3,12,35,0,5],[2024,0,8,53.8,7,13,1,5],[2022,0,8,28.6,4,14,1,14],[2023,0,8,null,null,null,2,9],[2024,0,25,null,null,null,2,5],[2024,0,18,null,null,null,2,5],[2023,0,18,null,null,null,2,9],[2022,0,18,null,null,null,2,14],[2022,0,19,18.2,2,11,1,14],[2023,0,19,45.5,5,11,1,9],[2024,0,19,null,null,null,2,5],[2024,0,11,43.9,18,41,0,5],[2023,0,11,54.2,26,48,0,9],[2022,0,11,28.6,16,56,0,14],[2022,0,12,6.7,1,15,1,14],[2023,0,12,0,0,10,1,9],[2024,0,12,10,1,10,1,5],[2024,0,20,null,null,null,2,5],[2023,0,20,null,null,null,2,9],[2022,0,20,null,null,null,2,14],[2022,0,21,34.6,9,26,0,14],[2023,0,21,43.3,13,30,0,9],[2024,0,21,37.9,11,29,0,5],[2023,1,13,null,null,null,2,7],[2022,1,13,null,null,null,2,12],[2024,1,13,null,null,null,2,1],[2024,1,0,42.7,176,412,0,1],[2022,1,0,40.1,171,426,0,12],[2023,1,0,37.7,163,432,0,7],[2023,1,14,20.7,6,29,1,7],[2022,1,14,26.5,9,34,0,12],[2024,1,14,35.3,12,34,0,1],[2024,1,15,null,null,null,2,1],[2022,1,15,null,null,null,2,12],[2023,1,15,null,null,null,2,7],[2023,1,2,28.9,11,38,0,7],[2022,1,2,32.7,17,52,0,12],[2024,1,2,47.2,17,36,0,1],[2024,1,22,41.6,77,185,0,1],[2022,1,22,35.4,70,198,0,12],[2023,1,22,37.7,75,199,0,7],[2023,1,16,null,null,null,2,7],[2022,1,16,null,null,null,2,12],[2024,1,16,null,null,null,2,1],[2024,1,5,null,null,null,2,1],[2022,1,5,null,null,null,2,12],[2023,1,5,null,null,null,2,7],[2023,1,28,null,null,null,2,7],[2023,1,29,37.6,162,431,0,7],[2022,1,29,40.1,171,426,0,12],[2024,1,29,42.7,176,412,0,1],[2023,1,30,null,null,null,2,7],[2023,1,17,32.9,49,149,0,7],[2024,1,17,39.7,58,146,0,1],[2022,1,17,34.5,51,148,0,12],[2022,1,6,null,null,null,2,12],[2024,1,6,null,null,null,2,1],[2023,1,6,null,null,null,2,7],[2023,1,23,37.4,86,230,0,7],[2024,1,23,43,95,221,0,1],[2022,1,23,44.2,99,224,0,12],[2022,1,8,24,12,50,0,12],[2024,1,8,34.9,15,43,0,1],[2023,1,8,30,15,50,0,7],[2023,1,25,null,null,null,2,7],[2024,1,25,null,null,null,2,1],[2022,1,25,null,null,null,2,12],[2022,1,18,null,null,null,2,12],[2024,1,18,null,null,null,2,1],[2023,1,18,null,null,null,2,7],[2023,1,19,50,34,68,0,7],[2024,1,19,50,24,48,0,1],[2022,1,19,46.8,29,62,0,12],[2022,1,11,45.3,112,247,0,12],[2024,1,11,49,120,245,0,1],[2023,1,11,43,107,249,0,7],[2023,1,12,51.2,43,84,0,7],[2024,1,12,62.5,50,80,0,1],[2022,1,12,56.5,39,69,0,12],[2022,1,20,null,null,null,2,12],[2024,1,20,52.9,9,17,1,1],[2023,1,20,57.1,8,14,1,7],[2023,1,21,39.3,64,163,0,7],[2024,1,21,46.5,72,155,0,1],[2022,1,21,45.6,77,169,0,12],[2024,2,13,null,null,1,2,2],[2024,2,0,-90.9,null,86,0,2],[2023,2,0,-61.4,null,77,0,10],[2022,2,0,-72.3,null,79,0,15],[2023,2,1,null,null,3,2,10],[2024,2,1,null,null,2,2,2],[2024,2,14,-83.8,null,11,1,2],[2023,2,14,null,null,5,2,10],[2022,2,14,null,null,5,2,15],[2022,2,15,null,null,1,2,15],[2023,2,15,null,null,2,2,10],[2023,2,2,null,null,8,2,10],[2022,2,2,null,null,9,2,15],[2024,2,2,-78.1,null,14,1,2],[2024,2,3,null,null,3,2,2],[2022,2,3,null,null,8,2,15],[2023,2,3,null,null,5,2,10],[2023,2,4,-54.9,null,55,0,10],[2022,2,4,-80,null,60,0,15],[2024,2,4,-96.8,null,64,0,2],[2024,2,5,null,null,1,2,2],[2024,2,17,-93.5,null,30,0,2],[2022,2,17,-79.8,null,26,1,15],[2023,2,17,-72.7,null,30,0,10],[2023,2,6,null,null,2,2,10],[2024,2,6,null,null,1,2,2],[2024,2,7,null,null,5,2,2],[2023,2,7,null,null,2,2,10],[2024,2,18,null,null,1,2,2],[2024,2,9,-62.7,null,11,1,2],[2023,2,9,null,null,3,2,10],[2022,2,9,null,null,1,2,15],[2022,2,10,-47,null,72,0,15],[2023,2,10,-62.7,null,74,0,10],[2024,2,10,-94.2,null,84,0,2],[2024,2,11,-107.4,null,43,0,2],[2023,2,11,-70,null,41,0,10],[2022,2,11,-75.4,null,40,0,15],[2022,2,12,null,null,9,2,15],[2023,2,12,-143.5,null,15,1,10],[2024,2,12,-146.5,null,13,1,2],[2024,2,20,null,null,3,2,2],[2022,2,20,null,null,2,2,15],[2022,2,21,-78.8,null,34,0,15],[2024,2,21,-89.8,null,30,0,2],[2023,2,21,-60,null,30,0,10],[2023,3,13,null,null,null,2,9],[2024,3,13,null,null,null,2,5],[2022,3,13,null,null,null,2,14],[2022,3,0,10.1,9,89,0,14],[2024,3,0,11.3,9,80,0,5],[2023,3,0,8.4,7,83,0,9],[2023,3,14,null,null,null,2,9],[2024,3,14,null,null,null,2,5],[2022,3,14,null,null,null,2,14],[2022,3,15,null,null,null,2,14],[2024,3,15,null,null,null,2,5],[2023,3,15,null,null,null,2,9],[2023,3,2,null,null,null,2,9],[2024,3,2,null,null,null,2,5],[2022,3,2,9.1,1,11,1,14],[2022,3,22,12.8,6,47,0,14],[2024,3,22,2.9,1,34,0,5],[2023,3,22,5.4,2,37,0,9],[2023,3,16,null,null,null,2,9],[2024,3,16,null,null,null,2,5],[2022,3,16,null,null,null,2,14],[2022,3,5,null,null,null,2,14],[2023,3,5,null,null,null,2,9],[2023,3,17,4,1,25,1,9],[2022,3,17,8.8,3,34,0,14],[2024,3,17,3.1,1,32,0,5],[2024,3,6,null,null,null,2,5],[2022,3,6,null,null,null,2,14],[2023,3,6,null,null,null,2,9],[2023,3,23,10.9,5,46,0,9],[2022,3,23,7.1,3,42,0,14],[2024,3,23,18.6,8,43,0,5],[2024,3,8,0,0,13,1,5],[2022,3,8,0,0,14,1,14],[2023,3,8,null,null,null,2,9],[2024,3,25,null,null,null,2,5],[2024,3,18,null,null,null,2,5],[2023,3,18,null,null,null,2,9],[2022,3,18,null,null,null,2,14],[2022,3,19,8.3,1,12,1,14],[2023,3,19,21.4,3,14,1,9],[2024,3,19,null,null,null,2,5],[2024,3,11,14.6,7,48,0,5],[2023,3,11,7.7,4,52,0,9],[2022,3,11,11.1,7,63,0,14],[2022,3,12,16.7,3,18,1,14],[2023,3,12,9.1,1,11,1,9],[2024,3,12,33.3,5,15,1,5],[2024,3,20,null,null,null,2,5],[2023,3,20,null,null,null,2,9],[2022,3,20,null,null,null,2,14],[2022,3,21,16.1,5,31,0,14],[2023,3,21,9.1,3,33,0,9],[2024,3,21,9.4,3,32,0,5],[2024,4,13,null,null,null,2,5],[2023,4,13,null,null,null,2,9],[2022,4,13,null,null,null,2,14],[2022,4,0,89.9,80,89,0,14],[2023,4,0,91.6,76,83,0,9],[2024,4,0,88.8,71,80,0,5],[2024,4,14,null,null,null,2,5],[2023,4,14,null,null,null,2,9],[2022,4,14,null,null,null,2,14],[2022,4,15,null,null,null,2,14],[2023,4,15,null,null,null,2,9],[2024,4,15,null,null,null,2,5],[2024,4,2,null,null,null,2,5],[2023,4,2,null,null,null,2,9],[2022,4,2,90.9,10,11,1,14],[2022,4,22,87.2,41,47,0,14],[2023,4,22,94.6,35,37,0,9],[2024,4,22,97.1,33,34,0,5],[2024,4,16,null,null,null,2,5],[2023,4,16,null,null,null,2,9],[2022,4,16,null,null,null,2,14],[2022,4,5,null,null,null,2,14],[2023,4,5,null,null,null,2,9],[2023,4,17,96,24,25,1,9],[2022,4,17,91.2,31,34,0,14],[2024,4,17,96.9,31,32,0,5],[2024,4,6,null,null,null,2,5],[2022,4,6,null,null,null,2,14],[2023,4,6,null,null,null,2,9],[2023,4,23,89.1,41,46,0,9],[2022,4,23,92.9,39,42,0,14],[2024,4,23,81.4,35,43,0,5],[2024,4,8,100,13,13,1,5],[2022,4,8,100,14,14,1,14],[2023,4,8,null,null,null,2,9],[2024,4,25,null,null,null,2,5],[2024,4,18,null,null,null,2,5],[2023,4,18,null,null,null,2,9],[2022,4,18,null,null,null,2,14],[2022,4,19,91.7,11,12,1,14],[2023,4,19,78.6,11,14,1,9],[2024,4,19,null,null,null,2,5],[2024,4,11,85.4,41,48,0,5],[2023,4,11,92.3,48,52,0,9],[2022,4,11,88.9,56,63,0,14],[2022,4,12,83.3,15,18,1,14],[2023,4,12,90.9,10,11,1,9],[2024,4,12,66.7,10,15,1,5],[2024,4,20,null,null,null,2,5],[2023,4,20,null,null,null,2,9],[2022,4,20,null,null,null,2,14],[2022,4,21,83.9,26,31,0,14],[2023,4,21,90.9,30,33,0,9],[2024,4,21,90.6,29,32,0,5],[2024,5,13,null,null,1,2,3],[2024,5,0,-157.7,null,87,0,3],[2023,5,0,-122.3,null,78,0,11],[2022,5,0,-141.5,null,80,0,16],[2023,5,1,null,null,3,2,11],[2024,5,1,null,null,2,2,3],[2024,5,14,-170.9,null,11,1,3],[2023,5,14,null,null,5,2,11],[2022,5,14,null,null,5,2,16],[2022,5,15,null,null,1,2,16],[2023,5,15,null,null,2,2,11],[2023,5,2,null,null,8,2,11],[2022,5,2,null,null,9,2,16],[2024,5,2,-171.9,null,15,1,3],[2024,5,3,null,null,4,2,3],[2022,5,3,null,null,8,2,16],[2023,5,3,null,null,5,2,11],[2023,5,4,-120.8,null,56,0,11],[2022,5,4,-145.7,null,61,0,16],[2024,5,4,-152.5,null,64,0,3],[2024,5,5,null,null,1,2,3],[2024,5,17,-165.3,null,31,0,3],[2022,5,17,-150.3,null,26,1,16],[2023,5,17,-125.7,null,30,0,11],[2023,5,6,null,null,2,2,11],[2024,5,6,null,null,1,2,3],[2024,5,7,null,null,5,2,3],[2023,5,7,null,null,2,2,11],[2024,5,18,null,null,1,2,3],[2024,5,9,-164.8,null,11,1,3],[2023,5,9,null,null,3,2,11],[2022,5,9,null,null,1,2,16],[2022,5,10,-124.7,null,74,0,16],[2023,5,10,-126.1,null,75,0,11],[2024,5,10,-161.3,null,85,0,3],[2024,5,11,-170.3,null,44,0,3],[2023,5,11,-129,null,41,0,11],[2022,5,11,-147.3,null,41,0,16],[2022,5,12,null,null,9,2,16],[2023,5,12,-188.9,null,15,1,11],[2024,5,12,-218.3,null,13,1,3],[2024,5,20,null,null,3,2,3],[2022,5,20,null,null,3,2,16],[2022,5,21,-151.7,null,34,0,16],[2024,5,21,-163,null,30,0,3],[2023,5,21,-117.1,null,31,0,11],[2024,6,13,null,null,null,2,4],[2022,6,13,null,null,null,2,13],[2023,6,13,null,null,null,2,8],[2023,6,0,10.6,48,452,0,8],[2022,6,0,13,58,447,0,13],[2024,6,0,11.5,49,426,0,4],[2024,6,14,5.7,2,35,0,4],[2022,6,14,8.8,3,34,0,13],[2023,6,14,3.2,1,31,0,8],[2023,6,15,null,null,null,2,8],[2022,6,15,null,null,null,2,13],[2024,6,15,null,null,null,2,4],[2024,6,2,16.2,6,37,0,4],[2022,6,2,7.5,4,53,0,13],[2023,6,2,10.5,4,38,0,8],[2023,6,22,9,19,210,0,8],[2022,6,22,11,23,209,0,13],[2024,6,22,5.2,10,192,0,4],[2024,6,16,null,null,null,2,4],[2022,6,16,null,null,null,2,13],[2023,6,16,null,null,null,2,8],[2023,6,5,null,null,null,2,8],[2022,6,5,null,null,null,2,13],[2024,6,5,null,null,null,2,4],[2024,6,17,13.7,21,153,0,4],[2022,6,17,9.2,14,153,0,13],[2023,6,17,10.5,16,152,0,8],[2023,6,6,null,null,null,2,8],[2022,6,6,null,null,null,2,13],[2024,6,6,null,null,null,2,4],[2024,6,23,17.1,39,228,0,4],[2022,6,23,15,35,234,0,13],[2023,6,23,12.1,29,239,0,8],[2023,6,8,0,0,51,0,8],[2022,6,8,6,3,50,0,13],[2024,6,8,6.8,3,44,0,4],[2024,6,25,null,null,null,2,4],[2022,6,25,null,null,null,2,13],[2023,6,25,null,null,null,2,8],[2023,6,18,null,null,null,2,8],[2022,6,18,null,null,null,2,13],[2024,6,18,null,null,null,2,4],[2024,6,19,14,7,50,0,4],[2022,6,19,21,13,62,0,13],[2023,6,19,17.6,12,68,0,8],[2023,6,11,10.2,27,264,0,8],[2022,6,11,12.4,32,258,0,13],[2024,6,11,12.1,31,257,0,4],[2024,6,12,19.3,16,83,0,4],[2022,6,12,10.7,8,75,0,13],[2023,6,12,15.5,13,84,0,8],[2023,6,20,17.6,3,17,1,8],[2022,6,20,null,null,null,2,13],[2024,6,20,11.1,2,18,1,4],[2024,6,21,9.5,15,158,0,4],[2022,6,21,14.1,26,184,0,13],[2023,6,21,8,14,175,0,8]]},"23752182330207":{"demographics":{"African American":{"count":0,"percent":0.0},"American Indian":{"count":0,"percent":0.0},"Asian":{"count":0,"percent":0.0},"English Learner":{"count":1,"percent":14.3},"Filipino":{"count":0,"percent":0.0},"Foster":{"count":0,"percent":0.0},"Free/Reduced Meal Eligible":{"count":3,"percent":42.9},"Hispanic":{"count":3,"percent":42.9},"Homeless":{"count":0,"percent":0.0},"Migrant":{"count":0,"percent":0.0},"Not Reported":{"count":0,"percent":0.0},"Pacific Islander":{"count":0,"percent":0.0},"Socioeconomically Disadvantaged":{"count":3,"percent":42.9},"Students with Disabilities":{"count":1,"percent":14.3},"Two or More Races":{"count":1,"percent":14.3},"White":{"count":3,"percent":42.9}},"observations":[[2022,0,13,null,null,null,2,14],[2023,0,13,null,null,null,2,9],[2024,0,13,null,null,null,2,5],[2024,0,0,null,null,null,2,5],[2022,0,0,null,null,null,2,14],[2023,0,0,null,null,null,2,9],[2023,0,14,null,null,null,2,9],[2024,0,14,null,null,null,2,5],[2022,0,14,null,null,null,2,14],[2022,0,15,null,null,null,2,14],[2023,0,15,null,null,null,2,9],[2024,0,15,null,null,null,2,5],[2023,0,2,null,null,null,2,9],[2023,0,22,null,null,null,2,9],[2022,0,22,null,null,null,2,14],[2024,0,22,null,null,null,2,5],[2024,0,16,null,null,null,2,5],[2023,0,16,null,null,null,2,9],[2022,0,16,null,null,null,2,14],[2022,0,17,null,null,null,2,14],[2024,0,17,null,null,null,2,5],[2023,0,17,null,null,null,2,9],[2023,0,23,null,null,null,2,9],[2022,0,23,null,null,null,2,14],[2024,0,23,null,null,null,2,5],[2022,0,25,null,null,null,2,14],[2022,0,18,null,null,null,2,14],[2023,0,18,null,null,null,2,9],[2024,0,18,null,null,null,2,5],[2024,0,19,null,null,null,2,5],[2022,0,19,null,null,null,2,14],[2023,0,19,null,null,null,2,9],[2023,0,11,null,null,null,2,9],[2024,0,11,null,null,null,2,5],[2022,0,11,null,null,null,2,14],[2022,0,12,null,null,null,2,14],[2024,0,12,null,null,null,2,5],[2024,0,20,null,null,null,2,5],[2023,0,20,null,null,null,2,9],[2022,0,20,null,null,null,2,14],[2022,0,21,null,null,null,2,14],[2024,0,21,null,null,null,2,5],[2023,0,21,null,null,null,2,9],[2022,1,13,null,null,null,2,12],[2023,1,13,null,null,null,2,7],[2024,1,13,null,null,null,2,1],[2024,1,0,null,null,null,2,1],[2022,1,0,45.5,5,11,1,12],[2023,1,0,null,null,null,2,7],[2023,1,14,null,null,null,2,7],[2024,1,14,null,null,null,2,1],[2022,1,14,null,null,null,2,12],[2022,1,15,null,null,null,2,12],[2023,1,15,null,null,null,2,7],[2024,1,15,null,null,null,2,1],[2022,1,2,null,null,null,2,12],[2023,1,2,null,null,null,2,7],[2023,1,22,null,null,null,2,7],[2024,1,22,null,null,null,2,1],[2022,1,22,null,null,null,2,12],[2022,1,16,null,null,null,2,12],[2023,1,16,null,null,null,2,7],[2024,1,16,null,null,null,2,1],[2024,1,29,null,null,null,2,1],[2022,1,29,45.5,5,11,1,12],[2023,1,29,null,null,null,2,7],[2023,1,17,null,null,null,2,7],[2024,1,17,null,null,null,2,1],[2022,1,17,null,null,null,2,12],[2022,1,23,null,null,null,2,12],[2023,1,23,null,null,null,2,7],[2024,1,23,null,null,null,2,1],[2022,1,25,null,null,null,2,12],[2022,1,18,null,null,null,2,12],[2024,1,18,null,null,null,2,1],[2023,1,18,null,null,null,2,7],[2023,1,19,null,null,null,2,7],[2022,1,19,null,null,null,2,12],[2024,1,19,null,null,null,2,1],[2024,1,11,null,null,null,2,1],[2023,1,11,null,null,null,2,7],[2022,1,11,null,null,null,2,12],[2022,1,12,null,null,null,2,12],[2024,1,12,null,null,null,2,1],[2023,1,12,null,null,null,2,7],[2023,1,20,null,null,null,2,7],[2022,1,20,null,null,null,2,12],[2024,1,20,null,null,null,2,1],[2024,1,21,null,null,null,2,1],[2023,1,21,null,null,null,2,7],[2022,1,21,null,null,null,2,12],[2022,2,13,null,null,1,2,15],[2022,2,0,null,null,2,2,15],[2024,2,0,null,null,1,2,2],[2023,2,0,null,null,3,2,10],[2023,2,14,null,null,1,2,10],[2023,2,2,null,null,1,2,10],[2022,2,2,null,null,1,2,15],[2022,2,3,null,null,1,2,15],[2023,2,3,null,null,1,2,10],[2023,2,4,null,null,2,2,10],[2022,2,4,null,null,1,2,15],[2024,2,4,null,null,1,2,2],[2022,2,17,null,null,1,2,15],[2023,2,17,null,null,1,2,10],[2023,2,7,null,null,1,2,10],[2023,2,10,null,null,3,2,10],[2022,2,10,null,null,1,2,15],[2024,2,10,null,null,1,2,2],[2024,2,11,null,null,1,2,2],[2023,2,11,null,null,2,2,10],[2023,2,12,null,null,1,2,10],[2022,2,12,null,null,1,2,15],[2024,2,20,null,null,1,2,2],[2023,2,21,null,null,1,2,10],[2023,3,13,null,null,null,2,9],[2022,3,13,null,null,null,2,14],[2024,3,13,null,null,null,2,5],[2024,3,0,null,null,null,2,5],[2023,3,0,null,null,null,2,9],[2022,3,0,null,null,null,2,14],[2022,3,14,null,null,null,2,14],[2024,3,14,null,null,null,2,5],[2023,3,14,null,null,null,2,9],[2023,3,15,null,null,null,2,9],[2022,3,15,null,null,null,2,14],[2024,3,15,null,null,null,2,5],[2023,3,2,null,null,null,2,9],[2023,3,22,null,null,null,2,9],[2024,3,22,null,null,null,2,5],[2022,3,22,null,null,null,2,14],[2022,3,16,null,null,null,2,14],[2023,3,16,null,null,null,2,9],[2024,3,16,null,null,null,2,5],[2023,3,17,null,null,null,2,9],[2022,3,17,null,null,null,2,14],[2024,3,17,null,null,null,2,5],[2024,3,23,null,null,null,2,5],[2023,3,23,null,null,null,2,9],[2022,3,23,null,null,null,2,14],[2022,3,25,null,null,null,2,14],[2022,3,18,null,null,null,2,14],[2024,3,18,null,null,null,2,5],[2023,3,18,null,null,null,2,9],[2023,3,19,null,null,null,2,9],[2022,3,19,null,null,null,2,14],[2024,3,19,null,null,null,2,5],[2024,3,11,null,null,null,2,5],[2023,3,11,null,null,null,2,9],[2022,3,11,null,null,null,2,14],[2022,3,12,null,null,null,2,14],[2024,3,12,null,null,null,2,5],[2024,3,20,null,null,null,2,5],[2022,3,20,null,null,null,2,14],[2023,3,20,null,null,null,2,9],[2023,3,21,null,null,null,2,9],[2024,3,21,null,null,null,2,5],[2022,3,21,null,null,null,2,14],[2022,4,13,null,null,null,2,14],[2023,4,13,null,null,null,2,9],[2024,4,13,null,null,null,2,5],[2024,4,0,null,null,null,2,5],[2022,4,0,null,null,null,2,14],[2023,4,0,null,null,null,2,9],[2023,4,14,null,null,null,2,9],[2024,4,14,null,null,null,2,5],[2022,4,14,null,null,null,2,14],[2022,4,15,null,null,null,2,14],[2023,4,15,null,null,null,2,9],[2024,4,15,null,null,null,2,5],[2023,4,2,null,null,null,2,9],[2023,4,22,null,null,null,2,9],[2022,4,22,null,null,null,2,14],[2024,4,22,null,null,null,2,5],[2024,4,16,null,null,null,2,5],[2023,4,16,null,null,null,2,9],[2022,4,16,null,null,null,2,14],[2022,4,17,null,null,null,2,14],[2024,4,17,null,null,null,2,5],[2023,4,17,null,null,null,2,9],[2023,4,23,null,null,null,2,9],[2022,4,23,null,null,null,2,14],[2024,4,23,null,null,null,2,5],[2022,4,25,null,null,null,2,14],[2022,4,18,null,null,null,2,14],[2023,4,18,null,null,null,2,9],[2024,4,18,null,null,null,2,5],[2024,4,19,null,null,null,2,5],[2022,4,19,null,null,null,2,14],[2023,4,19,null,null,null,2,9],[2023,4,11,null,null,null,2,9],[2024,4,11,null,null,null,2,5],[2022,4,11,null,null,null,2,14],[2022,4,12,null,null,null,2,14],[2024,4,12,null,null,null,2,5],[2024,4,20,null,null,null,2,5],[2023,4,20,null,null,null,2,9],[2022,4,20,null,null,null,2,14],[2022,4,21,null,null,null,2,14],[2024,4,21,null,null,null,2,5],[2023,4,21,null,null,null,2,9],[2022,5,13,null,null,1,2,16],[2022,5,0,null,null,2,2,16],[2023,5,0,null,null,3,2,11],[2024,5,0,null,null,1,2,3],[2023,5,14,null,null,1,2,11],[2023,5,2,null,null,1,2,11],[2022,5,2,null,null,1,2,16],[2022,5,3,null,null,1,2,16],[2023,5,3,null,null,1,2,11],[2023,5,4,null,null,2,2,11],[2022,5,4,null,null,1,2,16],[2024,5,4,null,null,1,2,3],[2023,5,17,null,null,1,2,11],[2022,5,17,null,null,1,2,16],[2023,5,7,null,null,1,2,11],[2023,5,10,null,null,3,2,11],[2024,5,10,null,null,1,2,3],[2022,5,10,null,null,1,2,16],[2023,5,11,null,null,2,2,11],[2024,5,11,null,null,1,2,3],[2022,5,12,null,null,1,2,16],[2023,5,12,null,null,1,2,11],[2024,5,20,null,null,1,2,3],[2023,5,21,null,null,1,2,11],[2024,6,13,null,null,null,2,4],[2022,6,13,null,null,null,2,13],[2023,6,13,null,null,null,2,8],[2023,6,0,0,0,10,1,8],[2024,6,0,0,0,7,1,4],[2022,6,0,0,0,11,1,13],[2022,6,14,null,null,null,2,13],[2023,6,14,null,null,null,2,8],[2024,6,14,null,null,null,2,4],[2024,6,15,null,null,null,2,4],[2022,6,15,null,null,null,2,13],[2023,6,15,null,null,null,2,8],[2023,6,2,null,null,null,2,8],[2022,6,2,null,null,null,2,13],[2022,6,22,null,null,null,2,13],[2024,6,22,null,null,null,2,4],[2023,6,22,null,null,null,2,8],[2023,6,16,null,null,null,2,8],[2022,6,16,null,null,null,2,13],[2024,6,16,null,null,null,2,4],[2024,6,17,null,null,null,2,4],[2023,6,17,null,null,null,2,8],[2022,6,17,null,null,null,2,13],[2022,6,23,null,null,null,2,13],[2024,6,23,null,null,null,2,4],[2023,6,23,null,null,null,2,8],[2022,6,25,null,null,null,2,13],[2022,6,18,null,null,null,2,13],[2023,6,18,null,null,null,2,8],[2024,6,18,null,null,null,2,4],[2024,6,19,null,null,null,2,4],[2022,6,19,null,null,null,2,13],[2023,6,19,null,null,null,2,8],[2023,6,11,null,null,null,2,8],[2024,6,11,null,null,null,2,4],[2022,6,11,null,null,null,2,13],[2022,6,12,null,null,null,2,13],[2023,6,12,null,null,null,2,8],[2024,6,12,null,null,null,2,4],[2024,6,20,null,null,null,2,4],[2022,6,20,null,null,null,2,13],[2023,6,20,null,null,null,2,8],[2023,6,21,null,null,null,2,8],[2024,6,21,null,null,null,2,4],[2022,6,21,null,null,null,2,13]]}},"shard":"23-7"}
